Workbook

Sheet README
B1: Manufacturing Plant Operating Model
B2: Meridian Home Appliances Pvt Ltd (fictional) · Plant 1, Chakan (Pune) · 15 products · 10 raw materials · 10 suppliers · 9 work centres · 12-month plan
B4: 1. What this workbook is
B5: A connected planning model of a mid-size Indian electrical home-appliance plant. Fifteen products (ceiling, pedestal, table and exhaust fans, an air cooler, mixer grinders, a kettle, an induction cooktop, a sandwich maker, a room heater, an immersion rod, an iron and a water pump) are built from ten raw materials bought from ten suppliers. Material flows through a press shop, aluminium die-casting, injection moulding, motor and heating-element winding and a powder-coating line into sub-assembly modules, then three final-assembly lines and packing. Change any blue input and unit costs, margins, material requirements, capacity loads, reorder status and supplier spend all recalculate.
B7: 2. Plant at a glance (live)
B8: Annual production | C8: =TEXT(Products!R18,"#,##0")&" units" -> 2,620,700 units
B9: Revenue (ex-GST) | C9: ="₹ "&TEXT(Products!S18*Assumptions!$B$20/Assumptions!$B$21,"#,##0.0")&" crore" -> ₹ 363.9 crore
B10: Raw-material spend | C10: ="₹ "&TEXT(Spend!M15*Assumptions!$B$20/Assumptions!$B$21,"#,##0.0")&" crore ("&TEXT(Spend!M15/Products!S18,"0.0%")&" of revenue)" -> ₹ 161.6 crore (44.4% of revenue)
B11: Gross margin | C11: =TEXT(Products!Q18,"0.0%")&" (after raw material, bought-out parts and conversion cost)" -> 29.6% (after raw material, bought-out parts and conversion cost)
B12: Peak capacity pressure | C12: =TEXT(MAX(Capacity!R18:R26),"0%")&" peak utilization; "&SUM(Capacity!T18:T26)&" work-centre months above 100%" -> 109% peak utilization; 5 work-centre months above 100%
B13: Model integrity | C13: =Checks!B3 -> ALL 33 CHECKS PASS
B15: 3. How the numbers flow
B16: Cost: Products x BOM -> raw-material cost per unit. Add bought-out parts and conversion cost (Routing minutes x WorkCentres rates) -> standard cost -> margin vs selling price.
B17: Materials: Demand_Plan (units by month) x BOM_Matrix (gross kg per unit, after process yield) -> MRP (kg by month).
B18: Purchasing: MRP x Sourcing split (primary / secondary / sole source) x effective price -> Spend matrix (₹ lakh by supplier and material) -> Suppliers (spend share, watch-list flags).
B19: Capacity: Demand_Plan x Routing minutes / 60 -> load hours by work centre and month -> Capacity (utilization vs effective hours after OEE).
B20: Inventory: MRP usage + weighted lead time + safety days -> reorder point, status (REORDER NOW / WATCH / OK), suggested order quantity and ABC class.
B21: Assurance: Checks proves the totals tie out by two independent routes, and that IDs, shares and ranges are valid.
B23: 4. Sheet guide (click a name to jump)
B24: Sheet | C24: Type | D24: What it holds
B25: Dashboard | C25: Output | D25: KPI tiles, capacity heat map, live takeaways and six charts (revenue by family, utilization, spend by material and supplier, margins, inventory cover).
B26: Assumptions | C26: Input | D26: Global parameters and the demand multiplier lever; thresholds for flags, ABC classes and capacity colours.
B27: Products | C27: Input + calc | D27: 15 products P01-P15: spec, final-assembly line, batch size, bought-out parts, selling price, and the cost / margin / revenue roll-up.
B28: RawMaterials | C28: Input + calc | D28: 10 materials RW01-RW10: specification, yield, safety days, price lever, weighted price and lead time, price basis notes.
B29: Suppliers | C29: Input + calc | D29: 10 suppliers S01-S10: location, type, delivery / quality / financial inputs; spend share and automatic watch-list reasons.
B30: Sourcing | C30: Input + calc | D30: 18 supplier-material links: share of requirement, quoted and effective price, lead time, MOQ, transport; annual volume and spend.
B31: BOM | C31: Input + calc | D31: 102 bill-of-material lines by assembly module: net kg per unit, process yield, gross kg, cost and loss.
B32: BOM_Matrix | C32: Calc | D32: Product x material views of net kg, gross kg and cost per unit, plus cost by assembly module.
B33: WorkCentres | C33: Input + calc | D33: 9 work centres: units, shifts, OEE, cost rate; effective capacity in hours per month.
B34: Routing | C34: Input + calc | D34: Standard minutes per unit at each work centre (including each product's own final-assembly line) and the conversion-cost build-up.
B35: Demand_Plan | C35: Input + calc | D35: Seasonality indices and the 12-month production plan in units, revenue by month and by product family.
... B40: Checks | C40: Output | D40: 33 live integrity checks.
B42: 5. Colour and format conventions
B43: Blue text | C43: Hard-coded input or assumption - safe to change.
B44: Black text | C44: Formula - do not overwrite.
B45: Green text | C45: Value pulled from another sheet.
B46: Yellow fill | C46: Scenario lever (demand multiplier, per-material price change).
B47: Units: money tables are in ₹ lakh (1 lakh = 100,000) and dashboard headline figures in ₹ crore (1 crore = 10,000,000); prices are ex-GST; materials are in kg; time is in minutes per unit or hours per month. Tab colours: blue = input sheets, green = calculation sheets, orange = dashboard, yellow = assumptions, grey = documentation and checks. The heat-map and status colours (red / amber / green / grey) are always paired with text so colour is never the only signal.
B49: 6. Try these what-ifs
B50: • Assumptions!B10: set the demand multiplier to 1.15 - watch the capacity heat map, the reorder list and the supplier spend shares change.
B51: • RawMaterials!H5: enter +20% on copper winding wire (RW04) - see the effect on product margins, plant gross margin and supplier concentration.
B52: • Sourcing!G8:G9: change the copper wire split from 75/25 to 50/50 (keep the two shares adding to 100%) - weighted price, lead time and concentration index update.
B53: • WorkCentres!G6: add a second powder-coating line (units 1 -> 2), or change shifts from 2 to 3 on a final-assembly line, and re-read the Capacity status column.
B54: • Products!O: change a selling price to test price/margin trade-offs; Inventory!E: type a new stock level to see how reorder status flips.
B56: 7. Assumptions and data basis - read before relying on any number
B57: • Fictional by design: the company, all ten supplier names and their ratings are invented. Place names are real Indian industrial locations used only for realism.
B58: • Calculated (live formulas): every cost, margin, requirement, load, utilization, reorder point, spend figure and check. Nothing downstream of the inputs is typed in.
B59: • Engineering estimates (planning values, not measurements): BOM quantities, process yields, routing minutes, OEE, shifts and machine counts, work-centre cost rates, supplier lead times / MOQs / delivery and quality metrics, seasonality, opening stock, on-order quantities and selling prices.
B60: • Price-benchmarked: raw-material base prices are indicative planning rates in ₹ per kg (ex-GST), anchored to public trade listings for CR coil, ADC12 alloy, copper wire, ABS, SS304 sheet and nichrome wire and estimated for CRNGO coil, PP, powder coating and cartons. The listings found were undated or from different months, so they are NOT current quotes - see RawMaterials column P for each basis.
... B71: The structure is generic: replace names and specifications on Products, RawMaterials and Suppliers; set BOM quantities, yields and Sourcing splits; set routing minutes, work-centre counts, shifts and rates; load a forecast and seasonality; then update the inventory snapshot. Formulas, checks, dashboard and charts follow. Keep IDs in the same row order across sheets (the Checks sheet tests this) and add BOM or Sourcing rows directly below the last row of each table.

Sheet Dashboard
A1: =Assumptions!B5&" | "&Assumptions!B6 -> Meridian Home Appliances Pvt Ltd | Plant 1, Chakan (Pune), Maharashtra
A2: ="Plant operating dashboard · plan "&TEXT(Demand_Plan!E5,"mmm-yy")&" to "&TEXT(Demand_Plan!P5,"mmm-yy")&" · stock as of "&TEXT(Assumptions!B7,"dd-mmm-yyyy")&" · fictional company and suppliers, illustrative figures" -> Plant operating dashboard · plan Nov-26 to Oct-27 · stock as of 20-Oct-2026 · fictional company and suppliers, illustrative figures
B4: Annual production | D4: Revenue (ex-GST) | F4: Gross margin | H4: Raw-material spend | J4: Material yield loss | L4: Tightest work centre (peak) | N4: Overloaded work-centre months
B5: =Products!R18 -> 2620700 | D5: =Products!S18*Assumptions!$B$20/Assumptions!$B$21 -> 363.87617 | F5: =Products!Q18 -> 0.29587649 | H5: =Spend!M15*Assumptions!$B$20/Assumptions!$B$21 -> 161.57992 | J5: =MRP!V15 -> 0.11975655 | L5: =MAX(Capacity!R18:R26) -> 1.0877297 | N5: =SUM(Capacity!T18:T26) -> 5
B6: ="units across 15 products" -> units across 15 products | D6: ="₹ "&TEXT(Products!S18,"#,##0")&" lakh" -> ₹ 36,388 lakh | F6: ="₹ "&TEXT(Products!T18*Assumptions!$B$20/Assumptions!$B$21,"#,##0.0")&" cr gross profit" -> ₹ 107.7 cr gross profit | H6: =TEXT(Spend!M15/Products!S18,"0.0%")&" of revenue" -> 44.4% of revenue | J6: =TEXT(MRP!U15/1000,"#,##0")&" tonnes of scrap a year" -> 1,028 tonnes of scrap a year | L6: =INDEX(WorkCentres!$C$2:$C$10,MATCH(INDEX(Capacity!A18:A26,MATCH(MAX(Capacity!R18:R26),Capacity!R18:R26,0)),WorkCentres!$A$2:$A$10,0))&" - "&TEXT(INDEX(Capacity!S18:S26,MATCH(MAX(Capacity!R18:R26),Capacity!R18:R26,0)),"mmm-yy") -> FA-1 Fans & coolers - Apr-27 | N6: ="of "&COUNT(Capacity!E18:P26)&" (9 centres x 12 months)" -> of 108 (9 centres x 12 months)
B8: Suppliers on watch-list | D8: Largest supplier share | F8: Import share of RM spend | H8: Sole-sourced materials | J8: Materials to reorder now | L8: RM stock value | N8: Model integrity checks
B9: =COUNTIF(Suppliers!T2:T11,">0") -> 6 | D9: =MAX(Suppliers!R2:R11) -> 0.32747839 | F9: =SUMIF(Suppliers!S2:S11,"Import",Suppliers!Q2:Q11)/SUM(Suppliers!Q2:Q11) -> 0.04799131 | H9: =COUNTIF(RawMaterials!R2:R11,"Yes") -> 2 | J9: =COUNTIF(Inventory!O5:O14,"REORDER NOW") -> 2 | L9: =Inventory!T15*Assumptions!$B$20/Assumptions!$B$21 -> 7.189056 | N9: =COUNTIF(Checks!C5:C37,"PASS")&" / "&COUNTA(Checks!C5:C37) -> 33 / 33
B10: ="of "&COUNTA(Suppliers!A2:A11)&" suppliers" -> of 10 suppliers | D10: =INDEX(Suppliers!C2:C11,MATCH(MAX(Suppliers!R2:R11),Suppliers!R2:R11,0))&" (share of RM spend)" -> Vadodara Wires (share of RM spend) | F10: =COUNTIF(Suppliers!S2:S11,"Import")&" import supplier(s)" -> 1 import supplier(s) | H10: ="of "&COUNTA(RawMaterials!A2:A11)&" raw materials" -> of 10 raw materials | J10: =COUNTIF(Inventory!O5:O14,"WATCH")&" more on watch" -> 1 more on watch | L10: =TEXT(Inventory!E19,"0")&" days of annual spend" -> 16 days of annual spend | N10: =IF(COUNTIF(Checks!C5:C37,"PASS")=ROWS(Checks!C5:C37),"all checks pass","see Checks sheet") -> all checks pass
B12: What the model says right now (live text)
B13: ="Cost: "&INDEX(Spend!$C$3:$L$3,MATCH(MAX(Spend!$C$16:$L$16),Spend!$C$16:$L$16,0))&" is the biggest cost line at "&TEXT(MAX(Spend!$C$16:$L$16),"0%")&" of raw-material spend, and "&INDEX(Suppliers!$C$2:$C$11,MATCH(MAX(Suppliers!$R$2:$R$11),Suppliers!$R$2:$R$11,0))&" alone supplies "&TEXT(MAX(Suppliers!$R$2:$R$11),"0%")&" of the total - a price or delivery shock there moves the plant margin." -> Cost: Copper winding wire is the biggest cost line at 41% of raw-material spend, and Vadodara Wires alone supplies 33% of the total - a price or delivery shock there moves the plant margin.
B14: ="Capacity: "&INDEX(WorkCentres!$C$2:$C$10,MATCH(INDEX(Capacity!$A$18:$A$26,MATCH(MAX(Capacity!$R$18:$R$26),Capacity!$R$18:$R$26,0)),WorkCentres!$A$2:$A$10,0))&" is the tightest centre at "&TEXT(MAX(Capacity!$R$18:$R$26),"0%")&" in "&TEXT(INDEX(Capacity!$S$18:$S$26,MATCH(MAX(Capacity!$R$18:$R$26),Capacity!$R$18:$R$26,0)),"mmm-yy")&IF(SUM(Capacity!$T$18:$T$26)>0,"; "&SUM(Capacity!$T$18:$T$26)&" work-centre months exceed 100% and need a 3rd shift, overtime or off-season pre-build.","; no work centre exceeds 100%.") -> Capacity: FA-1 Fans & coolers is the tightest centre at 109% in Apr-27; 5 work-centre months exceed 100% and need a 3rd shift, overtime or off-season pre-build.
B15: ="Supply: "&COUNTIF(Inventory!$O$5:$O$14,"REORDER NOW")&" material(s) at or below the reorder point today (suggested orders worth ₹"&TEXT(Inventory!$S$15,"#,##0")&" lakh), "&COUNTIF(Inventory!$O$5:$O$14,"WATCH")&" more on watch; "&COUNTIF(RawMaterials!$R$2:$R$11,"Yes")&" material(s) depend on a single supplier." -> Supply: 2 material(s) at or below the reorder point today (suggested orders worth ₹221 lakh), 1 more on watch; 2 material(s) depend on a single supplier.
B17: Capacity heat map - utilization by work centre and month (red > 100%, amber >= 85%, green 50-85%, grey < 50%)
B18: Work centre | D18: =Capacity!E$17 -> 46327 | E18: =Capacity!F$17 -> 46357 | F18: =Capacity!G$17 -> 46388 | G18: =Capacity!H$17 -> 46419 | H18: =Capacity!I$17 -> 46447 | I18: =Capacity!J$17 -> 46478 | J18: =Capacity!K$17 -> 46508 | K18: =Capacity!L$17 -> 46539 | ... O18: =Capacity!P$17 -> 46661
B19: =INDEX(WorkCentres!$C$2:$C$10,MATCH(Capacity!$A18,WorkCentres!$A$2:$A$10,0)) -> Press shop | D19: =Capacity!E18 -> 0.62029724 | E19: =Capacity!F18 -> 0.56905573 | F19: =Capacity!G18 -> 0.5684345 | G19: =Capacity!H18 -> 0.67691282 | H19: =Capacity!I18 -> 0.87999609 | I19: =Capacity!J18 -> 0.96738711 | J19: =Capacity!K18 -> 0.92286706 | K19: =Capacity!L18 -> 0.77546932 | ... O19: =Capacity!P18 -> 0.73935082
B20: =INDEX(WorkCentres!$C$2:$C$10,MATCH(Capacity!$A19,WorkCentres!$A$2:$A$10,0)) -> Al die-casting | D20: =Capacity!E19 -> 0.69376018 | E20: =Capacity!F19 -> 0.61277218 | F20: =Capacity!G19 -> 0.60168905 | G20: =Capacity!H19 -> 0.71789021 | H20: =Capacity!I19 -> 0.91447904 | I20: =Capacity!J19 -> 0.98853276 | J20: =Capacity!K19 -> 0.94891127 | K20: =Capacity!L19 -> 0.82258598 | ... O20: =Capacity!P19 -> 0.80112943
B21: =INDEX(WorkCentres!$C$2:$C$10,MATCH(Capacity!$A20,WorkCentres!$A$2:$A$10,0)) -> Injection moulding | D21: =Capacity!E20 -> 0.72080329 | E21: =Capacity!F20 -> 0.69040256 | F21: =Capacity!G20 -> 0.67299763 | G21: =Capacity!H20 -> 0.71801132 | H21: =Capacity!I20 -> 0.92942875 | I21: =Capacity!J20 -> 1.0158712 | J21: =Capacity!K20 -> 0.95141393 | K21: =Capacity!L20 -> 0.75743273 | ... O21: =Capacity!P20 -> 0.70906784
B22: =INDEX(WorkCentres!$C$2:$C$10,MATCH(Capacity!$A21,WorkCentres!$A$2:$A$10,0)) -> Winding & motor | D22: =Capacity!E21 -> 0.66680007 | E22: =Capacity!F21 -> 0.63171585 | F22: =Capacity!G21 -> 0.63028192 | G22: =Capacity!H21 -> 0.69640915 | H22: =Capacity!I21 -> 0.84516083 | I22: =Capacity!J21 -> 0.90645402 | J22: =Capacity!K21 -> 0.86379227 | K22: =Capacity!L21 -> 0.73602168 | ... O22: =Capacity!P21 -> 0.74934159
B23: =INDEX(WorkCentres!$C$2:$C$10,MATCH(Capacity!$A22,WorkCentres!$A$2:$A$10,0)) -> Powder coating | D23: =Capacity!E22 -> 0.479468 | E23: =Capacity!F22 -> 0.44483139 | F23: =Capacity!G22 -> 0.46714059 | G23: =Capacity!H22 -> 0.60024244 | H23: =Capacity!I22 -> 0.86196033 | I23: =Capacity!J22 -> 0.98989152 | J23: =Capacity!K22 -> 0.94126671 | K23: =Capacity!L22 -> 0.76673104 | ... O23: =Capacity!P22 -> 0.63051309
B24: =INDEX(WorkCentres!$C$2:$C$10,MATCH(Capacity!$A23,WorkCentres!$A$2:$A$10,0)) -> FA-1 Fans & coolers | D24: =Capacity!E23 -> 0.35301402 | E24: =Capacity!F23 -> 0.29874537 | F24: =Capacity!G23 -> 0.3220554 | G24: =Capacity!H23 -> 0.52681081 | H24: =Capacity!I23 -> 0.91071918 | I24: =Capacity!J23 -> 1.0877297 | J24: =Capacity!K23 -> 1.0248697 | K24: =Capacity!L23 -> 0.79354775 | ... O24: =Capacity!P23 -> 0.54915673
B25: =INDEX(WorkCentres!$C$2:$C$10,MATCH(Capacity!$A24,WorkCentres!$A$2:$A$10,0)) -> FA-2 Kitchen | D25: =Capacity!E24 -> 0.89547197 | E25: =Capacity!F24 -> 0.79213015 | F25: =Capacity!G24 -> 0.71628331 | G25: =Capacity!H24 -> 0.70795626 | H25: =Capacity!I24 -> 0.63474108 | I25: =Capacity!J24 -> 0.56199723 | J25: =Capacity!K24 -> 0.55649824 | K25: =Capacity!L24 -> 0.57008861 | ... O25: =Capacity!P24 -> 0.8935866
B26: =INDEX(WorkCentres!$C$2:$C$10,MATCH(Capacity!$A25,WorkCentres!$A$2:$A$10,0)) -> FA-3 Heating & pumps | D26: =Capacity!E25 -> 0.90379902 | E26: =Capacity!F25 -> 1.0312298 | F26: =Capacity!G25 -> 1.0553019 | G26: =Capacity!H25 -> 0.79168687 | H26: =Capacity!I25 -> 0.55786738 | I26: =Capacity!J25 -> 0.47319409 | J26: =Capacity!K25 -> 0.44626023 | K26: =Capacity!L25 -> 0.44390352 | ... O26: =Capacity!P25 -> 0.67772301
B27: =INDEX(WorkCentres!$C$2:$C$10,MATCH(Capacity!$A26,WorkCentres!$A$2:$A$10,0)) -> Packing & dispatch | D27: =Capacity!E26 -> 0.66617194 | E27: =Capacity!F26 -> 0.6362832 | F27: =Capacity!G26 -> 0.63185187 | G27: =Capacity!H26 -> 0.69063532 | H27: =Capacity!I26 -> 0.85001912 | I27: =Capacity!J26 -> 0.91326425 | J27: =Capacity!K26 -> 0.86543773 | K27: =Capacity!L26 -> 0.72824853 | ... O27: =Capacity!P26 -> 0.73689115
B30: Charts
B85: Where a blue cover bar is shorter than its orange reorder-point bar, the material has hit its reorder trigger (quantities are on the Inventory sheet).
B92: Chart data (formulas that feed the charts above - do not overwrite)
B94: Raw-material spend, ranked (₹ lakh) | G94: Supplier spend, ranked (₹ lakh)
B95: Material | D95: ₹ lakh | E95: rank key | G95: Supplier | I95: ₹ lakh | J95: rank key
B96: =INDEX(Spend!$C$3:$L$3,MATCH(SMALL($E$96:$E$105,1),$E$96:$E$105,0)) -> Powder coating | D96: =INDEX(Spend!$C$15:$L$15,MATCH(SMALL($E$96:$E$105,1),$E$96:$E$105,0)) -> 314.24756 | E96: =Spend!C$15+ROW()/1000000000 -> 1255.1539 | G96: =INDEX(Suppliers!$C$2:$C$11,MATCH(SMALL($J$96:$J$105,1),$J$96:$J$105,0)) -> Ahmedabad Coatings | I96: =INDEX(Spend!$M$5:$M$14,MATCH(SMALL($J$96:$J$105,1),$J$96:$J$105,0)) -> 314.24756 | J96: =Spend!M5+ROW()/1000000000 -> 1540.7753
B97: =INDEX(Spend!$C$3:$L$3,MATCH(SMALL($E$96:$E$105,2),$E$96:$E$105,0)) -> Nichrome wire | D97: =INDEX(Spend!$C$15:$L$15,MATCH(SMALL($E$96:$E$105,2),$E$96:$E$105,0)) -> 458.43417 | E97: =Spend!D$15+ROW()/1000000000 -> 1560.2804 | G97: =INDEX(Suppliers!$C$2:$C$11,MATCH(SMALL($J$96:$J$105,2),$J$96:$J$105,0)) -> Pacific Plastics (TW) | I97: =INDEX(Spend!$M$5:$M$14,MATCH(SMALL($J$96:$J$105,2),$J$96:$J$105,0)) -> 775.4432 | J97: =Spend!M6+ROW()/1000000000 -> 1813.1851
B98: =INDEX(Spend!$C$3:$L$3,MATCH(SMALL($E$96:$E$105,3),$E$96:$E$105,0)) -> PP granules | D98: =INDEX(Spend!$C$15:$L$15,MATCH(SMALL($E$96:$E$105,3),$E$96:$E$105,0)) -> 769.40391 | E98: =Spend!E$15+ROW()/1000000000 -> 2266.4944 | G98: =INDEX(Suppliers!$C$2:$C$11,MATCH(SMALL($J$96:$J$105,3),$J$96:$J$105,0)) -> Bhiwandi Packaging | I98: =INDEX(Spend!$M$5:$M$14,MATCH(SMALL($J$96:$J$105,3),$J$96:$J$105,0)) -> 795.32526 | J98: =Spend!M7+ROW()/1000000000 -> 1453.5033
B99: =INDEX(Spend!$C$3:$L$3,MATCH(SMALL($E$96:$E$105,4),$E$96:$E$105,0)) -> Corrugated cartons | D99: =INDEX(Spend!$C$15:$L$15,MATCH(SMALL($E$96:$E$105,4),$E$96:$E$105,0)) -> 795.32526 | E99: =Spend!F$15+ROW()/1000000000 -> 6664.6628 | G99: =INDEX(Suppliers!$C$2:$C$11,MATCH(SMALL($J$96:$J$105,4),$J$96:$J$105,0)) -> Mumbai Polymer | I99: =INDEX(Spend!$M$5:$M$14,MATCH(SMALL($J$96:$J$105,4),$J$96:$J$105,0)) -> 1066.9995 | J99: =Spend!M8+ROW()/1000000000 -> 1417.5745
B100: =INDEX(Spend!$C$3:$L$3,MATCH(SMALL($E$96:$E$105,5),$E$96:$E$105,0)) -> SS304 sheet | D100: =INDEX(Spend!$C$15:$L$15,MATCH(SMALL($E$96:$E$105,5),$E$96:$E$105,0)) -> 1000.9508 | E100: =Spend!G$15+ROW()/1000000000 -> 769.40391 | G100: =INDEX(Suppliers!$C$2:$C$11,MATCH(SMALL($J$96:$J$105,5),$J$96:$J$105,0)) -> Bharat Metal Traders | I100: =INDEX(Spend!$M$5:$M$14,MATCH(SMALL($J$96:$J$105,5),$J$96:$J$105,0)) -> 1417.5745 | J100: =Spend!M9+ROW()/1000000000 -> 5291.3933
B101: =INDEX(Spend!$C$3:$L$3,MATCH(SMALL($E$96:$E$105,6),$E$96:$E$105,0)) -> ABS granules | D101: =INDEX(Spend!$C$15:$L$15,MATCH(SMALL($E$96:$E$105,6),$E$96:$E$105,0)) -> 1073.0388 | E101: =Spend!H$15+ROW()/1000000000 -> 1073.0388 | G101: =INDEX(Suppliers!$C$2:$C$11,MATCH(SMALL($J$96:$J$105,6),$J$96:$J$105,0)) -> Deccan Aluminium | I101: =INDEX(Spend!$M$5:$M$14,MATCH(SMALL($J$96:$J$105,6),$J$96:$J$105,0)) -> 1453.5033 | J101: =Spend!M10+ROW()/1000000000 -> 1689.545
B102: =INDEX(Spend!$C$3:$L$3,MATCH(SMALL($E$96:$E$105,7),$E$96:$E$105,0)) -> CRNGO steel coil | D102: =INDEX(Spend!$C$15:$L$15,MATCH(SMALL($E$96:$E$105,7),$E$96:$E$105,0)) -> 1255.1539 | E102: =Spend!I$15+ROW()/1000000000 -> 1000.9508 | G102: =INDEX(Suppliers!$C$2:$C$11,MATCH(SMALL($J$96:$J$105,7),$J$96:$J$105,0)) -> Kalinga Steels | I102: =INDEX(Spend!$M$5:$M$14,MATCH(SMALL($J$96:$J$105,7),$J$96:$J$105,0)) -> 1540.7753 | J102: =Spend!M11+ROW()/1000000000 -> 1066.9995
B103: =INDEX(Spend!$C$3:$L$3,MATCH(SMALL($E$96:$E$105,8),$E$96:$E$105,0)) -> CRCA steel sheet | D103: =INDEX(Spend!$C$15:$L$15,MATCH(SMALL($E$96:$E$105,8),$E$96:$E$105,0)) -> 1560.2804 | E103: =Spend!J$15+ROW()/1000000000 -> 458.43417 | G103: =INDEX(Suppliers!$C$2:$C$11,MATCH(SMALL($J$96:$J$105,8),$J$96:$J$105,0)) -> Coimbatore Magnet | I103: =INDEX(Spend!$M$5:$M$14,MATCH(SMALL($J$96:$J$105,8),$J$96:$J$105,0)) -> 1689.545 | J103: =Spend!M12+ROW()/1000000000 -> 775.4432
B104: =INDEX(Spend!$C$3:$L$3,MATCH(SMALL($E$96:$E$105,9),$E$96:$E$105,0)) -> Aluminium ADC12 | D104: =INDEX(Spend!$C$15:$L$15,MATCH(SMALL($E$96:$E$105,9),$E$96:$E$105,0)) -> 2266.4944 | E104: =Spend!K$15+ROW()/1000000000 -> 314.24756 | G104: =INDEX(Suppliers!$C$2:$C$11,MATCH(SMALL($J$96:$J$105,9),$J$96:$J$105,0)) -> Pune Coil Proc. | I104: =INDEX(Spend!$M$5:$M$14,MATCH(SMALL($J$96:$J$105,9),$J$96:$J$105,0)) -> 1813.1851 | J104: =Spend!M13+ROW()/1000000000 -> 314.24756
B105: =INDEX(Spend!$C$3:$L$3,MATCH(SMALL($E$96:$E$105,10),$E$96:$E$105,0)) -> Copper winding wire | D105: =INDEX(Spend!$C$15:$L$15,MATCH(SMALL($E$96:$E$105,10),$E$96:$E$105,0)) -> 6664.6628 | E105: =Spend!L$15+ROW()/1000000000 -> 795.32526 | G105: =INDEX(Suppliers!$C$2:$C$11,MATCH(SMALL($J$96:$J$105,10),$J$96:$J$105,0)) -> Vadodara Wires | I105: =INDEX(Spend!$M$5:$M$14,MATCH(SMALL($J$96:$J$105,10),$J$96:$J$105,0)) -> 5291.3933 | J105: =Spend!M14+ROW()/1000000000 -> 795.32526
B108: Work-centre utilization | H108: Monthly revenue by family (₹ lakh)
B109: Work centre | D109: Average | E109: Peak month | F109: 100% line | H109: Family | J109: =TEXT(Demand_Plan!E$5,"mmm-yy") -> Nov-26 | K109: =TEXT(Demand_Plan!F$5,"mmm-yy") -> Dec-26 | L109: =TEXT(Demand_Plan!G$5,"mmm-yy") -> Jan-27 | M109: =TEXT(Demand_Plan!H$5,"mmm-yy") -> Feb-27 | N109: =TEXT(Demand_Plan!I$5,"mmm-yy") -> Mar-27 | O109: =TEXT(Demand_Plan!J$5,"mmm-yy") -> Apr-27 | P109: =TEXT(Demand_Plan!K$5,"mmm-yy") -> May-27 | Q109: =TEXT(Demand_Plan!L$5,"mmm-yy") -> Jun-27 | ... U109: =TEXT(Demand_Plan!P$5,"mmm-yy") -> Oct-27
B110: =INDEX(WorkCentres!$C$2:$C$10,MATCH(Capacity!$A18,WorkCentres!$A$2:$A$10,0)) -> Press shop | D110: =Capacity!Q18 -> 0.71050228 | E110: =Capacity!R18 -> 0.96738711 | F110: =Assumptions!$B$19 -> 1 | H110: =Demand_Plan!$A$44 -> Fans & Cooling | J110: =Demand_Plan!E44 -> 936.405 | K110: =Demand_Plan!F44 -> 787.66 | L110: =Demand_Plan!G44 -> 852.28 | M110: =Demand_Plan!H44 -> 1418.31 | N110: =Demand_Plan!I44 -> 2484.295 | O110: =Demand_Plan!J44 -> 2979.5 | P110: =Demand_Plan!K44 -> 2805.34 | Q110: =Demand_Plan!L44 -> 2161.185 | ... U110: =Demand_Plan!P44 -> 1478.63
B111: =INDEX(WorkCentres!$C$2:$C$10,MATCH(Capacity!$A19,WorkCentres!$A$2:$A$10,0)) -> Al die-casting | D111: =Capacity!Q19 -> 0.75910875 | E111: =Capacity!R19 -> 0.98853276 | F111: =Assumptions!$B$19 -> 1 | H111: =Demand_Plan!$A$45 -> Kitchen Appliances | J111: =Demand_Plan!E45 -> 1257.85 | K111: =Demand_Plan!F45 -> 1089.9875 | L111: =Demand_Plan!G45 -> 979.425 | M111: =Demand_Plan!H45 -> 984.3125 | N111: =Demand_Plan!I45 -> 890.825 | O111: =Demand_Plan!J45 -> 793.975 | P111: =Demand_Plan!K45 -> 788.375 | Q111: =Demand_Plan!L45 -> 806.5 | ... U111: =Demand_Plan!P45 -> 1251.7375
B112: =INDEX(WorkCentres!$C$2:$C$10,MATCH(Capacity!$A20,WorkCentres!$A$2:$A$10,0)) -> Injection moulding | D112: =Capacity!Q20 -> 0.74383806 | E112: =Capacity!R20 -> 1.0158712 | F112: =Assumptions!$B$19 -> 1 | H112: =Demand_Plan!$A$46 -> Heating & Water | J112: =Demand_Plan!E46 -> 523.185 | K112: =Demand_Plan!F46 -> 584.94 | L112: =Demand_Plan!G46 -> 602.885 | M112: =Demand_Plan!H46 -> 472.695 | N112: =Demand_Plan!I46 -> 371.06 | O112: =Demand_Plan!J46 -> 341.365 | P112: =Demand_Plan!K46 -> 328.315 | Q112: =Demand_Plan!L46 -> 319.705 | ... U112: =Demand_Plan!P46 -> 397.99
B113: =INDEX(WorkCentres!$C$2:$C$10,MATCH(Capacity!$A21,WorkCentres!$A$2:$A$10,0)) -> Winding & motor | D113: =Capacity!Q21 -> 0.70818705 | E113: =Capacity!R21 -> 0.90645402 | F113: =Assumptions!$B$19 -> 1
B114: =INDEX(WorkCentres!$C$2:$C$10,MATCH(Capacity!$A22,WorkCentres!$A$2:$A$10,0)) -> Powder coating | D114: =Capacity!Q22 -> 0.65109018 | E114: =Capacity!R22 -> 0.98989152 | F114: =Assumptions!$B$19 -> 1
B115: =INDEX(WorkCentres!$C$2:$C$10,MATCH(Capacity!$A23,WorkCentres!$A$2:$A$10,0)) -> FA-1 Fans & coolers | D115: =Capacity!Q23 -> 0.61856189 | E115: =Capacity!R23 -> 1.0877297 | F115: =Assumptions!$B$19 -> 1
B116: =INDEX(WorkCentres!$C$2:$C$10,MATCH(Capacity!$A24,WorkCentres!$A$2:$A$10,0)) -> FA-2 Kitchen | D116: =Capacity!Q24 -> 0.68503724 | E116: =Capacity!R24 -> 0.89547197 | F116: =Assumptions!$B$19 -> 1
B117: =INDEX(WorkCentres!$C$2:$C$10,MATCH(Capacity!$A25,WorkCentres!$A$2:$A$10,0)) -> FA-3 Heating & pumps | D117: =Capacity!Q25 -> 0.64071702 | E117: =Capacity!R25 -> 1.0553019 | F117: =Assumptions!$B$19 -> 1
B118: =INDEX(WorkCentres!$C$2:$C$10,MATCH(Capacity!$A26,WorkCentres!$A$2:$A$10,0)) -> Packing & dispatch | D118: =Capacity!Q26 -> 0.70667045 | E118: =Capacity!R26 -> 0.91326425 | F118: =Assumptions!$B$19 -> 1
B121: Gross margin by product | H121: Inventory: days of cover vs reorder point
B122: Product | D122: Gross margin % | H122: Material | J122: Cover incl. on order (days) | K122: Reorder point (days)
B123: =Products!A2 -> P01 | D123: =Products!Q2 -> 0.26937895 | H123: =INDEX(RawMaterials!$C$2:$C$11,MATCH(Inventory!$A5,RawMaterials!$A$2:$A$11,0)) -> CRNGO steel coil | J123: =Inventory!J5 -> 38.71894 | K123: =Inventory!K5+Inventory!L5 -> 23.8
B124: =Products!A3 -> P02 | D124: =Products!Q3 -> 0.35051264 | H124: =INDEX(RawMaterials!$C$2:$C$11,MATCH(Inventory!$A6,RawMaterials!$A$2:$A$11,0)) -> CRCA steel sheet | J124: =Inventory!J6 -> 15.989576 | K124: =Inventory!K6+Inventory!L6 -> 17.85
B125: =Products!A4 -> P03 | D125: =Products!Q4 -> 0.29076557 | H125: =INDEX(RawMaterials!$C$2:$C$11,MATCH(Inventory!$A7,RawMaterials!$A$2:$A$11,0)) -> Aluminium ADC12 | J125: =Inventory!J7 -> 15.002583 | K125: =Inventory!K7+Inventory!L7 -> 13.9
B126: =Products!A5 -> P04 | D126: =Products!Q5 -> 0.28926728 | H126: =INDEX(RawMaterials!$C$2:$C$11,MATCH(Inventory!$A8,RawMaterials!$A$2:$A$11,0)) -> Copper winding wire | J126: =Inventory!J8 -> 23.261519 | K126: =Inventory!K8+Inventory!L8 -> 19.5
B127: =Products!A6 -> P05 | D127: =Products!Q6 -> 0.30136142 | H127: =INDEX(RawMaterials!$C$2:$C$11,MATCH(Inventory!$A9,RawMaterials!$A$2:$A$11,0)) -> PP granules | J127: =Inventory!J9 -> 41.005864 | K127: =Inventory!K9+Inventory!L9 -> 24.4
B128: =Products!A7 -> P06 | D128: =Products!Q7 -> 0.2793186 | H128: =INDEX(RawMaterials!$C$2:$C$11,MATCH(Inventory!$A10,RawMaterials!$A$2:$A$11,0)) -> ABS granules | J128: =Inventory!J10 -> 32.986866 | K128: =Inventory!K10+Inventory!L10 -> 39.2
B129: =Products!A8 -> P07 | D129: =Products!Q8 -> 0.30909929 | H129: =INDEX(RawMaterials!$C$2:$C$11,MATCH(Inventory!$A11,RawMaterials!$A$2:$A$11,0)) -> SS304 sheet | J129: =Inventory!J11 -> 18.995482 | K129: =Inventory!K11+Inventory!L11 -> 12.2
B130: =Products!A9 -> P08 | D130: =Products!Q9 -> 0.32040624 | H130: =INDEX(RawMaterials!$C$2:$C$11,MATCH(Inventory!$A12,RawMaterials!$A$2:$A$11,0)) -> Nichrome wire | J130: =Inventory!J12 -> 36.041134 | K130: =Inventory!K12+Inventory!L12 -> 27.3
B131: =Products!A10 -> P09 | D131: =Products!Q10 -> 0.29741858 | H131: =INDEX(RawMaterials!$C$2:$C$11,MATCH(Inventory!$A13,RawMaterials!$A$2:$A$11,0)) -> Powder coating | J131: =Inventory!J13 -> 24.016436 | K131: =Inventory!K13+Inventory!L13 -> 19
B132: =Products!A11 -> P10 | D132: =Products!Q11 -> 0.30031085 | H132: =INDEX(RawMaterials!$C$2:$C$11,MATCH(Inventory!$A14,RawMaterials!$A$2:$A$11,0)) -> Corrugated cartons | J132: =Inventory!J14 -> 21.687081 | K132: =Inventory!K14+Inventory!L14 -> 13
B133: =Products!A12 -> P11 | D133: =Products!Q12 -> 0.31022213
B134: =Products!A13 -> P12 | D134: =Products!Q13 -> 0.29936961
B135: =Products!A14 -> P13 | D135: =Products!Q14 -> 0.27660346
B136: =Products!A15 -> P14 | D136: =Products!Q15 -> 0.3024449
B137: =Products!A16 -> P15 | D137: =Products!Q16 -> 0.25950291

Sheet Assumptions
A1: Assumptions & scenario levers
A2: Global parameters that drive every calculation sheet. Blue = input. Yellow = scenario lever you can change to test a what-if.
A4: Parameter | B4: Value | C4: Unit | D4: Where it is used / note
A5: Company (fictional) | B5: Meridian Home Appliances Pvt Ltd | D5: Fictional company created for this model; supplier names are fictional too.
A6: Plant | B6: Plant 1, Chakan (Pune), Maharashtra | D6: Single-plant, make-to-forecast operating model.
A7: Inventory snapshot date | B7: 46315 | C7: date | D7: Stock and on-order quantities on the Inventory sheet are as of this date.
A8: Plan start month | B8: 46327 | C8: month | D8: First of 12 planning months (Demand_Plan, MRP, Capacity headers follow from this).
A9: Working days per month | B9: 26 | C9: days | D9: Capacity: every work centre runs this many days a month (6-day week).
A10: Demand multiplier | B10: 1 | C10: x | D10: LEVER. Scales every product's demand: 1.10 = +10%. Flows to MRP, Capacity, Spend, Inventory.
A11: Order-up-to cover | B11: 30 | C11: days | D11: Inventory: order-up-to level = reorder point + this many days of usage.
A12: WATCH buffer above reorder point | B12: 0.15 | C12: % | D12: Inventory: status is WATCH when position is within this % above the reorder point.
A13: ABC class A cut-off (cumulative spend) | B13: 0.8 | C13: % | D13: Materials inside the first 80% of cumulative spend are class A.
A14: ABC class B cut-off (cumulative spend) | B14: 0.95 | C14: % | D14: Next band up to 95% is class B; the rest is class C.
A15: Supplier flag: on-time delivery below | B15: 0.9 | C15: % | D15: Suppliers: low on-time delivery flag.
A16: Supplier flag: financial health score below | B16: 65 | C16: score | D16: Suppliers: weak financial score flag (scale 0-100).
A17: Supplier flag: share of total RM spend at or above | B17: 0.2 | C17: % | D17: Suppliers: concentration flag.
A18: Capacity: TIGHT at or above | B18: 0.85 | C18: % | D18: Capacity status and heat-map colour (amber).
... A21: Rupees per crore | B21: 10000000 | C21: ₹ | D21: Unit conversion: dashboard KPIs are shown in ₹ crore (1 crore = 10,000,000).
A23: Per-material price changes are set on RawMaterials (column H, yellow). Selling prices are on Products (column O).

Sheet Products
A1: Product ID | B1: Product | C1: Family | D1: Specification | E1: Final assembly WC | F1: Final assembly line | G1: Batch / lot size (units) | H1: Warranty (months) | I1: Base demand (units / month) | J1: Bought-out parts (₹ / unit) | K1: Key bought-out parts | L1: Raw-material cost (₹ / unit) | M1: Conversion cost (₹ / unit) | N1: Standard cost (₹ / unit) | O1: Selling price, ex-GST (₹ / unit) | P1: Gross margin (₹ / unit) | Q1: Gross margin (%) | R1: Annual units (plan) | S1: Annual revenue (₹ lakh) | T1: Annual gross profit (₹ lakh) | U1: RM share of standard cost
A2: P01 | B2: Ceiling Fan 1200 mm - Induction | C2: Fans & Cooling | D2: 1200 mm sweep, 75 W induction motor, 3 blades | E2: WC06 | F2: =INDEX(WorkCentres!$C$2:$C$10,MATCH(E2,WorkCentres!$A$2:$A$10,0)) -> FA-1 Fans & coolers | G2: 500 | H2: 24 | I2: 38000 | J2: 235 | K2: Ball bearings, capacitor, regulator, shaft and down-rod, fasteners | L2: =SUMIFS(BOM!$K$2:$K$400,BOM!$B$2:$B$400,$A2) -> 1067.5833 | M2: =INDEX(Routing!$L$25:$L$39,MATCH($A2,Routing!$A$25:$A$39,0)) -> 165.965 | N2: =L2+J2+M2 -> 1468.5483 | O2: 2010 | P2: =O2-N2 -> 541.45169 | Q2: =IF(O2=0,0,P2/O2) -> 0.26937895 | R2: =INDEX(Demand_Plan!$Q$24:$Q$38,MATCH($A2,Demand_Plan!$A$24:$A$38,0)) -> 458500 | S2: =R2*O2/Assumptions!$B$20 -> 9215.85 | T2: =R2*P2/Assumptions!$B$20 -> 2482.556 | U2: =IF(N2=0,0,L2/N2) -> 0.72696506
A3: P02 | B3: Ceiling Fan 1200 mm - BLDC | C3: Fans & Cooling | D3: 1200 mm sweep, 28 W BLDC motor, 3 blades | E3: WC06 | F3: =INDEX(WorkCentres!$C$2:$C$10,MATCH(E3,WorkCentres!$A$2:$A$10,0)) -> FA-1 Fans & coolers | G3: 250 | H3: 36 | I3: 12000 | J3: 650 | K3: BLDC driver PCB and remote receiver, magnets, bearings, fasteners | L3: =SUMIFS(BOM!$K$2:$K$400,BOM!$B$2:$B$400,$A3) -> 874.44226 | M3: =INDEX(Routing!$L$25:$L$39,MATCH($A3,Routing!$A$25:$A$39,0)) -> 157.73 | N3: =L3+J3+M3 -> 1682.1723 | O3: 2590 | P3: =O3-N3 -> 907.82774 | Q3: =IF(O3=0,0,P3/O3) -> 0.35051264 | R3: =INDEX(Demand_Plan!$Q$24:$Q$38,MATCH($A3,Demand_Plan!$A$24:$A$38,0)) -> 145000 | S3: =R3*O3/Assumptions!$B$20 -> 3755.5 | T3: =R3*P3/Assumptions!$B$20 -> 1316.3502 | U3: =IF(N3=0,0,L3/N3) -> 0.5198292
A4: P03 | B4: Pedestal Fan 400 mm | C4: Fans & Cooling | D4: 400 mm sweep, 3-speed, oscillating, height-adjustable | E4: WC06 | F4: =INDEX(WorkCentres!$C$2:$C$10,MATCH(E4,WorkCentres!$A$2:$A$10,0)) -> FA-1 Fans & coolers | G4: 250 | H4: 24 | I4: 9000 | J4: 310 | K4: Bearings, capacitor, guard grills, oscillation gearbox, switch, cord | L4: =SUMIFS(BOM!$K$2:$K$400,BOM!$B$2:$B$400,$A4) -> 782.38259 | M4: =INDEX(Routing!$L$25:$L$39,MATCH($A4,Routing!$A$25:$A$39,0)) -> 155.87 | N4: =L4+J4+M4 -> 1248.2526 | O4: 1760 | P4: =O4-N4 -> 511.74741 | Q4: =IF(O4=0,0,P4/O4) -> 0.29076557 | R4: =INDEX(Demand_Plan!$Q$24:$Q$38,MATCH($A4,Demand_Plan!$A$24:$A$38,0)) -> 109500 | S4: =R4*O4/Assumptions!$B$20 -> 1927.2 | T4: =R4*P4/Assumptions!$B$20 -> 560.36341 | U4: =IF(N4=0,0,L4/N4) -> 0.62678227
A5: P04 | B5: Table Fan 400 mm | C5: Fans & Cooling | D5: 400 mm sweep, 3-speed, oscillating | E5: WC06 | F5: =INDEX(WorkCentres!$C$2:$C$10,MATCH(E5,WorkCentres!$A$2:$A$10,0)) -> FA-1 Fans & coolers | G5: 500 | H5: 24 | I5: 14000 | J5: 190 | K5: Bearings, capacitor, guard grills, oscillation gearbox, switch, cord | L5: =SUMIFS(BOM!$K$2:$K$400,BOM!$B$2:$B$400,$A5) -> 554.98026 | M5: =INDEX(Routing!$L$25:$L$39,MATCH($A5,Routing!$A$25:$A$39,0)) -> 118.56 | N5: =L5+J5+M5 -> 863.54026 | O5: 1215 | P5: =O5-N5 -> 351.45974 | Q5: =IF(O5=0,0,P5/O5) -> 0.28926728 | R5: =INDEX(Demand_Plan!$Q$24:$Q$38,MATCH($A5,Demand_Plan!$A$24:$A$38,0)) -> 171000 | S5: =R5*O5/Assumptions!$B$20 -> 2077.65 | T5: =R5*P5/Assumptions!$B$20 -> 600.99616 | U5: =IF(N5=0,0,L5/N5) -> 0.64268024
A6: P05 | B6: Exhaust Fan 230 mm | C6: Fans & Cooling | D6: 230 mm (9 in) sweep, 55 W, with shutter | E6: WC06 | F6: =INDEX(WorkCentres!$C$2:$C$10,MATCH(E6,WorkCentres!$A$2:$A$10,0)) -> FA-1 Fans & coolers | G6: 500 | H6: 24 | I6: 16000 | J6: 95 | K6: Bearings, capacitor, shutter hardware, cord | L6: =SUMIFS(BOM!$K$2:$K$400,BOM!$B$2:$B$400,$A6) -> 315.33339 | M6: =INDEX(Routing!$L$25:$L$39,MATCH($A6,Routing!$A$25:$A$39,0)) -> 85.7 | N6: =L6+J6+M6 -> 496.03339 | O6: 710 | P6: =O6-N6 -> 213.96661 | Q6: =IF(O6=0,0,P6/O6) -> 0.30136142 | R6: =INDEX(Demand_Plan!$Q$24:$Q$38,MATCH($A6,Demand_Plan!$A$24:$A$38,0)) -> 195000 | S6: =R6*O6/Assumptions!$B$20 -> 1384.5 | T6: =R6*P6/Assumptions!$B$20 -> 417.23489 | U6: =IF(N6=0,0,L6/N6) -> 0.63571001
A7: P06 | B7: Personal Air Cooler 30 L | C7: Fans & Cooling | D7: 30 L tank, 3-speed blower, honeycomb pads | E7: WC06 | F7: =INDEX(WorkCentres!$C$2:$C$10,MATCH(E7,WorkCentres!$A$2:$A$10,0)) -> FA-1 Fans & coolers | G7: 100 | H7: 24 | I7: 6500 | J7: 480 | K7: Water pump, honeycomb pads, castors, float valve, switch, cord | L7: =SUMIFS(BOM!$K$2:$K$400,BOM!$B$2:$B$400,$A7) -> 898.3293 | M7: =INDEX(Routing!$L$25:$L$39,MATCH($A7,Routing!$A$25:$A$39,0)) -> 217.98 | N7: =L7+J7+M7 -> 1596.3093 | O7: 2215 | P7: =O7-N7 -> 618.6907 | Q7: =IF(O7=0,0,P7/O7) -> 0.2793186 | R7: =INDEX(Demand_Plan!$Q$24:$Q$38,MATCH($A7,Demand_Plan!$A$24:$A$38,0)) -> 78300 | S7: =R7*O7/Assumptions!$B$20 -> 1734.345 | T7: =R7*P7/Assumptions!$B$20 -> 484.43482 | U7: =IF(N7=0,0,L7/N7) -> 0.56275391
A8: P07 | B8: Mixer Grinder 500 W | C8: Kitchen Appliances | D8: 500 W universal motor, 3 stainless-steel jars | E8: WC07 | F8: =INDEX(WorkCentres!$C$2:$C$10,MATCH(E8,WorkCentres!$A$2:$A$10,0)) -> FA-2 Kitchen | G8: 500 | H8: 24 | I8: 18000 | J8: 165 | K8: Jar lids and gaskets, switch, overload protector, cord, rubber feet | L8: =SUMIFS(BOM!$K$2:$K$400,BOM!$B$2:$B$400,$A8) -> 771.03894 | M8: =INDEX(Routing!$L$25:$L$39,MATCH($A8,Routing!$A$25:$A$39,0)) -> 138.31167 | N8: =L8+J8+M8 -> 1074.3506 | O8: 1555 | P8: =O8-N8 -> 480.64939 | Q8: =IF(O8=0,0,P8/O8) -> 0.30909929 | R8: =INDEX(Demand_Plan!$Q$24:$Q$38,MATCH($A8,Demand_Plan!$A$24:$A$38,0)) -> 218500 | S8: =R8*O8/Assumptions!$B$20 -> 3397.675 | T8: =R8*P8/Assumptions!$B$20 -> 1050.2189 | U8: =IF(N8=0,0,L8/N8) -> 0.71767907
A9: P08 | B9: Mixer Grinder 750 W | C9: Kitchen Appliances | D9: 750 W universal motor, 3 stainless-steel jars | E9: WC07 | F9: =INDEX(WorkCentres!$C$2:$C$10,MATCH(E9,WorkCentres!$A$2:$A$10,0)) -> FA-2 Kitchen | G9: 250 | H9: 24 | I9: 14000 | J9: 195 | K9: Jar lids and gaskets, switch, overload protector, cord, rubber feet | L9: =SUMIFS(BOM!$K$2:$K$400,BOM!$B$2:$B$400,$A9) -> 1006.8588 | M9: =INDEX(Routing!$L$25:$L$39,MATCH($A9,Routing!$A$25:$A$39,0)) -> 160.72667 | N9: =L9+J9+M9 -> 1362.5855 | O9: 2005 | P9: =O9-N9 -> 642.41451 | Q9: =IF(O9=0,0,P9/O9) -> 0.32040624 | R9: =INDEX(Demand_Plan!$Q$24:$Q$38,MATCH($A9,Demand_Plan!$A$24:$A$38,0)) -> 169250 | S9: =R9*O9/Assumptions!$B$20 -> 3393.4625 | T9: =R9*P9/Assumptions!$B$20 -> 1087.2866 | U9: =IF(N9=0,0,L9/N9) -> 0.73893259
A10: P09 | B10: Electric Kettle 1.5 L | C10: Kitchen Appliances | D10: 1.5 L stainless-steel vessel, 1500 W concealed element | E10: WC07 | F10: =INDEX(WorkCentres!$C$2:$C$10,MATCH(E10,WorkCentres!$A$2:$A$10,0)) -> FA-2 Kitchen | G10: 500 | H10: 12 | I10: 22000 | J10: 140 | K10: Thermostat/cut-off controller, base connector, cord, switch and indicator | L10: =SUMIFS(BOM!$K$2:$K$400,BOM!$B$2:$B$400,$A10) -> 197.06726 | M10: =INDEX(Routing!$L$25:$L$39,MATCH($A10,Routing!$A$25:$A$39,0)) -> 56.378333 | N10: =L10+J10+M10 -> 393.4456 | O10: 560 | P10: =O10-N10 -> 166.5544 | Q10: =IF(O10=0,0,P10/O10) -> 0.29741858 | R10: =INDEX(Demand_Plan!$Q$24:$Q$38,MATCH($A10,Demand_Plan!$A$24:$A$38,0)) -> 266500 | S10: =R10*O10/Assumptions!$B$20 -> 1492.4 | T10: =R10*P10/Assumptions!$B$20 -> 443.86749 | U10: =IF(N10=0,0,L10/N10) -> 0.50087551
A11: P10 | B11: Induction Cooktop 2000 W | C11: Kitchen Appliances | D11: 2000 W induction, touch/push controls, glass top | E11: WC07 | F11: =INDEX(WorkCentres!$C$2:$C$10,MATCH(E11,WorkCentres!$A$2:$A$10,0)) -> FA-2 Kitchen | G11: 250 | H11: 12 | I11: 11000 | J11: 780 | K11: Control PCB with IGBT, ceramic glass plate, cooling fan, cord, controls | L11: =SUMIFS(BOM!$K$2:$K$400,BOM!$B$2:$B$400,$A11) -> 371.37702 | M11: =INDEX(Routing!$L$25:$L$39,MATCH($A11,Routing!$A$25:$A$39,0)) -> 104.565 | N11: =L11+J11+M11 -> 1255.942 | O11: 1795 | P11: =O11-N11 -> 539.05798 | Q11: =IF(O11=0,0,P11/O11) -> 0.30031085 | R11: =INDEX(Demand_Plan!$Q$24:$Q$38,MATCH($A11,Demand_Plan!$A$24:$A$38,0)) -> 133500 | S11: =R11*O11/Assumptions!$B$20 -> 2396.325 | T11: =R11*P11/Assumptions!$B$20 -> 719.64241 | U11: =IF(N11=0,0,L11/N11) -> 0.29569599
A12: P11 | B12: Sandwich Maker 750 W | C12: Kitchen Appliances | D12: 750 W, non-stick die-cast plates, 2-slice | E12: WC07 | F12: =INDEX(WorkCentres!$C$2:$C$10,MATCH(E12,WorkCentres!$A$2:$A$10,0)) -> FA-2 Kitchen | G12: 250 | H12: 12 | I12: 9500 | J12: 90 | K12: Thermostat, non-stick coating service, cord, indicator, rubber feet | L12: =SUMIFS(BOM!$K$2:$K$400,BOM!$B$2:$B$400,$A12) -> 302.83062 | M12: =INDEX(Routing!$L$25:$L$39,MATCH($A12,Routing!$A$25:$A$39,0)) -> 96.911667 | N12: =L12+J12+M12 -> 489.74229 | O12: 710 | P12: =O12-N12 -> 220.25771 | Q12: =IF(O12=0,0,P12/O12) -> 0.31022213 | R12: =INDEX(Demand_Plan!$Q$24:$Q$38,MATCH($A12,Demand_Plan!$A$24:$A$38,0)) -> 115500 | S12: =R12*O12/Assumptions!$B$20 -> 820.05 | T12: =R12*P12/Assumptions!$B$20 -> 254.39766 | U12: =IF(N12=0,0,L12/N12) -> 0.61834689
A13: P12 | B13: Fan Room Heater 2000 W | C13: Heating & Water | D13: 2000 W, 2 heat settings with fan, tip-over cut-off | E13: WC08 | F13: =INDEX(WorkCentres!$C$2:$C$10,MATCH(E13,WorkCentres!$A$2:$A$10,0)) -> FA-3 Heating & pumps | G13: 250 | H13: 12 | I13: 7000 | J13: 215 | K13: Thermal fuse and thermostat, switches, tip-over switch, cord | L13: =SUMIFS(BOM!$K$2:$K$400,BOM!$B$2:$B$400,$A13) -> 441.30176 | M13: =INDEX(Routing!$L$25:$L$39,MATCH($A13,Routing!$A$25:$A$39,0)) -> 114.39167 | N13: =L13+J13+M13 -> 770.69342 | O13: 1100 | P13: =O13-N13 -> 329.30658 | Q13: =IF(O13=0,0,P13/O13) -> 0.29936961 | R13: =INDEX(Demand_Plan!$Q$24:$Q$38,MATCH($A13,Demand_Plan!$A$24:$A$38,0)) -> 85250 | S13: =R13*O13/Assumptions!$B$20 -> 937.75 | T13: =R13*P13/Assumptions!$B$20 -> 280.73386 | U13: =IF(N13=0,0,L13/N13) -> 0.57260351
... A16: P15 | B16: Water Pump 0.5 HP Monoblock | C16: Heating & Water | D16: 0.5 HP (0.37 kW) single-phase monoblock centrifugal pump | E16: WC08 | F16: =INDEX(WorkCentres!$C$2:$C$10,MATCH(E16,WorkCentres!$A$2:$A$10,0)) -> FA-3 Heating & pumps | G16: 100 | H16: 24 | I16: 4500 | J16: 450 | K16: Mechanical seal, bearings, capacitor, terminal block, noryl impeller | L16: =SUMIFS(BOM!$K$2:$K$400,BOM!$B$2:$B$400,$A16) -> 1929.7305 | M16: =INDEX(Routing!$L$25:$L$39,MATCH($A16,Routing!$A$25:$A$39,0)) -> 260.14167 | N16: =L16+J16+M16 -> 2639.8721 | O16: 3565 | P16: =O16-N16 -> 925.12788 | Q16: =IF(O16=0,0,P16/O16) -> 0.25950291 | R16: =INDEX(Demand_Plan!$Q$24:$Q$38,MATCH($A16,Demand_Plan!$A$24:$A$38,0)) -> 54400 | S16: =R16*O16/Assumptions!$B$20 -> 1939.36 | T16: =R16*P16/Assumptions!$B$20 -> 503.26957 | U16: =IF(N16=0,0,L16/N16) -> 0.73099391
A18: Plant total | Q18: =IF(S18=0,0,T18/S18) -> 0.29587649 | R18: =SUM(R2:R16) -> 2620700 | S18: =SUM(S2:S16) -> 36387.618 | T18: =SUM(T2:T16) -> 10766.241 | U18: =IF(SUMPRODUCT(R2:R16,N2:N16)=0,0,SUMPRODUCT(R2:R16,L2:L16)/SUMPRODUCT(R2:R16,N2:N16)) -> 0.63064495
A20: Standard cost = raw material (from BOM) + bought-out parts + conversion (routing minutes x work-centre rate). Selling prices are planning ex-factory prices (before GST) chosen to give roughly 26-35% gross margin at base-case costs - replace with your actual price list.
A21: Bought-out parts (electronics, bearings, switches, glass, cords, etc.) are not among the 10 modelled raw materials; they are carried as a ₹ / unit allowance so unit costs stay realistic. Plant total margin and RM share are volume-weighted.

Sheet RawMaterials
A1: RM ID | B1: Raw material | C1: Short name | D1: Specification | E1: Category | F1: UoM | G1: Standard price (₹ / kg, weighted) | H1: Price change vs base (lever) | I1: Process yield (net ÷ gross) | J1: Weighted lead time (days) | K1: Longest lead time (days) | L1: Order lot (kg) = MOQ of main source | M1: Safety stock (days of usage) | N1: Price volatility | O1: Storage / handling | P1: Price basis & source note | Q1: Sources (#) | R1: Sole source? | S1: Import share of supply | T1: Source-share check (must = 100%)
A2: RW01 | B2: CRNGO Electrical Steel Coil | C2: CRNGO steel coil | D2: Non-oriented silicon steel, M-grade, 0.50 mm slit coil | E2: Ferrous metal | F2: kg | G2: =SUMPRODUCT((Sourcing!$B$2:$B$60=$A2)*Sourcing!$G$2:$G$60*Sourcing!$I$2:$I$60) -> 93.4 | H2: 0 | I2: 0.7 | J2: =SUMPRODUCT((Sourcing!$B$2:$B$60=$A2)*Sourcing!$G$2:$G$60*Sourcing!$J$2:$J$60) -> 16.8 | K2: =SUMPRODUCT(MAX((Sourcing!$B$2:$B$60=$A2)*Sourcing!$J$2:$J$60)) -> 21 | L2: =SUMIFS(Sourcing!$K$2:$K$60,Sourcing!$B$2:$B$60,$A2,Sourcing!$F$2:$F$60,"Primary")+SUMIFS(Sourcing!$K$2:$K$60,Sourcing!$B$2:$B$60,$A2,Sourcing!$F$2:$F$60,"Sole source") -> 10000 | M2: 7 | N2: Medium | O2: Covered coil store; rust-sensitive, oiled coils | P2: Planning estimate - no dated public quote found; CRNGO is sold on mill price lists | Q2: =COUNTIF(Sourcing!$B$2:$B$60,$A2) -> 2 | R2: =IF(Q2=1,"Yes","No") -> No | S2: =SUMPRODUCT((Sourcing!$B$2:$B$60=$A2)*(Sourcing!$M$2:$M$60<>"India")*Sourcing!$G$2:$G$60) -> 0 | T2: =SUMIF(Sourcing!$B$2:$B$60,$A2,Sourcing!$G$2:$G$60) -> 1
A3: RW02 | B3: CRCA Steel Sheet / Coil | C3: CRCA steel sheet | D3: Cold-rolled low-carbon steel sheet / coil, IS 513 type, 0.5-1.2 mm | E3: Ferrous metal | F3: kg | G3: =SUMPRODUCT((Sourcing!$B$2:$B$60=$A3)*Sourcing!$G$2:$G$60*Sourcing!$I$2:$I$60) -> 66.65 | H3: 0 | I3: 0.85 | J3: =SUMPRODUCT((Sourcing!$B$2:$B$60=$A3)*Sourcing!$G$2:$G$60*Sourcing!$J$2:$J$60) -> 10.85 | K3: =SUMPRODUCT(MAX((Sourcing!$B$2:$B$60=$A3)*Sourcing!$J$2:$J$60)) -> 18 | L3: =SUMIFS(Sourcing!$K$2:$K$60,Sourcing!$B$2:$B$60,$A3,Sourcing!$F$2:$F$60,"Primary")+SUMIFS(Sourcing!$K$2:$K$60,Sourcing!$B$2:$B$60,$A3,Sourcing!$F$2:$F$60,"Sole source") -> 3000 | M3: 7 | N3: Medium | O3: Covered sheet and coil store | P3: CR coil list rates ₹61.9-64.6k/t ex-yard (Tata nexarc page, dated 'Oct-24', year unclear) + ₹3-4/kg cut-to-length; rounded | Q3: =COUNTIF(Sourcing!$B$2:$B$60,$A3) -> 2 | R3: =IF(Q3=1,"Yes","No") -> No | S3: =SUMPRODUCT((Sourcing!$B$2:$B$60=$A3)*(Sourcing!$M$2:$M$60<>"India")*Sourcing!$G$2:$G$60) -> 0 | T3: =SUMIF(Sourcing!$B$2:$B$60,$A3,Sourcing!$G$2:$G$60) -> 1
A4: RW03 | B4: Aluminium Alloy Ingot (ADC12) | C4: Aluminium ADC12 | D4: ADC12 / A383 die-casting alloy, 10 kg bars | E4: Non-ferrous metal | F4: kg | G4: =SUMPRODUCT((Sourcing!$B$2:$B$60=$A4)*Sourcing!$G$2:$G$60*Sourcing!$I$2:$I$60) -> 261.5 | H4: 0 | I4: 0.92 | J4: =SUMPRODUCT((Sourcing!$B$2:$B$60=$A4)*Sourcing!$G$2:$G$60*Sourcing!$J$2:$J$60) -> 7.9 | K4: =SUMPRODUCT(MAX((Sourcing!$B$2:$B$60=$A4)*Sourcing!$J$2:$J$60)) -> 10 | L4: =SUMIFS(Sourcing!$K$2:$K$60,Sourcing!$B$2:$B$60,$A4,Sourcing!$F$2:$F$60,"Primary")+SUMIFS(Sourcing!$K$2:$K$60,Sourcing!$B$2:$B$60,$A4,Sourcing!$F$2:$F$60,"Sole source") -> 5000 | M4: 6 | N4: High | O4: Ingot yard next to melting furnace | P4: ADC12 benchmark ₹201-219/kg in late 2024 (BigMint via alcircle); scaled for 2026 LME and INR levels - estimate | Q4: =COUNTIF(Sourcing!$B$2:$B$60,$A4) -> 2 | R4: =IF(Q4=1,"Yes","No") -> No | S4: =SUMPRODUCT((Sourcing!$B$2:$B$60=$A4)*(Sourcing!$M$2:$M$60<>"India")*Sourcing!$G$2:$G$60) -> 0 | T4: =SUMIF(Sourcing!$B$2:$B$60,$A4,Sourcing!$G$2:$G$60) -> 1
A5: RW04 | B5: Enamelled Copper Winding Wire | C5: Copper winding wire | D5: Class 180 (H), 0.25-0.80 mm round wire on spools | E5: Non-ferrous metal | F5: kg | G5: =SUMPRODUCT((Sourcing!$B$2:$B$60=$A5)*Sourcing!$G$2:$G$60*Sourcing!$I$2:$I$60) -> 1336.25 | H5: 0 | I5: 0.98 | J5: =SUMPRODUCT((Sourcing!$B$2:$B$60=$A5)*Sourcing!$G$2:$G$60*Sourcing!$J$2:$J$60) -> 12.5 | K5: =SUMPRODUCT(MAX((Sourcing!$B$2:$B$60=$A5)*Sourcing!$J$2:$J$60)) -> 14 | L5: =SUMIFS(Sourcing!$K$2:$K$60,Sourcing!$B$2:$B$60,$A5,Sourcing!$F$2:$F$60,"Primary")+SUMIFS(Sourcing!$K$2:$K$60,Sourcing!$B$2:$B$60,$A5,Sourcing!$F$2:$F$60,"Sole source") -> 1000 | M5: 7 | N5: High | O5: Dry, covered spool racks; moisture-sensitive enamel | P5: Copper wire rod ₹1,229-1,249/kg ex-GST (OfBusiness listing) + about ₹100/kg enamelling premium (estimate) | Q5: =COUNTIF(Sourcing!$B$2:$B$60,$A5) -> 2 | R5: =IF(Q5=1,"Yes","No") -> No | S5: =SUMPRODUCT((Sourcing!$B$2:$B$60=$A5)*(Sourcing!$M$2:$M$60<>"India")*Sourcing!$G$2:$G$60) -> 0 | T5: =SUMIF(Sourcing!$B$2:$B$60,$A5,Sourcing!$G$2:$G$60) -> 1
A6: RW05 | B6: Polypropylene (PP) Granules | C6: PP granules | D6: Injection-moulding grade PP, homopolymer/copolymer, 25 kg bags | E6: Polymer | F6: kg | G6: =SUMPRODUCT((Sourcing!$B$2:$B$60=$A6)*Sourcing!$G$2:$G$60*Sourcing!$I$2:$I$60) -> 107 | H6: 0 | I6: 0.97 | J6: =SUMPRODUCT((Sourcing!$B$2:$B$60=$A6)*Sourcing!$G$2:$G$60*Sourcing!$J$2:$J$60) -> 12.4 | K6: =SUMPRODUCT(MAX((Sourcing!$B$2:$B$60=$A6)*Sourcing!$J$2:$J$60)) -> 38 | L6: =SUMIFS(Sourcing!$K$2:$K$60,Sourcing!$B$2:$B$60,$A6,Sourcing!$F$2:$F$60,"Primary")+SUMIFS(Sourcing!$K$2:$K$60,Sourcing!$B$2:$B$60,$A6,Sourcing!$F$2:$F$60,"Sole source") -> 5000 | M6: 12 | N6: Medium | O6: Dry bagged store; hopper-dryer feed | P6: Mumbai PP list (PolymerUpdate) needs a login - planning estimate | Q6: =COUNTIF(Sourcing!$B$2:$B$60,$A6) -> 2 | R6: =IF(Q6=1,"Yes","No") -> No | S6: =SUMPRODUCT((Sourcing!$B$2:$B$60=$A6)*(Sourcing!$M$2:$M$60<>"India")*Sourcing!$G$2:$G$60) -> 0.2 | T6: =SUMIF(Sourcing!$B$2:$B$60,$A6,Sourcing!$G$2:$G$60) -> 1
A7: RW06 | B7: ABS Granules | C7: ABS granules | D7: General-purpose injection grade ABS, natural/black, 25 kg bags | E7: Polymer | F7: kg | G7: =SUMPRODUCT((Sourcing!$B$2:$B$60=$A7)*Sourcing!$G$2:$G$60*Sourcing!$I$2:$I$60) -> 156 | H7: 0 | I7: 0.97 | J7: =SUMPRODUCT((Sourcing!$B$2:$B$60=$A7)*Sourcing!$G$2:$G$60*Sourcing!$J$2:$J$60) -> 25.2 | K7: =SUMPRODUCT(MAX((Sourcing!$B$2:$B$60=$A7)*Sourcing!$J$2:$J$60)) -> 38 | L7: =SUMIFS(Sourcing!$K$2:$K$60,Sourcing!$B$2:$B$60,$A7,Sourcing!$F$2:$F$60,"Primary")+SUMIFS(Sourcing!$K$2:$K$60,Sourcing!$B$2:$B$60,$A7,Sourcing!$F$2:$F$60,"Sole source") -> 20000 | M7: 14 | N7: Medium | O7: Dry bagged store; pre-dried before moulding | P7: Listings ₹140-170/kg (OfBusiness, undated); rounded | Q7: =COUNTIF(Sourcing!$B$2:$B$60,$A7) -> 2 | R7: =IF(Q7=1,"Yes","No") -> No | S7: =SUMPRODUCT((Sourcing!$B$2:$B$60=$A7)*(Sourcing!$M$2:$M$60<>"India")*Sourcing!$G$2:$G$60) -> 0.6 | T7: =SUMIF(Sourcing!$B$2:$B$60,$A7,Sourcing!$G$2:$G$60) -> 1
A8: RW07 | B8: Stainless Steel 304 Sheet | C8: SS304 sheet | D8: SS 304, 2B finish, 0.6-1.0 mm sheet | E8: Ferrous metal (stainless) | F8: kg | G8: =SUMPRODUCT((Sourcing!$B$2:$B$60=$A8)*Sourcing!$G$2:$G$60*Sourcing!$I$2:$I$60) -> 206.5 | H8: 0 | I8: 0.82 | J8: =SUMPRODUCT((Sourcing!$B$2:$B$60=$A8)*Sourcing!$G$2:$G$60*Sourcing!$J$2:$J$60) -> 5.2 | K8: =SUMPRODUCT(MAX((Sourcing!$B$2:$B$60=$A8)*Sourcing!$J$2:$J$60)) -> 7 | L8: =SUMIFS(Sourcing!$K$2:$K$60,Sourcing!$B$2:$B$60,$A8,Sourcing!$F$2:$F$60,"Primary")+SUMIFS(Sourcing!$K$2:$K$60,Sourcing!$B$2:$B$60,$A8,Sourcing!$F$2:$F$60,"Sole source") -> 1000 | M8: 7 | N8: High | O8: Covered sheet rack; film-protected surface | P8: Listings ₹180-220/kg, 2B sheet ₹190-210/kg (OfBusiness, undated); rounded | Q8: =COUNTIF(Sourcing!$B$2:$B$60,$A8) -> 2 | R8: =IF(Q8=1,"Yes","No") -> No | S8: =SUMPRODUCT((Sourcing!$B$2:$B$60=$A8)*(Sourcing!$M$2:$M$60<>"India")*Sourcing!$G$2:$G$60) -> 0 | T8: =SUMIF(Sourcing!$B$2:$B$60,$A8,Sourcing!$G$2:$G$60) -> 1
A9: RW08 | B9: Nichrome Resistance Wire (Ni80/Cr20) | C9: Nichrome wire | D9: Ni80Cr20 heating wire/ribbon, 0.3-1.2 mm | E9: Alloy | F9: kg | G9: =SUMPRODUCT((Sourcing!$B$2:$B$60=$A9)*Sourcing!$G$2:$G$60*Sourcing!$I$2:$I$60) -> 2080 | H9: 0 | I9: 0.96 | J9: =SUMPRODUCT((Sourcing!$B$2:$B$60=$A9)*Sourcing!$G$2:$G$60*Sourcing!$J$2:$J$60) -> 12.3 | K9: =SUMPRODUCT(MAX((Sourcing!$B$2:$B$60=$A9)*Sourcing!$J$2:$J$60)) -> 15 | L9: =SUMIFS(Sourcing!$K$2:$K$60,Sourcing!$B$2:$B$60,$A9,Sourcing!$F$2:$F$60,"Primary")+SUMIFS(Sourcing!$K$2:$K$60,Sourcing!$B$2:$B$60,$A9,Sourcing!$F$2:$F$60,"Sole source") -> 100 | M9: 15 | N9: High | O9: Locked store; high value per kg | P9: Seller listings ₹2,000-2,100/kg for coil-form 80/20 wire (IndiaMART); rounded | Q9: =COUNTIF(Sourcing!$B$2:$B$60,$A9) -> 2 | R9: =IF(Q9=1,"Yes","No") -> No | S9: =SUMPRODUCT((Sourcing!$B$2:$B$60=$A9)*(Sourcing!$M$2:$M$60<>"India")*Sourcing!$G$2:$G$60) -> 0 | T9: =SUMIF(Sourcing!$B$2:$B$60,$A9,Sourcing!$G$2:$G$60) -> 1
A10: RW09 | B10: Powder Coating (Epoxy-Polyester) | C10: Powder coating | D10: Hybrid powder, gloss/textured, 20 kg boxes | E10: Coating | F10: kg | G10: =SUMPRODUCT((Sourcing!$B$2:$B$60=$A10)*Sourcing!$G$2:$G$60*Sourcing!$I$2:$I$60) -> 345 | H10: 0 | I10: 0.8 | J10: =SUMPRODUCT((Sourcing!$B$2:$B$60=$A10)*Sourcing!$G$2:$G$60*Sourcing!$J$2:$J$60) -> 9 | K10: =SUMPRODUCT(MAX((Sourcing!$B$2:$B$60=$A10)*Sourcing!$J$2:$J$60)) -> 9 | L10: =SUMIFS(Sourcing!$K$2:$K$60,Sourcing!$B$2:$B$60,$A10,Sourcing!$F$2:$F$60,"Primary")+SUMIFS(Sourcing!$K$2:$K$60,Sourcing!$B$2:$B$60,$A10,Sourcing!$F$2:$F$60,"Sole source") -> 500 | M10: 10 | N10: Medium | O10: Cool dry store; shelf life 12 months | P10: Planning estimate - retail listings not extracted | Q10: =COUNTIF(Sourcing!$B$2:$B$60,$A10) -> 1 | R10: =IF(Q10=1,"Yes","No") -> Yes | S10: =SUMPRODUCT((Sourcing!$B$2:$B$60=$A10)*(Sourcing!$M$2:$M$60<>"India")*Sourcing!$G$2:$G$60) -> 0 | T10: =SUMIF(Sourcing!$B$2:$B$60,$A10,Sourcing!$G$2:$G$60) -> 1
A11: RW10 | B11: Corrugated Board / Cartons | C11: Corrugated cartons | D11: 5-ply printed cartons with die-cut inserts, priced per kg of board | E11: Packaging | F11: kg | G11: =SUMPRODUCT((Sourcing!$B$2:$B$60=$A11)*Sourcing!$G$2:$G$60*Sourcing!$I$2:$I$60) -> 52 | H11: 0 | I11: 0.97 | J11: =SUMPRODUCT((Sourcing!$B$2:$B$60=$A11)*Sourcing!$G$2:$G$60*Sourcing!$J$2:$J$60) -> 6 | K11: =SUMPRODUCT(MAX((Sourcing!$B$2:$B$60=$A11)*Sourcing!$J$2:$J$60)) -> 6 | L11: =SUMIFS(Sourcing!$K$2:$K$60,Sourcing!$B$2:$B$60,$A11,Sourcing!$F$2:$F$60,"Primary")+SUMIFS(Sourcing!$K$2:$K$60,Sourcing!$B$2:$B$60,$A11,Sourcing!$F$2:$F$60,"Sole source") -> 2000 | M11: 7 | N11: Low | O11: Covered flat-pack store; humidity-sensitive | P11: Planning estimate (kraft board + converting) | Q11: =COUNTIF(Sourcing!$B$2:$B$60,$A11) -> 1 | R11: =IF(Q11=1,"Yes","No") -> Yes | S11: =SUMPRODUCT((Sourcing!$B$2:$B$60=$A11)*(Sourcing!$M$2:$M$60<>"India")*Sourcing!$G$2:$G$60) -> 0 | T11: =SUMIF(Sourcing!$B$2:$B$60,$A11,Sourcing!$G$2:$G$60) -> 1
A13: All quantities are in kg so the BOM is on one consistent basis. Standard price = share-weighted effective price across the sources on the Sourcing sheet (quoted price x (1 + price change)).
A14: Prices are indicative planning rates in ₹ per kg ex-GST, anchored to public listings where marked and otherwise estimated. They are not supplier quotes - see the README for what is calculated, estimated or sourced.

Sheet Suppliers
A1: Supplier ID | B1: Supplier (fictional) | C1: Short name | D1: City / state | E1: Country | F1: Supplier type | G1: Certifications | H1: On-time delivery (OTD) | I1: Avg delay when late (days) | J1: Rejection rate | K1: Lead-time std dev (days) | L1: Financial health score (0-100) | M1: Payment terms (days) | N1: Materials supplied (#) | O1: Sole-source materials (#) | P1: Avg lead time (days) | Q1: Annual spend (₹ lakh) | R1: Share of RM spend | S1: Domestic / import | T1: Risk flags (#) | U1: Watch-list reasons
A2: S01 | B2: Kalinga Electrical Steels Pvt Ltd | C2: Kalinga Steels | D2: Rourkela, Odisha | E2: India | F2: Steel mill | G2: ISO 9001, ISO 14001, BIS licence | H2: 0.91 | I2: 4.5 | J2: 0.008 | K2: 4 | L2: 84 | M2: 21 | N2: =COUNTIF(Sourcing!$D$2:$D$60,$A2) -> 2 | O2: =COUNTIFS(Sourcing!$D$2:$D$60,$A2,Sourcing!$F$2:$F$60,"Sole source") -> 0 | P2: =IFERROR(AVERAGEIF(Sourcing!$D$2:$D$60,$A2,Sourcing!$J$2:$J$60),0) -> 19.5 | Q2: =INDEX(Spend!$M$5:$M$14,MATCH($A2,Spend!$A$5:$A$14,0)) -> 1540.7753 | R2: =IF(SUM($Q$2:$Q$11)=0,0,Q2/SUM($Q$2:$Q$11)) -> 0.095356855 | S2: =IF(E2="India","Domestic","Import") -> Domestic | T2: =(H2<Assumptions!$B$15)+(O2>0)+(S2="Import")+(L2<Assumptions!$B$16)+(R2>=Assumptions!$B$17) -> 0 | U2: =IF(T2=0,"None",MID(IF(H2<Assumptions!$B$15,"; Low on-time delivery","")&IF(O2>0,"; Sole source for "&O2&" material(s)","")&IF(S2="Import","; Import / long lead time","")&IF(L2<Assumptions!$B$16,"; Weak financial score","")&IF(R2>=Assumptions!$B$17,"; High share of RM spend",""),3,200)) -> None
A3: S02 | B3: Pune Coil Processing Pvt Ltd | C3: Pune Coil Proc. | D3: Chakan, Pune, Maharashtra | E3: India | F3: Steel service centre | G3: ISO 9001 | H3: 0.955 | I3: 2 | J3: 0.009 | K3: 2 | L3: 74 | M3: 45 | N3: =COUNTIF(Sourcing!$D$2:$D$60,$A3) -> 3 | O3: =COUNTIFS(Sourcing!$D$2:$D$60,$A3,Sourcing!$F$2:$F$60,"Sole source") -> 0 | P3: =IFERROR(AVERAGEIF(Sourcing!$D$2:$D$60,$A3,Sourcing!$J$2:$J$60),0) -> 6.3333333 | Q3: =INDEX(Spend!$M$5:$M$14,MATCH($A3,Spend!$A$5:$A$14,0)) -> 1813.1851 | R3: =IF(SUM($Q$2:$Q$11)=0,0,Q3/SUM($Q$2:$Q$11)) -> 0.11221599 | S3: =IF(E3="India","Domestic","Import") -> Domestic | T3: =(H3<Assumptions!$B$15)+(O3>0)+(S3="Import")+(L3<Assumptions!$B$16)+(R3>=Assumptions!$B$17) -> 0 | U3: =IF(T3=0,"None",MID(IF(H3<Assumptions!$B$15,"; Low on-time delivery","")&IF(O3>0,"; Sole source for "&O3&" material(s)","")&IF(S3="Import","; Import / long lead time","")&IF(L3<Assumptions!$B$16,"; Weak financial score","")&IF(R3>=Assumptions!$B$17,"; High share of RM spend",""),3,200)) -> None
A4: S03 | B4: Deccan Aluminium Alloys Ltd | C4: Deccan Aluminium | D4: Hyderabad, Telangana | E4: India | F4: Secondary aluminium smelter | G4: ISO 9001, IATF 16949 | H4: 0.9 | I4: 3.5 | J4: 0.014 | K4: 3 | L4: 69 | M4: 30 | N4: =COUNTIF(Sourcing!$D$2:$D$60,$A4) -> 1 | O4: =COUNTIFS(Sourcing!$D$2:$D$60,$A4,Sourcing!$F$2:$F$60,"Sole source") -> 0 | P4: =IFERROR(AVERAGEIF(Sourcing!$D$2:$D$60,$A4,Sourcing!$J$2:$J$60),0) -> 10 | Q4: =INDEX(Spend!$M$5:$M$14,MATCH($A4,Spend!$A$5:$A$14,0)) -> 1453.5033 | R4: =IF(SUM($Q$2:$Q$11)=0,0,Q4/SUM($Q$2:$Q$11)) -> 0.089955688 | S4: =IF(E4="India","Domestic","Import") -> Domestic | T4: =(H4<Assumptions!$B$15)+(O4>0)+(S4="Import")+(L4<Assumptions!$B$16)+(R4>=Assumptions!$B$17) -> 0 | U4: =IF(T4=0,"None",MID(IF(H4<Assumptions!$B$15,"; Low on-time delivery","")&IF(O4>0,"; Sole source for "&O4&" material(s)","")&IF(S4="Import","; Import / long lead time","")&IF(L4<Assumptions!$B$16,"; Weak financial score","")&IF(R4>=Assumptions!$B$17,"; High share of RM spend",""),3,200)) -> None
A5: S04 | B5: Bharat Metal Traders | C5: Bharat Metal Traders | D5: Mumbai, Maharashtra | E5: India | F5: Metal trader / stockist | G5: GST-registered trader (no plant certification) | H5: 0.93 | I5: 2.5 | J5: 0.011 | K5: 2.5 | L5: 61 | M5: 15 | N5: =COUNTIF(Sourcing!$D$2:$D$60,$A5) -> 3 | O5: =COUNTIFS(Sourcing!$D$2:$D$60,$A5,Sourcing!$F$2:$F$60,"Sole source") -> 0 | P5: =IFERROR(AVERAGEIF(Sourcing!$D$2:$D$60,$A5,Sourcing!$J$2:$J$60),0) -> 4.3333333 | Q5: =INDEX(Spend!$M$5:$M$14,MATCH($A5,Spend!$A$5:$A$14,0)) -> 1417.5745 | R5: =IF(SUM($Q$2:$Q$11)=0,0,Q5/SUM($Q$2:$Q$11)) -> 0.087732097 | S5: =IF(E5="India","Domestic","Import") -> Domestic | T5: =(H5<Assumptions!$B$15)+(O5>0)+(S5="Import")+(L5<Assumptions!$B$16)+(R5>=Assumptions!$B$17) -> 1 | U5: =IF(T5=0,"None",MID(IF(H5<Assumptions!$B$15,"; Low on-time delivery","")&IF(O5>0,"; Sole source for "&O5&" material(s)","")&IF(S5="Import","; Import / long lead time","")&IF(L5<Assumptions!$B$16,"; Weak financial score","")&IF(R5>=Assumptions!$B$17,"; High share of RM spend",""),3,200)) -> Weak financial score
A6: S05 | B6: Vadodara Winding & Resistance Wires Ltd | C6: Vadodara Wires | D6: Vadodara, Gujarat | E6: India | F6: Winding & resistance wire maker | G6: ISO 9001, ISO 14001 | H6: 0.96 | I6: 1.5 | J6: 0.003 | K6: 1.5 | L6: 78 | M6: 45 | N6: =COUNTIF(Sourcing!$D$2:$D$60,$A6) -> 2 | O6: =COUNTIFS(Sourcing!$D$2:$D$60,$A6,Sourcing!$F$2:$F$60,"Sole source") -> 0 | P6: =IFERROR(AVERAGEIF(Sourcing!$D$2:$D$60,$A6,Sourcing!$J$2:$J$60),0) -> 13.5 | Q6: =INDEX(Spend!$M$5:$M$14,MATCH($A6,Spend!$A$5:$A$14,0)) -> 5291.3933 | R6: =IF(SUM($Q$2:$Q$11)=0,0,Q6/SUM($Q$2:$Q$11)) -> 0.32747839 | S6: =IF(E6="India","Domestic","Import") -> Domestic | T6: =(H6<Assumptions!$B$15)+(O6>0)+(S6="Import")+(L6<Assumptions!$B$16)+(R6>=Assumptions!$B$17) -> 1 | U6: =IF(T6=0,"None",MID(IF(H6<Assumptions!$B$15,"; Low on-time delivery","")&IF(O6>0,"; Sole source for "&O6&" material(s)","")&IF(S6="Import","; Import / long lead time","")&IF(L6<Assumptions!$B$16,"; Weak financial score","")&IF(R6>=Assumptions!$B$17,"; High share of RM spend",""),3,200)) -> High share of RM spend
A7: S06 | B7: Coimbatore Magnet Wires Pvt Ltd | C7: Coimbatore Magnet | D7: Coimbatore, Tamil Nadu | E7: India | F7: Winding wire maker | G7: ISO 9001 | H7: 0.885 | I7: 4 | J7: 0.007 | K7: 3.5 | L7: 66 | M7: 45 | N7: =COUNTIF(Sourcing!$D$2:$D$60,$A7) -> 1 | O7: =COUNTIFS(Sourcing!$D$2:$D$60,$A7,Sourcing!$F$2:$F$60,"Sole source") -> 0 | P7: =IFERROR(AVERAGEIF(Sourcing!$D$2:$D$60,$A7,Sourcing!$J$2:$J$60),0) -> 14 | Q7: =INDEX(Spend!$M$5:$M$14,MATCH($A7,Spend!$A$5:$A$14,0)) -> 1689.545 | R7: =IF(SUM($Q$2:$Q$11)=0,0,Q7/SUM($Q$2:$Q$11)) -> 0.10456405 | S7: =IF(E7="India","Domestic","Import") -> Domestic | T7: =(H7<Assumptions!$B$15)+(O7>0)+(S7="Import")+(L7<Assumptions!$B$16)+(R7>=Assumptions!$B$17) -> 1 | U7: =IF(T7=0,"None",MID(IF(H7<Assumptions!$B$15,"; Low on-time delivery","")&IF(O7>0,"; Sole source for "&O7&" material(s)","")&IF(S7="Import","; Import / long lead time","")&IF(L7<Assumptions!$B$16,"; Weak financial score","")&IF(R7>=Assumptions!$B$17,"; High share of RM spend",""),3,200)) -> Low on-time delivery
A8: S07 | B8: Mumbai Polymer Distribution Co. | C8: Mumbai Polymer | D8: Navi Mumbai, Maharashtra | E8: India | F8: Polymer distributor | G8: ISO 9001 | H8: 0.945 | I8: 2 | J8: 0.004 | K8: 2 | L8: 85 | M8: 30 | N8: =COUNTIF(Sourcing!$D$2:$D$60,$A8) -> 2 | O8: =COUNTIFS(Sourcing!$D$2:$D$60,$A8,Sourcing!$F$2:$F$60,"Sole source") -> 0 | P8: =IFERROR(AVERAGEIF(Sourcing!$D$2:$D$60,$A8,Sourcing!$J$2:$J$60),0) -> 6 | Q8: =INDEX(Spend!$M$5:$M$14,MATCH($A8,Spend!$A$5:$A$14,0)) -> 1066.9995 | R8: =IF(SUM($Q$2:$Q$11)=0,0,Q8/SUM($Q$2:$Q$11)) -> 0.066035401 | S8: =IF(E8="India","Domestic","Import") -> Domestic | T8: =(H8<Assumptions!$B$15)+(O8>0)+(S8="Import")+(L8<Assumptions!$B$16)+(R8>=Assumptions!$B$17) -> 0 | U8: =IF(T8=0,"None",MID(IF(H8<Assumptions!$B$15,"; Low on-time delivery","")&IF(O8>0,"; Sole source for "&O8&" material(s)","")&IF(S8="Import","; Import / long lead time","")&IF(L8<Assumptions!$B$16,"; Weak financial score","")&IF(R8>=Assumptions!$B$17,"; High share of RM spend",""),3,200)) -> None
A9: S08 | B9: Pacific Engineering Plastics Co. Ltd | C9: Pacific Plastics (TW) | D9: Kaohsiung | E9: Taiwan | F9: Resin producer (import) | G9: ISO 9001, ISO 14001 | H9: 0.86 | I9: 6.5 | J9: 0.005 | K9: 7 | L9: 88 | M9: 60 | N9: =COUNTIF(Sourcing!$D$2:$D$60,$A9) -> 2 | O9: =COUNTIFS(Sourcing!$D$2:$D$60,$A9,Sourcing!$F$2:$F$60,"Sole source") -> 0 | P9: =IFERROR(AVERAGEIF(Sourcing!$D$2:$D$60,$A9,Sourcing!$J$2:$J$60),0) -> 38 | Q9: =INDEX(Spend!$M$5:$M$14,MATCH($A9,Spend!$A$5:$A$14,0)) -> 775.4432 | R9: =IF(SUM($Q$2:$Q$11)=0,0,Q9/SUM($Q$2:$Q$11)) -> 0.04799131 | S9: =IF(E9="India","Domestic","Import") -> Import | T9: =(H9<Assumptions!$B$15)+(O9>0)+(S9="Import")+(L9<Assumptions!$B$16)+(R9>=Assumptions!$B$17) -> 2 | U9: =IF(T9=0,"None",MID(IF(H9<Assumptions!$B$15,"; Low on-time delivery","")&IF(O9>0,"; Sole source for "&O9&" material(s)","")&IF(S9="Import","; Import / long lead time","")&IF(L9<Assumptions!$B$16,"; Weak financial score","")&IF(R9>=Assumptions!$B$17,"; High share of RM spend",""),3,200)) -> Low on-time delivery; Import / long lead time
A10: S09 | B10: Ahmedabad Coatings & Powders Pvt Ltd | C10: Ahmedabad Coatings | D10: Ahmedabad, Gujarat | E10: India | F10: Powder-coating manufacturer | G10: ISO 9001 | H10: 0.925 | I10: 3 | J10: 0.006 | K10: 2.5 | L10: 58 | M10: 45 | N10: =COUNTIF(Sourcing!$D$2:$D$60,$A10) -> 1 | O10: =COUNTIFS(Sourcing!$D$2:$D$60,$A10,Sourcing!$F$2:$F$60,"Sole source") -> 1 | P10: =IFERROR(AVERAGEIF(Sourcing!$D$2:$D$60,$A10,Sourcing!$J$2:$J$60),0) -> 9 | Q10: =INDEX(Spend!$M$5:$M$14,MATCH($A10,Spend!$A$5:$A$14,0)) -> 314.24756 | R10: =IF(SUM($Q$2:$Q$11)=0,0,Q10/SUM($Q$2:$Q$11)) -> 0.019448429 | S10: =IF(E10="India","Domestic","Import") -> Domestic | T10: =(H10<Assumptions!$B$15)+(O10>0)+(S10="Import")+(L10<Assumptions!$B$16)+(R10>=Assumptions!$B$17) -> 2 | U10: =IF(T10=0,"None",MID(IF(H10<Assumptions!$B$15,"; Low on-time delivery","")&IF(O10>0,"; Sole source for "&O10&" material(s)","")&IF(S10="Import","; Import / long lead time","")&IF(L10<Assumptions!$B$16,"; Weak financial score","")&IF(R10>=Assumptions!$B$17,"; High share of RM spend",""),3,200)) -> Sole source for 1 material(s); Weak financial score
A11: S10 | B11: Bhiwandi Packaging Industries | C11: Bhiwandi Packaging | D11: Bhiwandi, Maharashtra | E11: India | F11: Corrugated carton converter | G11: ISO 9001, FSC chain of custody | H11: 0.97 | I11: 1 | J11: 0.009 | K11: 1 | L11: 72 | M11: 60 | N11: =COUNTIF(Sourcing!$D$2:$D$60,$A11) -> 1 | O11: =COUNTIFS(Sourcing!$D$2:$D$60,$A11,Sourcing!$F$2:$F$60,"Sole source") -> 1 | P11: =IFERROR(AVERAGEIF(Sourcing!$D$2:$D$60,$A11,Sourcing!$J$2:$J$60),0) -> 6 | Q11: =INDEX(Spend!$M$5:$M$14,MATCH($A11,Spend!$A$5:$A$14,0)) -> 795.32526 | R11: =IF(SUM($Q$2:$Q$11)=0,0,Q11/SUM($Q$2:$Q$11)) -> 0.049221788 | S11: =IF(E11="India","Domestic","Import") -> Domestic | T11: =(H11<Assumptions!$B$15)+(O11>0)+(S11="Import")+(L11<Assumptions!$B$16)+(R11>=Assumptions!$B$17) -> 1 | U11: =IF(T11=0,"None",MID(IF(H11<Assumptions!$B$15,"; Low on-time delivery","")&IF(O11>0,"; Sole source for "&O11&" material(s)","")&IF(S11="Import","; Import / long lead time","")&IF(L11<Assumptions!$B$16,"; Weak financial score","")&IF(R11>=Assumptions!$B$17,"; High share of RM spend",""),3,200)) -> Sole source for 1 material(s)
A13: Performance figures (OTD, delay, rejection, lead-time variability, financial score, payment terms) are illustrative planning inputs for fictional suppliers - not measured data. Flags use the thresholds on the Assumptions sheet.
A14: Annual spend comes from the Spend sheet (MRP volume x source split x effective price). Watch-list reasons are generated by formula, so they update when inputs change.

Sheet Sourcing
A1: Link ID | B1: RM ID | C1: Raw material | D1: Supplier ID | E1: Supplier | F1: Role | G1: Share of requirement | H1: Quoted price (₹ / kg) | I1: Effective price (₹ / kg) | J1: Lead time (days) | K1: MOQ (kg) | L1: Transport | M1: Supplier origin | N1: Annual volume (kg) | O1: Annual spend (₹ lakh) | Q1: Notes
A2: L01 | B2: RW01 | C2: =INDEX(RawMaterials!$B$2:$B$11,MATCH($B2,RawMaterials!$A$2:$A$11,0)) -> CRNGO Electrical Steel Coil | D2: S01 | E2: =INDEX(Suppliers!$B$2:$B$11,MATCH($D2,Suppliers!$A$2:$A$11,0)) -> Kalinga Electrical Steels Pvt Ltd | F2: Primary | G2: 0.7 | H2: 91 | I2: =H2*(1+INDEX(RawMaterials!$H$2:$H$11,MATCH($B2,RawMaterials!$A$2:$A$11,0))) -> 91 | J2: 21 | K2: 10000 | L2: Rail + road | M2: =INDEX(Suppliers!$E$2:$E$11,MATCH($D2,Suppliers!$A$2:$A$11,0)) -> India | N2: =G2*INDEX(MRP!$P$5:$P$14,MATCH($B2,MRP!$A$5:$A$14,0)) -> 940693.5 | O2: =N2*I2/Assumptions!$B$20 -> 856.03108 | Q2: Each material is bought from 1-2 sources. Share of requirement must add to 100% per material (see Checks). Role 'Sole source' = only one approved supplier. Annual volume = share x annual gross requirement from MRP; annual spend = volume x effective price. Quoted prices are indicative planning rates (ex-GST, delivered), not supplier quotes. Lead times and MOQs are typical for each supplier type. To add a sourcing link, type it in the next free row (formulas read rows 2-60) and copy the formulas in columns C, E, I, M, N and O down.
A3: L02 | B3: RW01 | C3: =INDEX(RawMaterials!$B$2:$B$11,MATCH($B3,RawMaterials!$A$2:$A$11,0)) -> CRNGO Electrical Steel Coil | D3: S02 | E3: =INDEX(Suppliers!$B$2:$B$11,MATCH($D3,Suppliers!$A$2:$A$11,0)) -> Pune Coil Processing Pvt Ltd | F3: Secondary | G3: 0.3 | H3: 99 | I3: =H3*(1+INDEX(RawMaterials!$H$2:$H$11,MATCH($B3,RawMaterials!$A$2:$A$11,0))) -> 99 | J3: 7 | K3: 2000 | L3: Road | M3: =INDEX(Suppliers!$E$2:$E$11,MATCH($D3,Suppliers!$A$2:$A$11,0)) -> India | N3: =G3*INDEX(MRP!$P$5:$P$14,MATCH($B3,MRP!$A$5:$A$14,0)) -> 403154.36 | O3: =N3*I3/Assumptions!$B$20 -> 399.12281
A4: L03 | B4: RW02 | C4: =INDEX(RawMaterials!$B$2:$B$11,MATCH($B4,RawMaterials!$A$2:$A$11,0)) -> CRCA Steel Sheet / Coil | D4: S02 | E4: =INDEX(Suppliers!$B$2:$B$11,MATCH($D4,Suppliers!$A$2:$A$11,0)) -> Pune Coil Processing Pvt Ltd | F4: Primary | G4: 0.55 | H4: 68 | I4: =H4*(1+INDEX(RawMaterials!$H$2:$H$11,MATCH($B4,RawMaterials!$A$2:$A$11,0))) -> 68 | J4: 5 | K4: 3000 | L4: Road | M4: =INDEX(Suppliers!$E$2:$E$11,MATCH($D4,Suppliers!$A$2:$A$11,0)) -> India | N4: =G4*INDEX(MRP!$P$5:$P$14,MATCH($B4,MRP!$A$5:$A$14,0)) -> 1287553.2 | O4: =N4*I4/Assumptions!$B$20 -> 875.5362
A5: L04 | B5: RW02 | C5: =INDEX(RawMaterials!$B$2:$B$11,MATCH($B5,RawMaterials!$A$2:$A$11,0)) -> CRCA Steel Sheet / Coil | D5: S01 | E5: =INDEX(Suppliers!$B$2:$B$11,MATCH($D5,Suppliers!$A$2:$A$11,0)) -> Kalinga Electrical Steels Pvt Ltd | F5: Secondary | G5: 0.45 | H5: 65 | I5: =H5*(1+INDEX(RawMaterials!$H$2:$H$11,MATCH($B5,RawMaterials!$A$2:$A$11,0))) -> 65 | J5: 18 | K5: 15000 | L5: Rail + road | M5: =INDEX(Suppliers!$E$2:$E$11,MATCH($D5,Suppliers!$A$2:$A$11,0)) -> India | N5: =G5*INDEX(MRP!$P$5:$P$14,MATCH($B5,MRP!$A$5:$A$14,0)) -> 1053452.6 | O5: =N5*I5/Assumptions!$B$20 -> 684.74422
A6: L05 | B6: RW03 | C6: =INDEX(RawMaterials!$B$2:$B$11,MATCH($B6,RawMaterials!$A$2:$A$11,0)) -> Aluminium Alloy Ingot (ADC12) | D6: S03 | E6: =INDEX(Suppliers!$B$2:$B$11,MATCH($D6,Suppliers!$A$2:$A$11,0)) -> Deccan Aluminium Alloys Ltd | F6: Primary | G6: 0.65 | H6: 258 | I6: =H6*(1+INDEX(RawMaterials!$H$2:$H$11,MATCH($B6,RawMaterials!$A$2:$A$11,0))) -> 258 | J6: 10 | K6: 5000 | L6: Road | M6: =INDEX(Suppliers!$E$2:$E$11,MATCH($D6,Suppliers!$A$2:$A$11,0)) -> India | N6: =G6*INDEX(MRP!$P$5:$P$14,MATCH($B6,MRP!$A$5:$A$14,0)) -> 563373.37 | O6: =N6*I6/Assumptions!$B$20 -> 1453.5033
A7: L06 | B7: RW03 | C7: =INDEX(RawMaterials!$B$2:$B$11,MATCH($B7,RawMaterials!$A$2:$A$11,0)) -> Aluminium Alloy Ingot (ADC12) | D7: S04 | E7: =INDEX(Suppliers!$B$2:$B$11,MATCH($D7,Suppliers!$A$2:$A$11,0)) -> Bharat Metal Traders | F7: Secondary | G7: 0.35 | H7: 268 | I7: =H7*(1+INDEX(RawMaterials!$H$2:$H$11,MATCH($B7,RawMaterials!$A$2:$A$11,0))) -> 268 | J7: 4 | K7: 1000 | L7: Road | M7: =INDEX(Suppliers!$E$2:$E$11,MATCH($D7,Suppliers!$A$2:$A$11,0)) -> India | N7: =G7*INDEX(MRP!$P$5:$P$14,MATCH($B7,MRP!$A$5:$A$14,0)) -> 303354.89 | O7: =N7*I7/Assumptions!$B$20 -> 812.99111
A8: L07 | B8: RW04 | C8: =INDEX(RawMaterials!$B$2:$B$11,MATCH($B8,RawMaterials!$A$2:$A$11,0)) -> Enamelled Copper Winding Wire | D8: S05 | E8: =INDEX(Suppliers!$B$2:$B$11,MATCH($D8,Suppliers!$A$2:$A$11,0)) -> Vadodara Winding & Resistance Wires Ltd | F8: Primary | G8: 0.75 | H8: 1330 | I8: =H8*(1+INDEX(RawMaterials!$H$2:$H$11,MATCH($B8,RawMaterials!$A$2:$A$11,0))) -> 1330 | J8: 12 | K8: 1000 | L8: Road | M8: =INDEX(Suppliers!$E$2:$E$11,MATCH($D8,Suppliers!$A$2:$A$11,0)) -> India | N8: =G8*INDEX(MRP!$P$5:$P$14,MATCH($B8,MRP!$A$5:$A$14,0)) -> 374069.01 | O8: =N8*I8/Assumptions!$B$20 -> 4975.1178
A9: L08 | B9: RW04 | C9: =INDEX(RawMaterials!$B$2:$B$11,MATCH($B9,RawMaterials!$A$2:$A$11,0)) -> Enamelled Copper Winding Wire | D9: S06 | E9: =INDEX(Suppliers!$B$2:$B$11,MATCH($D9,Suppliers!$A$2:$A$11,0)) -> Coimbatore Magnet Wires Pvt Ltd | F9: Secondary | G9: 0.25 | H9: 1355 | I9: =H9*(1+INDEX(RawMaterials!$H$2:$H$11,MATCH($B9,RawMaterials!$A$2:$A$11,0))) -> 1355 | J9: 14 | K9: 500 | L9: Road | M9: =INDEX(Suppliers!$E$2:$E$11,MATCH($D9,Suppliers!$A$2:$A$11,0)) -> India | N9: =G9*INDEX(MRP!$P$5:$P$14,MATCH($B9,MRP!$A$5:$A$14,0)) -> 124689.67 | O9: =N9*I9/Assumptions!$B$20 -> 1689.545
A10: L09 | B10: RW05 | C10: =INDEX(RawMaterials!$B$2:$B$11,MATCH($B10,RawMaterials!$A$2:$A$11,0)) -> Polypropylene (PP) Granules | D10: S07 | E10: =INDEX(Suppliers!$B$2:$B$11,MATCH($D10,Suppliers!$A$2:$A$11,0)) -> Mumbai Polymer Distribution Co. | F10: Primary | G10: 0.8 | H10: 108 | I10: =H10*(1+INDEX(RawMaterials!$H$2:$H$11,MATCH($B10,RawMaterials!$A$2:$A$11,0))) -> 108 | J10: 6 | K10: 5000 | L10: Road | M10: =INDEX(Suppliers!$E$2:$E$11,MATCH($D10,Suppliers!$A$2:$A$11,0)) -> India | N10: =G10*INDEX(MRP!$P$5:$P$14,MATCH($B10,MRP!$A$5:$A$14,0)) -> 575255.26 | O10: =N10*I10/Assumptions!$B$20 -> 621.27568
A11: L10 | B11: RW05 | C11: =INDEX(RawMaterials!$B$2:$B$11,MATCH($B11,RawMaterials!$A$2:$A$11,0)) -> Polypropylene (PP) Granules | D11: S08 | E11: =INDEX(Suppliers!$B$2:$B$11,MATCH($D11,Suppliers!$A$2:$A$11,0)) -> Pacific Engineering Plastics Co. Ltd | F11: Secondary | G11: 0.2 | H11: 103 | I11: =H11*(1+INDEX(RawMaterials!$H$2:$H$11,MATCH($B11,RawMaterials!$A$2:$A$11,0))) -> 103 | J11: 38 | K11: 20000 | L11: Sea + road | M11: =INDEX(Suppliers!$E$2:$E$11,MATCH($D11,Suppliers!$A$2:$A$11,0)) -> Taiwan | N11: =G11*INDEX(MRP!$P$5:$P$14,MATCH($B11,MRP!$A$5:$A$14,0)) -> 143813.81 | O11: =N11*I11/Assumptions!$B$20 -> 148.12823
A12: L11 | B12: RW06 | C12: =INDEX(RawMaterials!$B$2:$B$11,MATCH($B12,RawMaterials!$A$2:$A$11,0)) -> ABS Granules | D12: S08 | E12: =INDEX(Suppliers!$B$2:$B$11,MATCH($D12,Suppliers!$A$2:$A$11,0)) -> Pacific Engineering Plastics Co. Ltd | F12: Primary | G12: 0.6 | H12: 152 | I12: =H12*(1+INDEX(RawMaterials!$H$2:$H$11,MATCH($B12,RawMaterials!$A$2:$A$11,0))) -> 152 | J12: 38 | K12: 20000 | L12: Sea + road | M12: =INDEX(Suppliers!$E$2:$E$11,MATCH($D12,Suppliers!$A$2:$A$11,0)) -> Taiwan | N12: =G12*INDEX(MRP!$P$5:$P$14,MATCH($B12,MRP!$A$5:$A$14,0)) -> 412707.22 | O12: =N12*I12/Assumptions!$B$20 -> 627.31497
A13: L12 | B13: RW06 | C13: =INDEX(RawMaterials!$B$2:$B$11,MATCH($B13,RawMaterials!$A$2:$A$11,0)) -> ABS Granules | D13: S07 | E13: =INDEX(Suppliers!$B$2:$B$11,MATCH($D13,Suppliers!$A$2:$A$11,0)) -> Mumbai Polymer Distribution Co. | F13: Secondary | G13: 0.4 | H13: 162 | I13: =H13*(1+INDEX(RawMaterials!$H$2:$H$11,MATCH($B13,RawMaterials!$A$2:$A$11,0))) -> 162 | J13: 6 | K13: 2500 | L13: Road | M13: =INDEX(Suppliers!$E$2:$E$11,MATCH($D13,Suppliers!$A$2:$A$11,0)) -> India | N13: =G13*INDEX(MRP!$P$5:$P$14,MATCH($B13,MRP!$A$5:$A$14,0)) -> 275138.14 | O13: =N13*I13/Assumptions!$B$20 -> 445.72379
A14: L13 | B14: RW07 | C14: =INDEX(RawMaterials!$B$2:$B$11,MATCH($B14,RawMaterials!$A$2:$A$11,0)) -> Stainless Steel 304 Sheet | D14: S02 | E14: =INDEX(Suppliers!$B$2:$B$11,MATCH($D14,Suppliers!$A$2:$A$11,0)) -> Pune Coil Processing Pvt Ltd | F14: Primary | G14: 0.55 | H14: 202 | I14: =H14*(1+INDEX(RawMaterials!$H$2:$H$11,MATCH($B14,RawMaterials!$A$2:$A$11,0))) -> 202 | J14: 7 | K14: 1000 | L14: Road | M14: =INDEX(Suppliers!$E$2:$E$11,MATCH($D14,Suppliers!$A$2:$A$11,0)) -> India | N14: =G14*INDEX(MRP!$P$5:$P$14,MATCH($B14,MRP!$A$5:$A$14,0)) -> 266597.07 | O14: =N14*I14/Assumptions!$B$20 -> 538.52609
... A19: L18 | B19: RW10 | C19: =INDEX(RawMaterials!$B$2:$B$11,MATCH($B19,RawMaterials!$A$2:$A$11,0)) -> Corrugated Board / Cartons | D19: S10 | E19: =INDEX(Suppliers!$B$2:$B$11,MATCH($D19,Suppliers!$A$2:$A$11,0)) -> Bhiwandi Packaging Industries | F19: Sole source | G19: 1 | H19: 52 | I19: =H19*(1+INDEX(RawMaterials!$H$2:$H$11,MATCH($B19,RawMaterials!$A$2:$A$11,0))) -> 52 | J19: 6 | K19: 2000 | L19: Road | M19: =INDEX(Suppliers!$E$2:$E$11,MATCH($D19,Suppliers!$A$2:$A$11,0)) -> India | N19: =G19*INDEX(MRP!$P$5:$P$14,MATCH($B19,MRP!$A$5:$A$14,0)) -> 1529471.6 | O19: =N19*I19/Assumptions!$B$20 -> 795.32526

Sheet BOM
A1: Line ID | B1: Product ID | C1: Product | D1: Assembly module | E1: RM ID | F1: Raw material | G1: Net qty (kg / unit) | H1: Process yield | I1: Gross qty issued (kg / unit) | J1: Std price (₹ / kg) | K1: RM cost (₹ / unit) | L1: Process loss (kg / unit) | M1: Share of product RM cost | O1: Notes
A2: B001 | B2: P01 | C2: =INDEX(Products!$B$2:$B$16,MATCH($B2,Products!$A$2:$A$16,0)) -> Ceiling Fan 1200 mm - Induction | D2: Motor / coil sub-assembly | E2: RW01 | F2: =INDEX(RawMaterials!$B$2:$B$11,MATCH($E2,RawMaterials!$A$2:$A$11,0)) -> CRNGO Electrical Steel Coil | G2: 0.85 | H2: =INDEX(RawMaterials!$I$2:$I$11,MATCH($E2,RawMaterials!$A$2:$A$11,0)) -> 0.7 | I2: =G2/H2 -> 1.2142857 | J2: =INDEX(RawMaterials!$G$2:$G$11,MATCH($E2,RawMaterials!$A$2:$A$11,0)) -> 93.4 | K2: =I2*J2 -> 113.41429 | L2: =I2-G2 -> 0.36428571 | M2: =IF(SUMIFS($K$2:$K$400,$B$2:$B$400,$B2)=0,0,K2/SUMIFS($K$2:$K$400,$B$2:$B$400,$B2)) -> 0.1062346 | O2: 102 BOM lines. Net quantities are engineering estimates of the material that ends up in ONE finished unit; gross = net / process yield. Assembly modules show where each material is consumed in the build sequence: sub-assemblies first (motor, heating element, pump, jars, blades), then body, finishing and packing. Bought-out parts (electronics, bearings, switches, glass, cords) are not listed here - they are a ₹ / unit allowance on Products. To add a BOM line, type it directly below the last line (formulas read rows 2-400) and copy the formulas in columns C, F and H-M down.
A3: B002 | B3: P01 | C3: =INDEX(Products!$B$2:$B$16,MATCH($B3,Products!$A$2:$A$16,0)) -> Ceiling Fan 1200 mm - Induction | D3: Motor / coil sub-assembly | E3: RW04 | F3: =INDEX(RawMaterials!$B$2:$B$11,MATCH($E3,RawMaterials!$A$2:$A$11,0)) -> Enamelled Copper Winding Wire | G3: 0.42 | H3: =INDEX(RawMaterials!$I$2:$I$11,MATCH($E3,RawMaterials!$A$2:$A$11,0)) -> 0.98 | I3: =G3/H3 -> 0.42857143 | J3: =INDEX(RawMaterials!$G$2:$G$11,MATCH($E3,RawMaterials!$A$2:$A$11,0)) -> 1336.25 | K3: =I3*J3 -> 572.67857 | L3: =I3-G3 -> 0.0085714286 | M3: =IF(SUMIFS($K$2:$K$400,$B$2:$B$400,$B3)=0,0,K3/SUMIFS($K$2:$K$400,$B$2:$B$400,$B3)) -> 0.53642518
A4: B003 | B4: P01 | C4: =INDEX(Products!$B$2:$B$16,MATCH($B4,Products!$A$2:$A$16,0)) -> Ceiling Fan 1200 mm - Induction | D4: Motor / coil sub-assembly | E4: RW03 | F4: =INDEX(RawMaterials!$B$2:$B$11,MATCH($E4,RawMaterials!$A$2:$A$11,0)) -> Aluminium Alloy Ingot (ADC12) | G4: 0.5 | H4: =INDEX(RawMaterials!$I$2:$I$11,MATCH($E4,RawMaterials!$A$2:$A$11,0)) -> 0.92 | I4: =G4/H4 -> 0.54347826 | J4: =INDEX(RawMaterials!$G$2:$G$11,MATCH($E4,RawMaterials!$A$2:$A$11,0)) -> 261.5 | K4: =I4*J4 -> 142.11957 | L4: =I4-G4 -> 0.043478261 | M4: =IF(SUMIFS($K$2:$K$400,$B$2:$B$400,$B4)=0,0,K4/SUMIFS($K$2:$K$400,$B$2:$B$400,$B4)) -> 0.13312269
A5: B004 | B5: P01 | C5: =INDEX(Products!$B$2:$B$16,MATCH($B5,Products!$A$2:$A$16,0)) -> Ceiling Fan 1200 mm - Induction | D5: Body & structure | E5: RW02 | F5: =INDEX(RawMaterials!$B$2:$B$11,MATCH($E5,RawMaterials!$A$2:$A$11,0)) -> CRCA Steel Sheet / Coil | G5: 2.1 | H5: =INDEX(RawMaterials!$I$2:$I$11,MATCH($E5,RawMaterials!$A$2:$A$11,0)) -> 0.85 | I5: =G5/H5 -> 2.4705882 | J5: =INDEX(RawMaterials!$G$2:$G$11,MATCH($E5,RawMaterials!$A$2:$A$11,0)) -> 66.65 | K5: =I5*J5 -> 164.66471 | L5: =I5-G5 -> 0.37058824 | M5: =IF(SUMIFS($K$2:$K$400,$B$2:$B$400,$B5)=0,0,K5/SUMIFS($K$2:$K$400,$B$2:$B$400,$B5)) -> 0.15424061
A6: B005 | B6: P01 | C6: =INDEX(Products!$B$2:$B$16,MATCH($B6,Products!$A$2:$A$16,0)) -> Ceiling Fan 1200 mm - Induction | D6: Finishing (powder coat) | E6: RW09 | F6: =INDEX(RawMaterials!$B$2:$B$11,MATCH($E6,RawMaterials!$A$2:$A$11,0)) -> Powder Coating (Epoxy-Polyester) | G6: 0.08 | H6: =INDEX(RawMaterials!$I$2:$I$11,MATCH($E6,RawMaterials!$A$2:$A$11,0)) -> 0.8 | I6: =G6/H6 -> 0.1 | J6: =INDEX(RawMaterials!$G$2:$G$11,MATCH($E6,RawMaterials!$A$2:$A$11,0)) -> 345 | K6: =I6*J6 -> 34.5 | L6: =I6-G6 -> 0.02 | M6: =IF(SUMIFS($K$2:$K$400,$B$2:$B$400,$B6)=0,0,K6/SUMIFS($K$2:$K$400,$B$2:$B$400,$B6)) -> 0.032315979
A7: B006 | B7: P01 | C7: =INDEX(Products!$B$2:$B$16,MATCH($B7,Products!$A$2:$A$16,0)) -> Ceiling Fan 1200 mm - Induction | D7: Packaging | E7: RW10 | F7: =INDEX(RawMaterials!$B$2:$B$11,MATCH($E7,RawMaterials!$A$2:$A$11,0)) -> Corrugated Board / Cartons | G7: 0.75 | H7: =INDEX(RawMaterials!$I$2:$I$11,MATCH($E7,RawMaterials!$A$2:$A$11,0)) -> 0.97 | I7: =G7/H7 -> 0.77319588 | J7: =INDEX(RawMaterials!$G$2:$G$11,MATCH($E7,RawMaterials!$A$2:$A$11,0)) -> 52 | K7: =I7*J7 -> 40.206186 | L7: =I7-G7 -> 0.023195876 | M7: =IF(SUMIFS($K$2:$K$400,$B$2:$B$400,$B7)=0,0,K7/SUMIFS($K$2:$K$400,$B$2:$B$400,$B7)) -> 0.037660935
A8: B007 | B8: P02 | C8: =INDEX(Products!$B$2:$B$16,MATCH($B8,Products!$A$2:$A$16,0)) -> Ceiling Fan 1200 mm - BLDC | D8: Motor / coil sub-assembly | E8: RW01 | F8: =INDEX(RawMaterials!$B$2:$B$11,MATCH($E8,RawMaterials!$A$2:$A$11,0)) -> CRNGO Electrical Steel Coil | G8: 0.62 | H8: =INDEX(RawMaterials!$I$2:$I$11,MATCH($E8,RawMaterials!$A$2:$A$11,0)) -> 0.7 | I8: =G8/H8 -> 0.88571429 | J8: =INDEX(RawMaterials!$G$2:$G$11,MATCH($E8,RawMaterials!$A$2:$A$11,0)) -> 93.4 | K8: =I8*J8 -> 82.725714 | L8: =I8-G8 -> 0.26571429 | M8: =IF(SUMIFS($K$2:$K$400,$B$2:$B$400,$B8)=0,0,K8/SUMIFS($K$2:$K$400,$B$2:$B$400,$B8)) -> 0.094603976
A9: B008 | B9: P02 | C9: =INDEX(Products!$B$2:$B$16,MATCH($B9,Products!$A$2:$A$16,0)) -> Ceiling Fan 1200 mm - BLDC | D9: Motor / coil sub-assembly | E9: RW04 | F9: =INDEX(RawMaterials!$B$2:$B$11,MATCH($E9,RawMaterials!$A$2:$A$11,0)) -> Enamelled Copper Winding Wire | G9: 0.33 | H9: =INDEX(RawMaterials!$I$2:$I$11,MATCH($E9,RawMaterials!$A$2:$A$11,0)) -> 0.98 | I9: =G9/H9 -> 0.33673469 | J9: =INDEX(RawMaterials!$G$2:$G$11,MATCH($E9,RawMaterials!$A$2:$A$11,0)) -> 1336.25 | K9: =I9*J9 -> 449.96173 | L9: =I9-G9 -> 0.0067346939 | M9: =IF(SUMIFS($K$2:$K$400,$B$2:$B$400,$B9)=0,0,K9/SUMIFS($K$2:$K$400,$B$2:$B$400,$B9)) -> 0.51456998
A10: B009 | B10: P02 | C10: =INDEX(Products!$B$2:$B$16,MATCH($B10,Products!$A$2:$A$16,0)) -> Ceiling Fan 1200 mm - BLDC | D10: Motor / coil sub-assembly | E10: RW03 | F10: =INDEX(RawMaterials!$B$2:$B$11,MATCH($E10,RawMaterials!$A$2:$A$11,0)) -> Aluminium Alloy Ingot (ADC12) | G10: 0.45 | H10: =INDEX(RawMaterials!$I$2:$I$11,MATCH($E10,RawMaterials!$A$2:$A$11,0)) -> 0.92 | I10: =G10/H10 -> 0.48913043 | J10: =INDEX(RawMaterials!$G$2:$G$11,MATCH($E10,RawMaterials!$A$2:$A$11,0)) -> 261.5 | K10: =I10*J10 -> 127.90761 | L10: =I10-G10 -> 0.039130435 | M10: =IF(SUMIFS($K$2:$K$400,$B$2:$B$400,$B10)=0,0,K10/SUMIFS($K$2:$K$400,$B$2:$B$400,$B10)) -> 0.14627336
A11: B010 | B11: P02 | C11: =INDEX(Products!$B$2:$B$16,MATCH($B11,Products!$A$2:$A$16,0)) -> Ceiling Fan 1200 mm - BLDC | D11: Body & structure | E11: RW02 | F11: =INDEX(RawMaterials!$B$2:$B$11,MATCH($E11,RawMaterials!$A$2:$A$11,0)) -> CRCA Steel Sheet / Coil | G11: 1.85 | H11: =INDEX(RawMaterials!$I$2:$I$11,MATCH($E11,RawMaterials!$A$2:$A$11,0)) -> 0.85 | I11: =G11/H11 -> 2.1764706 | J11: =INDEX(RawMaterials!$G$2:$G$11,MATCH($E11,RawMaterials!$A$2:$A$11,0)) -> 66.65 | K11: =I11*J11 -> 145.06176 | L11: =I11-G11 -> 0.32647059 | M11: =IF(SUMIFS($K$2:$K$400,$B$2:$B$400,$B11)=0,0,K11/SUMIFS($K$2:$K$400,$B$2:$B$400,$B11)) -> 0.16589062
A12: B011 | B12: P02 | C12: =INDEX(Products!$B$2:$B$16,MATCH($B12,Products!$A$2:$A$16,0)) -> Ceiling Fan 1200 mm - BLDC | D12: Finishing (powder coat) | E12: RW09 | F12: =INDEX(RawMaterials!$B$2:$B$11,MATCH($E12,RawMaterials!$A$2:$A$11,0)) -> Powder Coating (Epoxy-Polyester) | G12: 0.07 | H12: =INDEX(RawMaterials!$I$2:$I$11,MATCH($E12,RawMaterials!$A$2:$A$11,0)) -> 0.8 | I12: =G12/H12 -> 0.0875 | J12: =INDEX(RawMaterials!$G$2:$G$11,MATCH($E12,RawMaterials!$A$2:$A$11,0)) -> 345 | K12: =I12*J12 -> 30.1875 | L12: =I12-G12 -> 0.0175 | M12: =IF(SUMIFS($K$2:$K$400,$B$2:$B$400,$B12)=0,0,K12/SUMIFS($K$2:$K$400,$B$2:$B$400,$B12)) -> 0.034522005
A13: B012 | B13: P02 | C13: =INDEX(Products!$B$2:$B$16,MATCH($B13,Products!$A$2:$A$16,0)) -> Ceiling Fan 1200 mm - BLDC | D13: Packaging | E13: RW10 | F13: =INDEX(RawMaterials!$B$2:$B$11,MATCH($E13,RawMaterials!$A$2:$A$11,0)) -> Corrugated Board / Cartons | G13: 0.72 | H13: =INDEX(RawMaterials!$I$2:$I$11,MATCH($E13,RawMaterials!$A$2:$A$11,0)) -> 0.97 | I13: =G13/H13 -> 0.74226804 | J13: =INDEX(RawMaterials!$G$2:$G$11,MATCH($E13,RawMaterials!$A$2:$A$11,0)) -> 52 | K13: =I13*J13 -> 38.597938 | L13: =I13-G13 -> 0.022268041 | M13: =IF(SUMIFS($K$2:$K$400,$B$2:$B$400,$B13)=0,0,K13/SUMIFS($K$2:$K$400,$B$2:$B$400,$B13)) -> 0.044140065
A14: B013 | B14: P03 | C14: =INDEX(Products!$B$2:$B$16,MATCH($B14,Products!$A$2:$A$16,0)) -> Pedestal Fan 400 mm | D14: Motor / coil sub-assembly | E14: RW01 | F14: =INDEX(RawMaterials!$B$2:$B$11,MATCH($E14,RawMaterials!$A$2:$A$11,0)) -> CRNGO Electrical Steel Coil | G14: 0.38 | H14: =INDEX(RawMaterials!$I$2:$I$11,MATCH($E14,RawMaterials!$A$2:$A$11,0)) -> 0.7 | I14: =G14/H14 -> 0.54285714 | J14: =INDEX(RawMaterials!$G$2:$G$11,MATCH($E14,RawMaterials!$A$2:$A$11,0)) -> 93.4 | K14: =I14*J14 -> 50.702857 | L14: =I14-G14 -> 0.16285714 | M14: =IF(SUMIFS($K$2:$K$400,$B$2:$B$400,$B14)=0,0,K14/SUMIFS($K$2:$K$400,$B$2:$B$400,$B14)) -> 0.064805707
... A103: B102 | B103: P15 | C103: =INDEX(Products!$B$2:$B$16,MATCH($B103,Products!$A$2:$A$16,0)) -> Water Pump 0.5 HP Monoblock | D103: Packaging | E103: RW10 | F103: =INDEX(RawMaterials!$B$2:$B$11,MATCH($E103,RawMaterials!$A$2:$A$11,0)) -> Corrugated Board / Cartons | G103: 0.85 | H103: =INDEX(RawMaterials!$I$2:$I$11,MATCH($E103,RawMaterials!$A$2:$A$11,0)) -> 0.97 | I103: =G103/H103 -> 0.87628866 | J103: =INDEX(RawMaterials!$G$2:$G$11,MATCH($E103,RawMaterials!$A$2:$A$11,0)) -> 52 | K103: =I103*J103 -> 45.56701 | L103: =I103-G103 -> 0.02628866 | M103: =IF(SUMIFS($K$2:$K$400,$B$2:$B$400,$B103)=0,0,K103/SUMIFS($K$2:$K$400,$B$2:$B$400,$B103)) -> 0.023613148

Sheet WorkCentres
A1: WC ID | B1: Work centre | C1: Short name | D1: Type | E1: Process | F1: Equipment | G1: Units (machines / stations) | H1: Shifts per day | I1: Hours per shift | J1: Working days / month | K1: OEE (effective output) | L1: Cost rate (₹ / unit-hour) | M1: Effective capacity (hours / month) | N1: Capacity per unit (hours / month)
A2: WC01 | B2: Press Shop | C2: Press shop | D2: Fabrication | E2: Blanking, stamping, deep-draw and lamination stamping of CRNGO / CRCA / SS304 | F2: Mechanical and hydraulic presses 63-250 t, lamination press | G2: 21 | H2: 2 | I2: 8 | J2: =Assumptions!$B$9 -> 26 | K2: 0.8 | L2: 780 | M2: =G2*H2*I2*J2*K2 -> 6988.8 | N2: =H2*I2*J2*K2 -> 332.8
A3: WC02 | B3: Aluminium Die-Casting & Machining | C3: Al die-casting | D3: Casting & machining | E3: HPDC of motor housings, end shields, plates and soleplates; fettling and machining | F3: HPDC cells 250-500 t, VMC/CNC machining | G3: 7 | H3: 3 | I3: 8 | J3: =Assumptions!$B$9 -> 26 | K3: 0.75 | L3: 2100 | M3: =G3*H3*I3*J3*K3 -> 3276 | N3: =H3*I3*J3*K3 -> 468
A4: WC03 | B4: Injection Moulding | C4: Injection moulding | D4: Moulding | E4: PP and ABS housings, blades, lids, handles and bodies | F4: Injection machines 80-1000 t, hopper dryers | G4: 8 | H4: 3 | I4: 8 | J4: =Assumptions!$B$9 -> 26 | K4: 0.8 | L4: 1300 | M4: =G4*H4*I4*J4*K4 -> 3993.6 | N4: =H4*I4*J4*K4 -> 499.2
A5: WC04 | B5: Winding & Motor / Element Sub-Assembly | C5: Winding & motor | D5: Sub-assembly | E5: Stator and armature winding, motor assembly, heating-element winding and fitting | F5: Automatic winders, motor assembly benches, element coiling | G5: 33 | H5: 2 | I5: 8 | J5: =Assumptions!$B$9 -> 26 | K5: 0.82 | L5: 420 | M5: =G5*H5*I5*J5*K5 -> 11256.96 | N5: =H5*I5*J5*K5 -> 341.12
A6: WC05 | B6: Powder-Coating Line | C6: Powder coating | D6: Finishing | E6: Pre-treatment, powder spray and curing of painted metal parts | F6: Conveyorised pre-treatment, spray booth, curing oven | G6: 1 | H6: 3 | I6: 8 | J6: =Assumptions!$B$9 -> 26 | K6: 0.78 | L6: 3300 | M6: =G6*H6*I6*J6*K6 -> 486.72 | N6: =H6*I6*J6*K6 -> 486.72
A7: WC06 | B7: FA-1 Final Assembly: Fans & Coolers | C7: FA-1 Fans & coolers | D7: Final assembly | E7: Final assembly, balancing and end-of-line test of fans and coolers | F7: Assembly stations, balancing rigs, EOL testers | G7: 55 | H7: 2 | I7: 8 | J7: =Assumptions!$B$9 -> 26 | K7: 0.85 | L7: 360 | M7: =G7*H7*I7*J7*K7 -> 19448 | N7: =H7*I7*J7*K7 -> 353.6
A8: WC07 | B8: FA-2 Final Assembly: Kitchen Appliances | C8: FA-2 Kitchen | D8: Final assembly | E8: Final assembly and electrical safety test of mixers, kettles, cooktops, sandwich makers | F8: Assembly stations, hi-pot and run-in testers | G8: 30 | H8: 2 | I8: 8 | J8: =Assumptions!$B$9 -> 26 | K8: 0.85 | L8: 360 | M8: =G8*H8*I8*J8*K8 -> 10608 | N8: =H8*I8*J8*K8 -> 353.6
A9: WC08 | B9: FA-3 Final Assembly: Heating, Personal Care & Pumps | C9: FA-3 Heating & pumps | D9: Final assembly | E9: Final assembly and test of heaters, immersion rods, irons and pumps | F9: Assembly stations, insulation and pressure testers | G9: 14 | H9: 2 | I9: 8 | J9: =Assumptions!$B$9 -> 26 | K9: 0.85 | L9: 360 | M9: =G9*H9*I9*J9*K9 -> 4950.4 | N9: =H9*I9*J9*K9 -> 353.6
A10: WC09 | B10: Packing & Dispatch | C10: Packing & dispatch | D10: Packing | E10: Carton packing, labelling, palletising and dispatch | F10: Packing tables, strapping, pallet wrappers | G10: 15 | H10: 2 | I10: 8 | J10: =Assumptions!$B$9 -> 26 | K10: 0.88 | L10: 270 | M10: =G10*H10*I10*J10*K10 -> 5491.2 | N10: =H10*I10*J10*K10 -> 366.08
A12: Effective capacity = units x shifts x hours per shift x working days x OEE. Cost rate is an all-in conversion rate per machine- or station-hour (labour, power, maintenance, depreciation, overhead) - an estimate for planning, not an accounting rate.
A13: Casting, moulding and powder coating run 3 shifts because they are capital-intensive; the other centres run 2 shifts, leaving a 3rd shift or overtime as the lever for seasonal peaks.

Sheet Routing
A1: Routing - standard minutes per unit at each work centre
A2: Blue minutes are engineering estimates scaled to the material each product pushes through the process. 'Own final-assembly line' must be > 0 for every product (checked).
A3: Work centre | C3: =WorkCentres!$C$2 -> Press shop | D3: =WorkCentres!$C$3 -> Al die-casting | E3: =WorkCentres!$C$4 -> Injection moulding | F3: =WorkCentres!$C$5 -> Winding & motor | G3: =WorkCentres!$C$6 -> Powder coating | H3: =WorkCentres!$C$7 -> FA-1 Fans & coolers | I3: =WorkCentres!$C$8 -> FA-2 Kitchen | J3: =WorkCentres!$C$9 -> FA-3 Heating & pumps | K3: =WorkCentres!$C$10 -> Packing & dispatch
A4: Product ID | B4: Product | C4: WC01 | D4: WC02 | E4: WC03 | F4: WC04 | G4: WC05 | H4: WC06 | I4: WC07 | J4: WC08 | K4: WC09 | L4: Total minutes / unit | M4: Own final-assembly line (min)
A5: Cost rate (₹ / unit-hour) | C5: =WorkCentres!$L$2 -> 780 | D5: =WorkCentres!$L$3 -> 2100 | E5: =WorkCentres!$L$4 -> 1300 | F5: =WorkCentres!$L$5 -> 420 | G5: =WorkCentres!$L$6 -> 3300 | H5: =WorkCentres!$L$7 -> 360 | I5: =WorkCentres!$L$8 -> 360 | J5: =WorkCentres!$L$9 -> 360 | K5: =WorkCentres!$L$10 -> 270
A6: P01 | B6: =INDEX(Products!$B$2:$B$16,MATCH($A6,Products!$A$2:$A$16,0)) -> Ceiling Fan 1200 mm - Induction | C6: 2.71 | D6: 1.05 | E6: 0 | F6: 3.53 | G6: 0.23 | H6: 8.5 | I6: 0 | J6: 0 | K6: 1.25 | L6: =SUM(C6:K6) -> 17.27 | M6: =SUMIF($C$4:$K$4,INDEX(Products!$E$2:$E$16,MATCH($A6,Products!$A$2:$A$16,0)),C6:K6) -> 8.5
A7: P02 | B7: =INDEX(Products!$B$2:$B$16,MATCH($A7,Products!$A$2:$A$16,0)) -> Ceiling Fan 1200 mm - BLDC | C7: 2.28 | D7: 0.97 | E7: 0 | F7: 2.95 | G7: 0.2 | H7: 9.5 | I7: 0 | J7: 0 | K7: 1.22 | L7: =SUM(C7:K7) -> 17.12 | M7: =SUMIF($C$4:$K$4,INDEX(Products!$E$2:$E$16,MATCH($A7,Products!$A$2:$A$16,0)),C7:K7) -> 9.5
A8: P03 | B8: =INDEX(Products!$B$2:$B$16,MATCH($A8,Products!$A$2:$A$16,0)) -> Pedestal Fan 400 mm | C8: 1.8 | D8: 0.74 | E8: 1.08 | F8: 2.36 | G8: 0.2 | H8: 8 | I8: 0 | J8: 0 | K8: 1.7 | L8: =SUM(C8:K8) -> 15.88 | M8: =SUMIF($C$4:$K$4,INDEX(Products!$E$2:$E$16,MATCH($A8,Products!$A$2:$A$16,0)),C8:K8) -> 8
A9: P04 | B9: =INDEX(Products!$B$2:$B$16,MATCH($A9,Products!$A$2:$A$16,0)) -> Table Fan 400 mm | C9: 1.16 | D9: 0.54 | E9: 1.05 | F9: 2.04 | G9: 0.12 | H9: 6 | I9: 0 | J9: 0 | K9: 1.1 | L9: =SUM(C9:K9) -> 12.01 | M9: =SUMIF($C$4:$K$4,INDEX(Products!$E$2:$E$16,MATCH($A9,Products!$A$2:$A$16,0)),C9:K9) -> 6
A10: P05 | B10: =INDEX(Products!$B$2:$B$16,MATCH($A10,Products!$A$2:$A$16,0)) -> Exhaust Fan 230 mm | C10: 0.79 | D10: 0.34 | E10: 0.96 | F10: 1.39 | G10: 0.09 | H10: 4 | I10: 0 | J10: 0 | K10: 0.9 | L10: =SUM(C10:K10) -> 8.47 | M10: =SUMIF($C$4:$K$4,INDEX(Products!$E$2:$E$16,MATCH($A10,Products!$A$2:$A$16,0)),C10:K10) -> 4
A11: P06 | B11: =INDEX(Products!$B$2:$B$16,MATCH($A11,Products!$A$2:$A$16,0)) -> Personal Air Cooler 30 L | C11: 0.79 | D11: 0.37 | E11: 5.55 | F11: 1.58 | G11: 0 | H11: 9 | I11: 0 | J11: 0 | K11: 2.1 | L11: =SUM(C11:K11) -> 19.39 | M11: =SUMIF($C$4:$K$4,INDEX(Products!$E$2:$E$16,MATCH($A11,Products!$A$2:$A$16,0)),C11:K11) -> 9
A12: P07 | B12: =INDEX(Products!$B$2:$B$16,MATCH($A12,Products!$A$2:$A$16,0)) -> Mixer Grinder 500 W | C12: 1.42 | D12: 0.79 | E12: 1.24 | F12: 2.23 | G12: 0 | H12: 0 | I12: 7.5 | J12: 0 | K12: 1.05 | L12: =SUM(C12:K12) -> 14.23 | M12: =SUMIF($C$4:$K$4,INDEX(Products!$E$2:$E$16,MATCH($A12,Products!$A$2:$A$16,0)),C12:K12) -> 7.5
A13: P08 | B13: =INDEX(Products!$B$2:$B$16,MATCH($A13,Products!$A$2:$A$16,0)) -> Mixer Grinder 750 W | C13: 1.79 | D13: 1.02 | E13: 1.36 | F13: 2.75 | G13: 0 | H13: 0 | I13: 8 | J13: 0 | K13: 1.12 | L13: =SUM(C13:K13) -> 16.04 | M13: =SUMIF($C$4:$K$4,INDEX(Products!$E$2:$E$16,MATCH($A13,Products!$A$2:$A$16,0)),C13:K13) -> 8
A14: P09 | B14: =INDEX(Products!$B$2:$B$16,MATCH($A14,Products!$A$2:$A$16,0)) -> Electric Kettle 1.5 L | C14: 0.68 | D14: 0 | E14: 0.71 | F14: 1.06 | G14: 0 | H14: 0 | I14: 3.5 | J14: 0 | K14: 0.83 | L14: =SUM(C14:K14) -> 6.78 | M14: =SUMIF($C$4:$K$4,INDEX(Products!$E$2:$E$16,MATCH($A14,Products!$A$2:$A$16,0)),C14:K14) -> 3.5
A15: P10 | B15: =INDEX(Products!$B$2:$B$16,MATCH($A15,Products!$A$2:$A$16,0)) -> Induction Cooktop 2000 W | C15: 0.86 | D15: 0.51 | E15: 0.75 | F15: 1.58 | G15: 0.09 | H15: 0 | I15: 6.5 | J15: 0 | K15: 0.95 | L15: =SUM(C15:K15) -> 11.24 | M15: =SUMIF($C$4:$K$4,INDEX(Products!$E$2:$E$16,MATCH($A15,Products!$A$2:$A$16,0)),C15:K15) -> 6.5
A16: P11 | B16: =INDEX(Products!$B$2:$B$16,MATCH($A16,Products!$A$2:$A$16,0)) -> Sandwich Maker 750 W | C16: 0.54 | D16: 1.14 | E16: 0.64 | F16: 1.37 | G16: 0 | H16: 0 | I16: 3.8 | J16: 0 | K16: 0.83 | L16: =SUM(C16:K16) -> 8.32 | M16: =SUMIF($C$4:$K$4,INDEX(Products!$E$2:$E$16,MATCH($A16,Products!$A$2:$A$16,0)),C16:K16) -> 3.8
A17: P12 | B17: =INDEX(Products!$B$2:$B$16,MATCH($A17,Products!$A$2:$A$16,0)) -> Fan Room Heater 2000 W | C17: 1.13 | D17: 0.4 | E17: 1 | F17: 2.23 | G17: 0.14 | H17: 0 | I17: 0 | J17: 6 | K17: 1.05 | L17: =SUM(C17:K17) -> 11.95 | M17: =SUMIF($C$4:$K$4,INDEX(Products!$E$2:$E$16,MATCH($A17,Products!$A$2:$A$16,0)),C17:K17) -> 6
... A20: P15 | B20: =INDEX(Products!$B$2:$B$16,MATCH($A20,Products!$A$2:$A$16,0)) -> Water Pump 0.5 HP Monoblock | C20: 3.15 | D20: 2.41 | E20: 0.64 | F20: 6 | G20: 0.18 | H20: 0 | I20: 0 | J20: 10.5 | K20: 1.35 | L20: =SUM(C20:K20) -> 24.23 | M20: =SUMIF($C$4:$K$4,INDEX(Products!$E$2:$E$16,MATCH($A20,Products!$A$2:$A$16,0)),C20:K20) -> 10.5
A21: Products routed (#) | C21: =COUNTIF(C6:C20,">0") -> 15 | D21: =COUNTIF(D6:D20,">0") -> 13 | E21: =COUNTIF(E6:E20,">0") -> 13 | F21: =COUNTIF(F6:F20,">0") -> 15 | G21: =COUNTIF(G6:G20,">0") -> 8 | H21: =COUNTIF(H6:H20,">0") -> 6 | I21: =COUNTIF(I6:I20,">0") -> 5 | J21: =COUNTIF(J6:J20,">0") -> 4 | K21: =COUNTIF(K6:K20,">0") -> 15 | L21: =AVERAGE(L6:L20) -> 13.012
A23: Conversion cost build-up (₹ per unit) = minutes x cost rate / 60
A24: Product ID | B24: Product | C24: WC01 | D24: WC02 | E24: WC03 | F24: WC04 | G24: WC05 | H24: WC06 | I24: WC07 | J24: WC08 | K24: WC09 | L24: Conversion cost (₹ / unit)
A25: =A6 -> P01 | B25: =B6 -> Ceiling Fan 1200 mm - Induction | C25: =C6*C$5/60 -> 35.23 | D25: =D6*D$5/60 -> 36.75 | E25: =E6*E$5/60 -> 0 | F25: =F6*F$5/60 -> 24.71 | G25: =G6*G$5/60 -> 12.65 | H25: =H6*H$5/60 -> 51 | I25: =I6*I$5/60 -> 0 | J25: =J6*J$5/60 -> 0 | K25: =K6*K$5/60 -> 5.625 | L25: =SUM(C25:K25) -> 165.965
A26: =A7 -> P02 | B26: =B7 -> Ceiling Fan 1200 mm - BLDC | C26: =C7*C$5/60 -> 29.64 | D26: =D7*D$5/60 -> 33.95 | E26: =E7*E$5/60 -> 0 | F26: =F7*F$5/60 -> 20.65 | G26: =G7*G$5/60 -> 11 | H26: =H7*H$5/60 -> 57 | I26: =I7*I$5/60 -> 0 | J26: =J7*J$5/60 -> 0 | K26: =K7*K$5/60 -> 5.49 | L26: =SUM(C26:K26) -> 157.73
A27: =A8 -> P03 | B27: =B8 -> Pedestal Fan 400 mm | C27: =C8*C$5/60 -> 23.4 | D27: =D8*D$5/60 -> 25.9 | E27: =E8*E$5/60 -> 23.4 | F27: =F8*F$5/60 -> 16.52 | G27: =G8*G$5/60 -> 11 | H27: =H8*H$5/60 -> 48 | I27: =I8*I$5/60 -> 0 | J27: =J8*J$5/60 -> 0 | K27: =K8*K$5/60 -> 7.65 | L27: =SUM(C27:K27) -> 155.87
A28: =A9 -> P04 | B28: =B9 -> Table Fan 400 mm | C28: =C9*C$5/60 -> 15.08 | D28: =D9*D$5/60 -> 18.9 | E28: =E9*E$5/60 -> 22.75 | F28: =F9*F$5/60 -> 14.28 | G28: =G9*G$5/60 -> 6.6 | H28: =H9*H$5/60 -> 36 | I28: =I9*I$5/60 -> 0 | J28: =J9*J$5/60 -> 0 | K28: =K9*K$5/60 -> 4.95 | L28: =SUM(C28:K28) -> 118.56
A29: =A10 -> P05 | B29: =B10 -> Exhaust Fan 230 mm | C29: =C10*C$5/60 -> 10.27 | D29: =D10*D$5/60 -> 11.9 | E29: =E10*E$5/60 -> 20.8 | F29: =F10*F$5/60 -> 9.73 | G29: =G10*G$5/60 -> 4.95 | H29: =H10*H$5/60 -> 24 | I29: =I10*I$5/60 -> 0 | J29: =J10*J$5/60 -> 0 | K29: =K10*K$5/60 -> 4.05 | L29: =SUM(C29:K29) -> 85.7
A30: =A11 -> P06 | B30: =B11 -> Personal Air Cooler 30 L | C30: =C11*C$5/60 -> 10.27 | D30: =D11*D$5/60 -> 12.95 | E30: =E11*E$5/60 -> 120.25 | F30: =F11*F$5/60 -> 11.06 | G30: =G11*G$5/60 -> 0 | H30: =H11*H$5/60 -> 54 | I30: =I11*I$5/60 -> 0 | J30: =J11*J$5/60 -> 0 | K30: =K11*K$5/60 -> 9.45 | L30: =SUM(C30:K30) -> 217.98
A31: =A12 -> P07 | B31: =B12 -> Mixer Grinder 500 W | C31: =C12*C$5/60 -> 18.46 | D31: =D12*D$5/60 -> 27.65 | E31: =E12*E$5/60 -> 26.866667 | F31: =F12*F$5/60 -> 15.61 | G31: =G12*G$5/60 -> 0 | H31: =H12*H$5/60 -> 0 | I31: =I12*I$5/60 -> 45 | J31: =J12*J$5/60 -> 0 | K31: =K12*K$5/60 -> 4.725 | L31: =SUM(C31:K31) -> 138.31167
A32: =A13 -> P08 | B32: =B13 -> Mixer Grinder 750 W | C32: =C13*C$5/60 -> 23.27 | D32: =D13*D$5/60 -> 35.7 | E32: =E13*E$5/60 -> 29.466667 | F32: =F13*F$5/60 -> 19.25 | G32: =G13*G$5/60 -> 0 | H32: =H13*H$5/60 -> 0 | I32: =I13*I$5/60 -> 48 | J32: =J13*J$5/60 -> 0 | K32: =K13*K$5/60 -> 5.04 | L32: =SUM(C32:K32) -> 160.72667
A33: =A14 -> P09 | B33: =B14 -> Electric Kettle 1.5 L | C33: =C14*C$5/60 -> 8.84 | D33: =D14*D$5/60 -> 0 | E33: =E14*E$5/60 -> 15.383333 | F33: =F14*F$5/60 -> 7.42 | G33: =G14*G$5/60 -> 0 | H33: =H14*H$5/60 -> 0 | I33: =I14*I$5/60 -> 21 | J33: =J14*J$5/60 -> 0 | K33: =K14*K$5/60 -> 3.735 | L33: =SUM(C33:K33) -> 56.378333
A34: =A15 -> P10 | B34: =B15 -> Induction Cooktop 2000 W | C34: =C15*C$5/60 -> 11.18 | D34: =D15*D$5/60 -> 17.85 | E34: =E15*E$5/60 -> 16.25 | F34: =F15*F$5/60 -> 11.06 | G34: =G15*G$5/60 -> 4.95 | H34: =H15*H$5/60 -> 0 | I34: =I15*I$5/60 -> 39 | J34: =J15*J$5/60 -> 0 | K34: =K15*K$5/60 -> 4.275 | L34: =SUM(C34:K34) -> 104.565
A35: =A16 -> P11 | B35: =B16 -> Sandwich Maker 750 W | C35: =C16*C$5/60 -> 7.02 | D35: =D16*D$5/60 -> 39.9 | E35: =E16*E$5/60 -> 13.866667 | F35: =F16*F$5/60 -> 9.59 | G35: =G16*G$5/60 -> 0 | H35: =H16*H$5/60 -> 0 | I35: =I16*I$5/60 -> 22.8 | J35: =J16*J$5/60 -> 0 | K35: =K16*K$5/60 -> 3.735 | L35: =SUM(C35:K35) -> 96.911667
A36: =A17 -> P12 | B36: =B17 -> Fan Room Heater 2000 W | C36: =C17*C$5/60 -> 14.69 | D36: =D17*D$5/60 -> 14 | E36: =E17*E$5/60 -> 21.666667 | F36: =F17*F$5/60 -> 15.61 | G36: =G17*G$5/60 -> 7.7 | H36: =H17*H$5/60 -> 0 | I36: =I17*I$5/60 -> 0 | J36: =J17*J$5/60 -> 36 | K36: =K17*K$5/60 -> 4.725 | L36: =SUM(C36:K36) -> 114.39167
... A39: =A20 -> P15 | B39: =B20 -> Water Pump 0.5 HP Monoblock | C39: =C20*C$5/60 -> 40.95 | D39: =D20*D$5/60 -> 84.35 | E39: =E20*E$5/60 -> 13.866667 | F39: =F20*F$5/60 -> 42 | G39: =G20*G$5/60 -> 9.9 | H39: =H20*H$5/60 -> 0 | I39: =I20*I$5/60 -> 0 | J39: =J20*J$5/60 -> 63 | K39: =K20*K$5/60 -> 6.075 | L39: =SUM(C39:K39) -> 260.14167
A41: Heuristic used to set minutes: press = 0.30 + 0.70 x CRCA kg + 0.90 x SS304 kg + 1.10 x CRNGO kg; die-casting = 0.20 + 1.70 x aluminium kg; moulding = 0.35 + 1.05 x plastic kg; winding = 0.80 + 6.5 x copper kg + 22 x nichrome kg; powder coat = 0.05 + 2.2 x powder kg; packing = 0.50 + 1.0 x carton kg. Final-assembly minutes are set per product.
A42: These are planning estimates for a fictional plant; replace with time-study or ERP routing data for a real one.

Sheet BOM_Matrix
A1: BOM matrix - which raw materials go into which product
A2: All cells are formulas over the BOM sheet. Rows = products, columns = raw materials. Use it to see material intensity at a glance.
A3: A. Net material per finished unit (kg) - what ends up inside the product
C4: =RawMaterials!$C$2 -> CRNGO steel coil | D4: =RawMaterials!$C$3 -> CRCA steel sheet | E4: =RawMaterials!$C$4 -> Aluminium ADC12 | F4: =RawMaterials!$C$5 -> Copper winding wire | G4: =RawMaterials!$C$6 -> PP granules | H4: =RawMaterials!$C$7 -> ABS granules | I4: =RawMaterials!$C$8 -> SS304 sheet | J4: =RawMaterials!$C$9 -> Nichrome wire | K4: =RawMaterials!$C$10 -> Powder coating | L4: =RawMaterials!$C$11 -> Corrugated cartons
A5: Product ID | B5: Product | C5: RW01 | D5: RW02 | E5: RW03 | F5: RW04 | G5: RW05 | H5: RW06 | I5: RW07 | J5: RW08 | K5: RW09 | L5: RW10 | M5: Total net (kg) | N5: Materials used (#)
A6: P01 | B6: =INDEX(Products!$B$2:$B$16,MATCH($A6,Products!$A$2:$A$16,0)) -> Ceiling Fan 1200 mm - Induction | C6: =SUMIFS(BOM!$G$2:$G$400,BOM!$B$2:$B$400,$A6,BOM!$E$2:$E$400,C$5) -> 0.85 | D6: =SUMIFS(BOM!$G$2:$G$400,BOM!$B$2:$B$400,$A6,BOM!$E$2:$E$400,D$5) -> 2.1 | E6: =SUMIFS(BOM!$G$2:$G$400,BOM!$B$2:$B$400,$A6,BOM!$E$2:$E$400,E$5) -> 0.5 | F6: =SUMIFS(BOM!$G$2:$G$400,BOM!$B$2:$B$400,$A6,BOM!$E$2:$E$400,F$5) -> 0.42 | G6: =SUMIFS(BOM!$G$2:$G$400,BOM!$B$2:$B$400,$A6,BOM!$E$2:$E$400,G$5) -> 0 | H6: =SUMIFS(BOM!$G$2:$G$400,BOM!$B$2:$B$400,$A6,BOM!$E$2:$E$400,H$5) -> 0 | I6: =SUMIFS(BOM!$G$2:$G$400,BOM!$B$2:$B$400,$A6,BOM!$E$2:$E$400,I$5) -> 0 | J6: =SUMIFS(BOM!$G$2:$G$400,BOM!$B$2:$B$400,$A6,BOM!$E$2:$E$400,J$5) -> 0 | ... L6: =SUMIFS(BOM!$G$2:$G$400,BOM!$B$2:$B$400,$A6,BOM!$E$2:$E$400,L$5) -> 0.75 | M6: =SUM(C6:L6) -> 4.7 | N6: =COUNTIF(C6:L6,">0") -> 6
A7: P02 | B7: =INDEX(Products!$B$2:$B$16,MATCH($A7,Products!$A$2:$A$16,0)) -> Ceiling Fan 1200 mm - BLDC | C7: =SUMIFS(BOM!$G$2:$G$400,BOM!$B$2:$B$400,$A7,BOM!$E$2:$E$400,C$5) -> 0.62 | D7: =SUMIFS(BOM!$G$2:$G$400,BOM!$B$2:$B$400,$A7,BOM!$E$2:$E$400,D$5) -> 1.85 | E7: =SUMIFS(BOM!$G$2:$G$400,BOM!$B$2:$B$400,$A7,BOM!$E$2:$E$400,E$5) -> 0.45 | F7: =SUMIFS(BOM!$G$2:$G$400,BOM!$B$2:$B$400,$A7,BOM!$E$2:$E$400,F$5) -> 0.33 | G7: =SUMIFS(BOM!$G$2:$G$400,BOM!$B$2:$B$400,$A7,BOM!$E$2:$E$400,G$5) -> 0 | H7: =SUMIFS(BOM!$G$2:$G$400,BOM!$B$2:$B$400,$A7,BOM!$E$2:$E$400,H$5) -> 0 | I7: =SUMIFS(BOM!$G$2:$G$400,BOM!$B$2:$B$400,$A7,BOM!$E$2:$E$400,I$5) -> 0 | J7: =SUMIFS(BOM!$G$2:$G$400,BOM!$B$2:$B$400,$A7,BOM!$E$2:$E$400,J$5) -> 0 | ... L7: =SUMIFS(BOM!$G$2:$G$400,BOM!$B$2:$B$400,$A7,BOM!$E$2:$E$400,L$5) -> 0.72 | M7: =SUM(C7:L7) -> 4.04 | N7: =COUNTIF(C7:L7,">0") -> 6
A8: P03 | B8: =INDEX(Products!$B$2:$B$16,MATCH($A8,Products!$A$2:$A$16,0)) -> Pedestal Fan 400 mm | C8: =SUMIFS(BOM!$G$2:$G$400,BOM!$B$2:$B$400,$A8,BOM!$E$2:$E$400,C$5) -> 0.38 | D8: =SUMIFS(BOM!$G$2:$G$400,BOM!$B$2:$B$400,$A8,BOM!$E$2:$E$400,D$5) -> 1.55 | E8: =SUMIFS(BOM!$G$2:$G$400,BOM!$B$2:$B$400,$A8,BOM!$E$2:$E$400,E$5) -> 0.32 | F8: =SUMIFS(BOM!$G$2:$G$400,BOM!$B$2:$B$400,$A8,BOM!$E$2:$E$400,F$5) -> 0.24 | G8: =SUMIFS(BOM!$G$2:$G$400,BOM!$B$2:$B$400,$A8,BOM!$E$2:$E$400,G$5) -> 0.3 | H8: =SUMIFS(BOM!$G$2:$G$400,BOM!$B$2:$B$400,$A8,BOM!$E$2:$E$400,H$5) -> 0.4 | I8: =SUMIFS(BOM!$G$2:$G$400,BOM!$B$2:$B$400,$A8,BOM!$E$2:$E$400,I$5) -> 0 | J8: =SUMIFS(BOM!$G$2:$G$400,BOM!$B$2:$B$400,$A8,BOM!$E$2:$E$400,J$5) -> 0 | ... L8: =SUMIFS(BOM!$G$2:$G$400,BOM!$B$2:$B$400,$A8,BOM!$E$2:$E$400,L$5) -> 1.2 | M8: =SUM(C8:L8) -> 4.46 | N8: =COUNTIF(C8:L8,">0") -> 8
A9: P04 | B9: =INDEX(Products!$B$2:$B$16,MATCH($A9,Products!$A$2:$A$16,0)) -> Table Fan 400 mm | C9: =SUMIFS(BOM!$G$2:$G$400,BOM!$B$2:$B$400,$A9,BOM!$E$2:$E$400,C$5) -> 0.3 | D9: =SUMIFS(BOM!$G$2:$G$400,BOM!$B$2:$B$400,$A9,BOM!$E$2:$E$400,D$5) -> 0.75 | E9: =SUMIFS(BOM!$G$2:$G$400,BOM!$B$2:$B$400,$A9,BOM!$E$2:$E$400,E$5) -> 0.2 | F9: =SUMIFS(BOM!$G$2:$G$400,BOM!$B$2:$B$400,$A9,BOM!$E$2:$E$400,F$5) -> 0.19 | G9: =SUMIFS(BOM!$G$2:$G$400,BOM!$B$2:$B$400,$A9,BOM!$E$2:$E$400,G$5) -> 0.25 | H9: =SUMIFS(BOM!$G$2:$G$400,BOM!$B$2:$B$400,$A9,BOM!$E$2:$E$400,H$5) -> 0.42 | I9: =SUMIFS(BOM!$G$2:$G$400,BOM!$B$2:$B$400,$A9,BOM!$E$2:$E$400,I$5) -> 0 | J9: =SUMIFS(BOM!$G$2:$G$400,BOM!$B$2:$B$400,$A9,BOM!$E$2:$E$400,J$5) -> 0 | ... L9: =SUMIFS(BOM!$G$2:$G$400,BOM!$B$2:$B$400,$A9,BOM!$E$2:$E$400,L$5) -> 0.6 | M9: =SUM(C9:L9) -> 2.74 | N9: =COUNTIF(C9:L9,">0") -> 8
A10: P05 | B10: =INDEX(Products!$B$2:$B$16,MATCH($A10,Products!$A$2:$A$16,0)) -> Exhaust Fan 230 mm | C10: =SUMIFS(BOM!$G$2:$G$400,BOM!$B$2:$B$400,$A10,BOM!$E$2:$E$400,C$5) -> 0.16 | D10: =SUMIFS(BOM!$G$2:$G$400,BOM!$B$2:$B$400,$A10,BOM!$E$2:$E$400,D$5) -> 0.45 | E10: =SUMIFS(BOM!$G$2:$G$400,BOM!$B$2:$B$400,$A10,BOM!$E$2:$E$400,E$5) -> 0.08 | F10: =SUMIFS(BOM!$G$2:$G$400,BOM!$B$2:$B$400,$A10,BOM!$E$2:$E$400,F$5) -> 0.09 | G10: =SUMIFS(BOM!$G$2:$G$400,BOM!$B$2:$B$400,$A10,BOM!$E$2:$E$400,G$5) -> 0.2 | H10: =SUMIFS(BOM!$G$2:$G$400,BOM!$B$2:$B$400,$A10,BOM!$E$2:$E$400,H$5) -> 0.38 | I10: =SUMIFS(BOM!$G$2:$G$400,BOM!$B$2:$B$400,$A10,BOM!$E$2:$E$400,I$5) -> 0 | J10: =SUMIFS(BOM!$G$2:$G$400,BOM!$B$2:$B$400,$A10,BOM!$E$2:$E$400,J$5) -> 0 | ... L10: =SUMIFS(BOM!$G$2:$G$400,BOM!$B$2:$B$400,$A10,BOM!$E$2:$E$400,L$5) -> 0.4 | M10: =SUM(C10:L10) -> 1.78 | N10: =COUNTIF(C10:L10,">0") -> 8
A11: P06 | B11: =INDEX(Products!$B$2:$B$16,MATCH($A11,Products!$A$2:$A$16,0)) -> Personal Air Cooler 30 L | C11: =SUMIFS(BOM!$G$2:$G$400,BOM!$B$2:$B$400,$A11,BOM!$E$2:$E$400,C$5) -> 0.22 | D11: =SUMIFS(BOM!$G$2:$G$400,BOM!$B$2:$B$400,$A11,BOM!$E$2:$E$400,D$5) -> 0.35 | E11: =SUMIFS(BOM!$G$2:$G$400,BOM!$B$2:$B$400,$A11,BOM!$E$2:$E$400,E$5) -> 0.1 | F11: =SUMIFS(BOM!$G$2:$G$400,BOM!$B$2:$B$400,$A11,BOM!$E$2:$E$400,F$5) -> 0.12 | G11: =SUMIFS(BOM!$G$2:$G$400,BOM!$B$2:$B$400,$A11,BOM!$E$2:$E$400,G$5) -> 4.6 | H11: =SUMIFS(BOM!$G$2:$G$400,BOM!$B$2:$B$400,$A11,BOM!$E$2:$E$400,H$5) -> 0.35 | I11: =SUMIFS(BOM!$G$2:$G$400,BOM!$B$2:$B$400,$A11,BOM!$E$2:$E$400,I$5) -> 0 | J11: =SUMIFS(BOM!$G$2:$G$400,BOM!$B$2:$B$400,$A11,BOM!$E$2:$E$400,J$5) -> 0 | ... L11: =SUMIFS(BOM!$G$2:$G$400,BOM!$B$2:$B$400,$A11,BOM!$E$2:$E$400,L$5) -> 1.6 | M11: =SUM(C11:L11) -> 7.34 | N11: =COUNTIF(C11:L11,">0") -> 7
A12: P07 | B12: =INDEX(Products!$B$2:$B$16,MATCH($A12,Products!$A$2:$A$16,0)) -> Mixer Grinder 500 W | C12: =SUMIFS(BOM!$G$2:$G$400,BOM!$B$2:$B$400,$A12,BOM!$E$2:$E$400,C$5) -> 0.45 | D12: =SUMIFS(BOM!$G$2:$G$400,BOM!$B$2:$B$400,$A12,BOM!$E$2:$E$400,D$5) -> 0.12 | E12: =SUMIFS(BOM!$G$2:$G$400,BOM!$B$2:$B$400,$A12,BOM!$E$2:$E$400,E$5) -> 0.35 | F12: =SUMIFS(BOM!$G$2:$G$400,BOM!$B$2:$B$400,$A12,BOM!$E$2:$E$400,F$5) -> 0.22 | G12: =SUMIFS(BOM!$G$2:$G$400,BOM!$B$2:$B$400,$A12,BOM!$E$2:$E$400,G$5) -> 0.3 | H12: =SUMIFS(BOM!$G$2:$G$400,BOM!$B$2:$B$400,$A12,BOM!$E$2:$E$400,H$5) -> 0.55 | I12: =SUMIFS(BOM!$G$2:$G$400,BOM!$B$2:$B$400,$A12,BOM!$E$2:$E$400,I$5) -> 0.6 | J12: =SUMIFS(BOM!$G$2:$G$400,BOM!$B$2:$B$400,$A12,BOM!$E$2:$E$400,J$5) -> 0 | ... L12: =SUMIFS(BOM!$G$2:$G$400,BOM!$B$2:$B$400,$A12,BOM!$E$2:$E$400,L$5) -> 0.55 | M12: =SUM(C12:L12) -> 3.14 | N12: =COUNTIF(C12:L12,">0") -> 8
A13: P08 | B13: =INDEX(Products!$B$2:$B$16,MATCH($A13,Products!$A$2:$A$16,0)) -> Mixer Grinder 750 W | C13: =SUMIFS(BOM!$G$2:$G$400,BOM!$B$2:$B$400,$A13,BOM!$E$2:$E$400,C$5) -> 0.62 | D13: =SUMIFS(BOM!$G$2:$G$400,BOM!$B$2:$B$400,$A13,BOM!$E$2:$E$400,D$5) -> 0.15 | E13: =SUMIFS(BOM!$G$2:$G$400,BOM!$B$2:$B$400,$A13,BOM!$E$2:$E$400,E$5) -> 0.48 | F13: =SUMIFS(BOM!$G$2:$G$400,BOM!$B$2:$B$400,$A13,BOM!$E$2:$E$400,F$5) -> 0.3 | G13: =SUMIFS(BOM!$G$2:$G$400,BOM!$B$2:$B$400,$A13,BOM!$E$2:$E$400,G$5) -> 0.34 | H13: =SUMIFS(BOM!$G$2:$G$400,BOM!$B$2:$B$400,$A13,BOM!$E$2:$E$400,H$5) -> 0.62 | I13: =SUMIFS(BOM!$G$2:$G$400,BOM!$B$2:$B$400,$A13,BOM!$E$2:$E$400,I$5) -> 0.78 | J13: =SUMIFS(BOM!$G$2:$G$400,BOM!$B$2:$B$400,$A13,BOM!$E$2:$E$400,J$5) -> 0 | ... L13: =SUMIFS(BOM!$G$2:$G$400,BOM!$B$2:$B$400,$A13,BOM!$E$2:$E$400,L$5) -> 0.62 | M13: =SUM(C13:L13) -> 3.91 | N13: =COUNTIF(C13:L13,">0") -> 8
A14: P09 | B14: =INDEX(Products!$B$2:$B$16,MATCH($A14,Products!$A$2:$A$16,0)) -> Electric Kettle 1.5 L | C14: =SUMIFS(BOM!$G$2:$G$400,BOM!$B$2:$B$400,$A14,BOM!$E$2:$E$400,C$5) -> 0 | D14: =SUMIFS(BOM!$G$2:$G$400,BOM!$B$2:$B$400,$A14,BOM!$E$2:$E$400,D$5) -> 0 | E14: =SUMIFS(BOM!$G$2:$G$400,BOM!$B$2:$B$400,$A14,BOM!$E$2:$E$400,E$5) -> 0 | F14: =SUMIFS(BOM!$G$2:$G$400,BOM!$B$2:$B$400,$A14,BOM!$E$2:$E$400,F$5) -> 0 | G14: =SUMIFS(BOM!$G$2:$G$400,BOM!$B$2:$B$400,$A14,BOM!$E$2:$E$400,G$5) -> 0.14 | H14: =SUMIFS(BOM!$G$2:$G$400,BOM!$B$2:$B$400,$A14,BOM!$E$2:$E$400,H$5) -> 0.2 | I14: =SUMIFS(BOM!$G$2:$G$400,BOM!$B$2:$B$400,$A14,BOM!$E$2:$E$400,I$5) -> 0.42 | J14: =SUMIFS(BOM!$G$2:$G$400,BOM!$B$2:$B$400,$A14,BOM!$E$2:$E$400,J$5) -> 0.012 | ... L14: =SUMIFS(BOM!$G$2:$G$400,BOM!$B$2:$B$400,$A14,BOM!$E$2:$E$400,L$5) -> 0.33 | M14: =SUM(C14:L14) -> 1.102 | N14: =COUNTIF(C14:L14,">0") -> 5
A15: P10 | B15: =INDEX(Products!$B$2:$B$16,MATCH($A15,Products!$A$2:$A$16,0)) -> Induction Cooktop 2000 W | C15: =SUMIFS(BOM!$G$2:$G$400,BOM!$B$2:$B$400,$A15,BOM!$E$2:$E$400,C$5) -> 0 | D15: =SUMIFS(BOM!$G$2:$G$400,BOM!$B$2:$B$400,$A15,BOM!$E$2:$E$400,D$5) -> 0.8 | E15: =SUMIFS(BOM!$G$2:$G$400,BOM!$B$2:$B$400,$A15,BOM!$E$2:$E$400,E$5) -> 0.18 | F15: =SUMIFS(BOM!$G$2:$G$400,BOM!$B$2:$B$400,$A15,BOM!$E$2:$E$400,F$5) -> 0.12 | G15: =SUMIFS(BOM!$G$2:$G$400,BOM!$B$2:$B$400,$A15,BOM!$E$2:$E$400,G$5) -> 0 | H15: =SUMIFS(BOM!$G$2:$G$400,BOM!$B$2:$B$400,$A15,BOM!$E$2:$E$400,H$5) -> 0.38 | I15: =SUMIFS(BOM!$G$2:$G$400,BOM!$B$2:$B$400,$A15,BOM!$E$2:$E$400,I$5) -> 0 | J15: =SUMIFS(BOM!$G$2:$G$400,BOM!$B$2:$B$400,$A15,BOM!$E$2:$E$400,J$5) -> 0 | ... L15: =SUMIFS(BOM!$G$2:$G$400,BOM!$B$2:$B$400,$A15,BOM!$E$2:$E$400,L$5) -> 0.45 | M15: =SUM(C15:L15) -> 1.95 | N15: =COUNTIF(C15:L15,">0") -> 6
A16: P11 | B16: =INDEX(Products!$B$2:$B$16,MATCH($A16,Products!$A$2:$A$16,0)) -> Sandwich Maker 750 W | C16: =SUMIFS(BOM!$G$2:$G$400,BOM!$B$2:$B$400,$A16,BOM!$E$2:$E$400,C$5) -> 0 | D16: =SUMIFS(BOM!$G$2:$G$400,BOM!$B$2:$B$400,$A16,BOM!$E$2:$E$400,D$5) -> 0.35 | E16: =SUMIFS(BOM!$G$2:$G$400,BOM!$B$2:$B$400,$A16,BOM!$E$2:$E$400,E$5) -> 0.55 | F16: =SUMIFS(BOM!$G$2:$G$400,BOM!$B$2:$B$400,$A16,BOM!$E$2:$E$400,F$5) -> 0 | G16: =SUMIFS(BOM!$G$2:$G$400,BOM!$B$2:$B$400,$A16,BOM!$E$2:$E$400,G$5) -> 0 | H16: =SUMIFS(BOM!$G$2:$G$400,BOM!$B$2:$B$400,$A16,BOM!$E$2:$E$400,H$5) -> 0.28 | I16: =SUMIFS(BOM!$G$2:$G$400,BOM!$B$2:$B$400,$A16,BOM!$E$2:$E$400,I$5) -> 0 | J16: =SUMIFS(BOM!$G$2:$G$400,BOM!$B$2:$B$400,$A16,BOM!$E$2:$E$400,J$5) -> 0.026 | ... L16: =SUMIFS(BOM!$G$2:$G$400,BOM!$B$2:$B$400,$A16,BOM!$E$2:$E$400,L$5) -> 0.33 | M16: =SUM(C16:L16) -> 1.536 | N16: =COUNTIF(C16:L16,">0") -> 5
A17: P12 | B17: =INDEX(Products!$B$2:$B$16,MATCH($A17,Products!$A$2:$A$16,0)) -> Fan Room Heater 2000 W | C17: =SUMIFS(BOM!$G$2:$G$400,BOM!$B$2:$B$400,$A17,BOM!$E$2:$E$400,C$5) -> 0.09 | D17: =SUMIFS(BOM!$G$2:$G$400,BOM!$B$2:$B$400,$A17,BOM!$E$2:$E$400,D$5) -> 1.05 | E17: =SUMIFS(BOM!$G$2:$G$400,BOM!$B$2:$B$400,$A17,BOM!$E$2:$E$400,E$5) -> 0.12 | F17: =SUMIFS(BOM!$G$2:$G$400,BOM!$B$2:$B$400,$A17,BOM!$E$2:$E$400,F$5) -> 0.05 | G17: =SUMIFS(BOM!$G$2:$G$400,BOM!$B$2:$B$400,$A17,BOM!$E$2:$E$400,G$5) -> 0.2 | H17: =SUMIFS(BOM!$G$2:$G$400,BOM!$B$2:$B$400,$A17,BOM!$E$2:$E$400,H$5) -> 0.42 | I17: =SUMIFS(BOM!$G$2:$G$400,BOM!$B$2:$B$400,$A17,BOM!$E$2:$E$400,I$5) -> 0 | J17: =SUMIFS(BOM!$G$2:$G$400,BOM!$B$2:$B$400,$A17,BOM!$E$2:$E$400,J$5) -> 0.05 | ... L17: =SUMIFS(BOM!$G$2:$G$400,BOM!$B$2:$B$400,$A17,BOM!$E$2:$E$400,L$5) -> 0.55 | M17: =SUM(C17:L17) -> 2.57 | N17: =COUNTIF(C17:L17,">0") -> 9
... A20: P15 | B20: =INDEX(Products!$B$2:$B$16,MATCH($A20,Products!$A$2:$A$16,0)) -> Water Pump 0.5 HP Monoblock | C20: =SUMIFS(BOM!$G$2:$G$400,BOM!$B$2:$B$400,$A20,BOM!$E$2:$E$400,C$5) -> 2 | D20: =SUMIFS(BOM!$G$2:$G$400,BOM!$B$2:$B$400,$A20,BOM!$E$2:$E$400,D$5) -> 0.7 | E20: =SUMIFS(BOM!$G$2:$G$400,BOM!$B$2:$B$400,$A20,BOM!$E$2:$E$400,E$5) -> 1.3 | F20: =SUMIFS(BOM!$G$2:$G$400,BOM!$B$2:$B$400,$A20,BOM!$E$2:$E$400,F$5) -> 0.8 | G20: =SUMIFS(BOM!$G$2:$G$400,BOM!$B$2:$B$400,$A20,BOM!$E$2:$E$400,G$5) -> 0.28 | H20: =SUMIFS(BOM!$G$2:$G$400,BOM!$B$2:$B$400,$A20,BOM!$E$2:$E$400,H$5) -> 0 | I20: =SUMIFS(BOM!$G$2:$G$400,BOM!$B$2:$B$400,$A20,BOM!$E$2:$E$400,I$5) -> 0.18 | J20: =SUMIFS(BOM!$G$2:$G$400,BOM!$B$2:$B$400,$A20,BOM!$E$2:$E$400,J$5) -> 0 | ... L20: =SUMIFS(BOM!$G$2:$G$400,BOM!$B$2:$B$400,$A20,BOM!$E$2:$E$400,L$5) -> 0.85 | M20: =SUM(C20:L20) -> 6.17 | N20: =COUNTIF(C20:L20,">0") -> 8
A21: Products using this material (#) | C21: =COUNTIF(C6:C20,">0") -> 10 | D21: =COUNTIF(D6:D20,">0") -> 13 | E21: =COUNTIF(E6:E20,">0") -> 13 | F21: =COUNTIF(F6:F20,">0") -> 11 | G21: =COUNTIF(G6:G20,">0") -> 11 | H21: =COUNTIF(H6:H20,">0") -> 11 | I21: =COUNTIF(I6:I20,">0") -> 5 | J21: =COUNTIF(J6:J20,">0") -> 5 | ... L21: =COUNTIF(L6:L20,">0") -> 15
A23: B. Gross material issued per unit (kg) = net / process yield - what must be bought and issued
C24: =RawMaterials!$C$2 -> CRNGO steel coil | D24: =RawMaterials!$C$3 -> CRCA steel sheet | E24: =RawMaterials!$C$4 -> Aluminium ADC12 | F24: =RawMaterials!$C$5 -> Copper winding wire | G24: =RawMaterials!$C$6 -> PP granules | H24: =RawMaterials!$C$7 -> ABS granules | I24: =RawMaterials!$C$8 -> SS304 sheet | J24: =RawMaterials!$C$9 -> Nichrome wire | K24: =RawMaterials!$C$10 -> Powder coating | L24: =RawMaterials!$C$11 -> Corrugated cartons
A25: Product ID | B25: Product | C25: RW01 | D25: RW02 | E25: RW03 | F25: RW04 | G25: RW05 | H25: RW06 | I25: RW07 | J25: RW08 | K25: RW09 | L25: RW10 | M25: Total gross (kg) | N25: Yield loss (%)
A26: P01 | B26: =INDEX(Products!$B$2:$B$16,MATCH($A26,Products!$A$2:$A$16,0)) -> Ceiling Fan 1200 mm - Induction | C26: =SUMIFS(BOM!$I$2:$I$400,BOM!$B$2:$B$400,$A26,BOM!$E$2:$E$400,C$25) -> 1.2142857 | D26: =SUMIFS(BOM!$I$2:$I$400,BOM!$B$2:$B$400,$A26,BOM!$E$2:$E$400,D$25) -> 2.4705882 | E26: =SUMIFS(BOM!$I$2:$I$400,BOM!$B$2:$B$400,$A26,BOM!$E$2:$E$400,E$25) -> 0.54347826 | F26: =SUMIFS(BOM!$I$2:$I$400,BOM!$B$2:$B$400,$A26,BOM!$E$2:$E$400,F$25) -> 0.42857143 | G26: =SUMIFS(BOM!$I$2:$I$400,BOM!$B$2:$B$400,$A26,BOM!$E$2:$E$400,G$25) -> 0 | H26: =SUMIFS(BOM!$I$2:$I$400,BOM!$B$2:$B$400,$A26,BOM!$E$2:$E$400,H$25) -> 0 | I26: =SUMIFS(BOM!$I$2:$I$400,BOM!$B$2:$B$400,$A26,BOM!$E$2:$E$400,I$25) -> 0 | J26: =SUMIFS(BOM!$I$2:$I$400,BOM!$B$2:$B$400,$A26,BOM!$E$2:$E$400,J$25) -> 0 | ... L26: =SUMIFS(BOM!$I$2:$I$400,BOM!$B$2:$B$400,$A26,BOM!$E$2:$E$400,L$25) -> 0.77319588 | M26: =SUM(C26:L26) -> 5.5301195 | N26: =IF(M26=0,0,(M26-M6)/M26) -> 0.15010878
A27: P02 | B27: =INDEX(Products!$B$2:$B$16,MATCH($A27,Products!$A$2:$A$16,0)) -> Ceiling Fan 1200 mm - BLDC | C27: =SUMIFS(BOM!$I$2:$I$400,BOM!$B$2:$B$400,$A27,BOM!$E$2:$E$400,C$25) -> 0.88571429 | D27: =SUMIFS(BOM!$I$2:$I$400,BOM!$B$2:$B$400,$A27,BOM!$E$2:$E$400,D$25) -> 2.1764706 | E27: =SUMIFS(BOM!$I$2:$I$400,BOM!$B$2:$B$400,$A27,BOM!$E$2:$E$400,E$25) -> 0.48913043 | F27: =SUMIFS(BOM!$I$2:$I$400,BOM!$B$2:$B$400,$A27,BOM!$E$2:$E$400,F$25) -> 0.33673469 | G27: =SUMIFS(BOM!$I$2:$I$400,BOM!$B$2:$B$400,$A27,BOM!$E$2:$E$400,G$25) -> 0 | H27: =SUMIFS(BOM!$I$2:$I$400,BOM!$B$2:$B$400,$A27,BOM!$E$2:$E$400,H$25) -> 0 | I27: =SUMIFS(BOM!$I$2:$I$400,BOM!$B$2:$B$400,$A27,BOM!$E$2:$E$400,I$25) -> 0 | J27: =SUMIFS(BOM!$I$2:$I$400,BOM!$B$2:$B$400,$A27,BOM!$E$2:$E$400,J$25) -> 0 | ... L27: =SUMIFS(BOM!$I$2:$I$400,BOM!$B$2:$B$400,$A27,BOM!$E$2:$E$400,L$25) -> 0.74226804 | M27: =SUM(C27:L27) -> 4.717818 | N27: =IF(M27=0,0,(M27-M7)/M27) -> 0.14367193
A28: P03 | B28: =INDEX(Products!$B$2:$B$16,MATCH($A28,Products!$A$2:$A$16,0)) -> Pedestal Fan 400 mm | C28: =SUMIFS(BOM!$I$2:$I$400,BOM!$B$2:$B$400,$A28,BOM!$E$2:$E$400,C$25) -> 0.54285714 | D28: =SUMIFS(BOM!$I$2:$I$400,BOM!$B$2:$B$400,$A28,BOM!$E$2:$E$400,D$25) -> 1.8235294 | E28: =SUMIFS(BOM!$I$2:$I$400,BOM!$B$2:$B$400,$A28,BOM!$E$2:$E$400,E$25) -> 0.34782609 | F28: =SUMIFS(BOM!$I$2:$I$400,BOM!$B$2:$B$400,$A28,BOM!$E$2:$E$400,F$25) -> 0.24489796 | G28: =SUMIFS(BOM!$I$2:$I$400,BOM!$B$2:$B$400,$A28,BOM!$E$2:$E$400,G$25) -> 0.30927835 | H28: =SUMIFS(BOM!$I$2:$I$400,BOM!$B$2:$B$400,$A28,BOM!$E$2:$E$400,H$25) -> 0.41237113 | I28: =SUMIFS(BOM!$I$2:$I$400,BOM!$B$2:$B$400,$A28,BOM!$E$2:$E$400,I$25) -> 0 | J28: =SUMIFS(BOM!$I$2:$I$400,BOM!$B$2:$B$400,$A28,BOM!$E$2:$E$400,J$25) -> 0 | ... L28: =SUMIFS(BOM!$I$2:$I$400,BOM!$B$2:$B$400,$A28,BOM!$E$2:$E$400,L$25) -> 1.2371134 | M28: =SUM(C28:L28) -> 5.0053735 | N28: =IF(M28=0,0,(M28-M8)/M28) -> 0.1089576
A29: P04 | B29: =INDEX(Products!$B$2:$B$16,MATCH($A29,Products!$A$2:$A$16,0)) -> Table Fan 400 mm | C29: =SUMIFS(BOM!$I$2:$I$400,BOM!$B$2:$B$400,$A29,BOM!$E$2:$E$400,C$25) -> 0.42857143 | D29: =SUMIFS(BOM!$I$2:$I$400,BOM!$B$2:$B$400,$A29,BOM!$E$2:$E$400,D$25) -> 0.88235294 | E29: =SUMIFS(BOM!$I$2:$I$400,BOM!$B$2:$B$400,$A29,BOM!$E$2:$E$400,E$25) -> 0.2173913 | F29: =SUMIFS(BOM!$I$2:$I$400,BOM!$B$2:$B$400,$A29,BOM!$E$2:$E$400,F$25) -> 0.19387755 | G29: =SUMIFS(BOM!$I$2:$I$400,BOM!$B$2:$B$400,$A29,BOM!$E$2:$E$400,G$25) -> 0.25773196 | H29: =SUMIFS(BOM!$I$2:$I$400,BOM!$B$2:$B$400,$A29,BOM!$E$2:$E$400,H$25) -> 0.43298969 | I29: =SUMIFS(BOM!$I$2:$I$400,BOM!$B$2:$B$400,$A29,BOM!$E$2:$E$400,I$25) -> 0 | J29: =SUMIFS(BOM!$I$2:$I$400,BOM!$B$2:$B$400,$A29,BOM!$E$2:$E$400,J$25) -> 0 | ... L29: =SUMIFS(BOM!$I$2:$I$400,BOM!$B$2:$B$400,$A29,BOM!$E$2:$E$400,L$25) -> 0.6185567 | M29: =SUM(C29:L29) -> 3.0689716 | N29: =IF(M29=0,0,(M29-M9)/M29) -> 0.10719277
A30: P05 | B30: =INDEX(Products!$B$2:$B$16,MATCH($A30,Products!$A$2:$A$16,0)) -> Exhaust Fan 230 mm | C30: =SUMIFS(BOM!$I$2:$I$400,BOM!$B$2:$B$400,$A30,BOM!$E$2:$E$400,C$25) -> 0.22857143 | D30: =SUMIFS(BOM!$I$2:$I$400,BOM!$B$2:$B$400,$A30,BOM!$E$2:$E$400,D$25) -> 0.52941176 | E30: =SUMIFS(BOM!$I$2:$I$400,BOM!$B$2:$B$400,$A30,BOM!$E$2:$E$400,E$25) -> 0.086956522 | F30: =SUMIFS(BOM!$I$2:$I$400,BOM!$B$2:$B$400,$A30,BOM!$E$2:$E$400,F$25) -> 0.091836735 | G30: =SUMIFS(BOM!$I$2:$I$400,BOM!$B$2:$B$400,$A30,BOM!$E$2:$E$400,G$25) -> 0.20618557 | H30: =SUMIFS(BOM!$I$2:$I$400,BOM!$B$2:$B$400,$A30,BOM!$E$2:$E$400,H$25) -> 0.39175258 | I30: =SUMIFS(BOM!$I$2:$I$400,BOM!$B$2:$B$400,$A30,BOM!$E$2:$E$400,I$25) -> 0 | J30: =SUMIFS(BOM!$I$2:$I$400,BOM!$B$2:$B$400,$A30,BOM!$E$2:$E$400,J$25) -> 0 | ... L30: =SUMIFS(BOM!$I$2:$I$400,BOM!$B$2:$B$400,$A30,BOM!$E$2:$E$400,L$25) -> 0.41237113 | M30: =SUM(C30:L30) -> 1.9720857 | N30: =IF(M30=0,0,(M30-M10)/M30) -> 0.097402321
A31: P06 | B31: =INDEX(Products!$B$2:$B$16,MATCH($A31,Products!$A$2:$A$16,0)) -> Personal Air Cooler 30 L | C31: =SUMIFS(BOM!$I$2:$I$400,BOM!$B$2:$B$400,$A31,BOM!$E$2:$E$400,C$25) -> 0.31428571 | D31: =SUMIFS(BOM!$I$2:$I$400,BOM!$B$2:$B$400,$A31,BOM!$E$2:$E$400,D$25) -> 0.41176471 | E31: =SUMIFS(BOM!$I$2:$I$400,BOM!$B$2:$B$400,$A31,BOM!$E$2:$E$400,E$25) -> 0.10869565 | F31: =SUMIFS(BOM!$I$2:$I$400,BOM!$B$2:$B$400,$A31,BOM!$E$2:$E$400,F$25) -> 0.12244898 | G31: =SUMIFS(BOM!$I$2:$I$400,BOM!$B$2:$B$400,$A31,BOM!$E$2:$E$400,G$25) -> 4.742268 | H31: =SUMIFS(BOM!$I$2:$I$400,BOM!$B$2:$B$400,$A31,BOM!$E$2:$E$400,H$25) -> 0.36082474 | I31: =SUMIFS(BOM!$I$2:$I$400,BOM!$B$2:$B$400,$A31,BOM!$E$2:$E$400,I$25) -> 0 | J31: =SUMIFS(BOM!$I$2:$I$400,BOM!$B$2:$B$400,$A31,BOM!$E$2:$E$400,J$25) -> 0 | ... L31: =SUMIFS(BOM!$I$2:$I$400,BOM!$B$2:$B$400,$A31,BOM!$E$2:$E$400,L$25) -> 1.6494845 | M31: =SUM(C31:L31) -> 7.7097724 | N31: =IF(M31=0,0,(M31-M11)/M31) -> 0.047961516
A32: P07 | B32: =INDEX(Products!$B$2:$B$16,MATCH($A32,Products!$A$2:$A$16,0)) -> Mixer Grinder 500 W | C32: =SUMIFS(BOM!$I$2:$I$400,BOM!$B$2:$B$400,$A32,BOM!$E$2:$E$400,C$25) -> 0.64285714 | D32: =SUMIFS(BOM!$I$2:$I$400,BOM!$B$2:$B$400,$A32,BOM!$E$2:$E$400,D$25) -> 0.14117647 | E32: =SUMIFS(BOM!$I$2:$I$400,BOM!$B$2:$B$400,$A32,BOM!$E$2:$E$400,E$25) -> 0.38043478 | F32: =SUMIFS(BOM!$I$2:$I$400,BOM!$B$2:$B$400,$A32,BOM!$E$2:$E$400,F$25) -> 0.2244898 | G32: =SUMIFS(BOM!$I$2:$I$400,BOM!$B$2:$B$400,$A32,BOM!$E$2:$E$400,G$25) -> 0.30927835 | H32: =SUMIFS(BOM!$I$2:$I$400,BOM!$B$2:$B$400,$A32,BOM!$E$2:$E$400,H$25) -> 0.56701031 | I32: =SUMIFS(BOM!$I$2:$I$400,BOM!$B$2:$B$400,$A32,BOM!$E$2:$E$400,I$25) -> 0.73170732 | J32: =SUMIFS(BOM!$I$2:$I$400,BOM!$B$2:$B$400,$A32,BOM!$E$2:$E$400,J$25) -> 0 | ... L32: =SUMIFS(BOM!$I$2:$I$400,BOM!$B$2:$B$400,$A32,BOM!$E$2:$E$400,L$25) -> 0.56701031 | M32: =SUM(C32:L32) -> 3.5639645 | N32: =IF(M32=0,0,(M32-M12)/M32) -> 0.11895867
A33: P08 | B33: =INDEX(Products!$B$2:$B$16,MATCH($A33,Products!$A$2:$A$16,0)) -> Mixer Grinder 750 W | C33: =SUMIFS(BOM!$I$2:$I$400,BOM!$B$2:$B$400,$A33,BOM!$E$2:$E$400,C$25) -> 0.88571429 | D33: =SUMIFS(BOM!$I$2:$I$400,BOM!$B$2:$B$400,$A33,BOM!$E$2:$E$400,D$25) -> 0.17647059 | E33: =SUMIFS(BOM!$I$2:$I$400,BOM!$B$2:$B$400,$A33,BOM!$E$2:$E$400,E$25) -> 0.52173913 | F33: =SUMIFS(BOM!$I$2:$I$400,BOM!$B$2:$B$400,$A33,BOM!$E$2:$E$400,F$25) -> 0.30612245 | G33: =SUMIFS(BOM!$I$2:$I$400,BOM!$B$2:$B$400,$A33,BOM!$E$2:$E$400,G$25) -> 0.35051546 | H33: =SUMIFS(BOM!$I$2:$I$400,BOM!$B$2:$B$400,$A33,BOM!$E$2:$E$400,H$25) -> 0.63917526 | I33: =SUMIFS(BOM!$I$2:$I$400,BOM!$B$2:$B$400,$A33,BOM!$E$2:$E$400,I$25) -> 0.95121951 | J33: =SUMIFS(BOM!$I$2:$I$400,BOM!$B$2:$B$400,$A33,BOM!$E$2:$E$400,J$25) -> 0 | ... L33: =SUMIFS(BOM!$I$2:$I$400,BOM!$B$2:$B$400,$A33,BOM!$E$2:$E$400,L$25) -> 0.63917526 | M33: =SUM(C33:L33) -> 4.4701319 | N33: =IF(M33=0,0,(M33-M13)/M33) -> 0.12530546
A34: P09 | B34: =INDEX(Products!$B$2:$B$16,MATCH($A34,Products!$A$2:$A$16,0)) -> Electric Kettle 1.5 L | C34: =SUMIFS(BOM!$I$2:$I$400,BOM!$B$2:$B$400,$A34,BOM!$E$2:$E$400,C$25) -> 0 | D34: =SUMIFS(BOM!$I$2:$I$400,BOM!$B$2:$B$400,$A34,BOM!$E$2:$E$400,D$25) -> 0 | E34: =SUMIFS(BOM!$I$2:$I$400,BOM!$B$2:$B$400,$A34,BOM!$E$2:$E$400,E$25) -> 0 | F34: =SUMIFS(BOM!$I$2:$I$400,BOM!$B$2:$B$400,$A34,BOM!$E$2:$E$400,F$25) -> 0 | G34: =SUMIFS(BOM!$I$2:$I$400,BOM!$B$2:$B$400,$A34,BOM!$E$2:$E$400,G$25) -> 0.1443299 | H34: =SUMIFS(BOM!$I$2:$I$400,BOM!$B$2:$B$400,$A34,BOM!$E$2:$E$400,H$25) -> 0.20618557 | I34: =SUMIFS(BOM!$I$2:$I$400,BOM!$B$2:$B$400,$A34,BOM!$E$2:$E$400,I$25) -> 0.51219512 | J34: =SUMIFS(BOM!$I$2:$I$400,BOM!$B$2:$B$400,$A34,BOM!$E$2:$E$400,J$25) -> 0.0125 | ... L34: =SUMIFS(BOM!$I$2:$I$400,BOM!$B$2:$B$400,$A34,BOM!$E$2:$E$400,L$25) -> 0.34020619 | M34: =SUM(C34:L34) -> 1.2154168 | N34: =IF(M34=0,0,(M34-M14)/M34) -> 0.093315128
A35: P10 | B35: =INDEX(Products!$B$2:$B$16,MATCH($A35,Products!$A$2:$A$16,0)) -> Induction Cooktop 2000 W | C35: =SUMIFS(BOM!$I$2:$I$400,BOM!$B$2:$B$400,$A35,BOM!$E$2:$E$400,C$25) -> 0 | D35: =SUMIFS(BOM!$I$2:$I$400,BOM!$B$2:$B$400,$A35,BOM!$E$2:$E$400,D$25) -> 0.94117647 | E35: =SUMIFS(BOM!$I$2:$I$400,BOM!$B$2:$B$400,$A35,BOM!$E$2:$E$400,E$25) -> 0.19565217 | F35: =SUMIFS(BOM!$I$2:$I$400,BOM!$B$2:$B$400,$A35,BOM!$E$2:$E$400,F$25) -> 0.12244898 | G35: =SUMIFS(BOM!$I$2:$I$400,BOM!$B$2:$B$400,$A35,BOM!$E$2:$E$400,G$25) -> 0 | H35: =SUMIFS(BOM!$I$2:$I$400,BOM!$B$2:$B$400,$A35,BOM!$E$2:$E$400,H$25) -> 0.39175258 | I35: =SUMIFS(BOM!$I$2:$I$400,BOM!$B$2:$B$400,$A35,BOM!$E$2:$E$400,I$25) -> 0 | J35: =SUMIFS(BOM!$I$2:$I$400,BOM!$B$2:$B$400,$A35,BOM!$E$2:$E$400,J$25) -> 0 | ... L35: =SUMIFS(BOM!$I$2:$I$400,BOM!$B$2:$B$400,$A35,BOM!$E$2:$E$400,L$25) -> 0.46391753 | M35: =SUM(C35:L35) -> 2.1399477 | N35: =IF(M35=0,0,(M35-M15)/M35) -> 0.088762788
A36: P11 | B36: =INDEX(Products!$B$2:$B$16,MATCH($A36,Products!$A$2:$A$16,0)) -> Sandwich Maker 750 W | C36: =SUMIFS(BOM!$I$2:$I$400,BOM!$B$2:$B$400,$A36,BOM!$E$2:$E$400,C$25) -> 0 | D36: =SUMIFS(BOM!$I$2:$I$400,BOM!$B$2:$B$400,$A36,BOM!$E$2:$E$400,D$25) -> 0.41176471 | E36: =SUMIFS(BOM!$I$2:$I$400,BOM!$B$2:$B$400,$A36,BOM!$E$2:$E$400,E$25) -> 0.59782609 | F36: =SUMIFS(BOM!$I$2:$I$400,BOM!$B$2:$B$400,$A36,BOM!$E$2:$E$400,F$25) -> 0 | G36: =SUMIFS(BOM!$I$2:$I$400,BOM!$B$2:$B$400,$A36,BOM!$E$2:$E$400,G$25) -> 0 | H36: =SUMIFS(BOM!$I$2:$I$400,BOM!$B$2:$B$400,$A36,BOM!$E$2:$E$400,H$25) -> 0.28865979 | I36: =SUMIFS(BOM!$I$2:$I$400,BOM!$B$2:$B$400,$A36,BOM!$E$2:$E$400,I$25) -> 0 | J36: =SUMIFS(BOM!$I$2:$I$400,BOM!$B$2:$B$400,$A36,BOM!$E$2:$E$400,J$25) -> 0.027083333 | ... L36: =SUMIFS(BOM!$I$2:$I$400,BOM!$B$2:$B$400,$A36,BOM!$E$2:$E$400,L$25) -> 0.34020619 | M36: =SUM(C36:L36) -> 1.6655401 | N36: =IF(M36=0,0,(M36-M16)/M36) -> 0.077776635
A37: P12 | B37: =INDEX(Products!$B$2:$B$16,MATCH($A37,Products!$A$2:$A$16,0)) -> Fan Room Heater 2000 W | C37: =SUMIFS(BOM!$I$2:$I$400,BOM!$B$2:$B$400,$A37,BOM!$E$2:$E$400,C$25) -> 0.12857143 | D37: =SUMIFS(BOM!$I$2:$I$400,BOM!$B$2:$B$400,$A37,BOM!$E$2:$E$400,D$25) -> 1.2352941 | E37: =SUMIFS(BOM!$I$2:$I$400,BOM!$B$2:$B$400,$A37,BOM!$E$2:$E$400,E$25) -> 0.13043478 | F37: =SUMIFS(BOM!$I$2:$I$400,BOM!$B$2:$B$400,$A37,BOM!$E$2:$E$400,F$25) -> 0.051020408 | G37: =SUMIFS(BOM!$I$2:$I$400,BOM!$B$2:$B$400,$A37,BOM!$E$2:$E$400,G$25) -> 0.20618557 | H37: =SUMIFS(BOM!$I$2:$I$400,BOM!$B$2:$B$400,$A37,BOM!$E$2:$E$400,H$25) -> 0.43298969 | I37: =SUMIFS(BOM!$I$2:$I$400,BOM!$B$2:$B$400,$A37,BOM!$E$2:$E$400,I$25) -> 0 | J37: =SUMIFS(BOM!$I$2:$I$400,BOM!$B$2:$B$400,$A37,BOM!$E$2:$E$400,J$25) -> 0.052083333 | ... L37: =SUMIFS(BOM!$I$2:$I$400,BOM!$B$2:$B$400,$A37,BOM!$E$2:$E$400,L$25) -> 0.56701031 | M37: =SUM(C37:L37) -> 2.8535896 | N37: =IF(M37=0,0,(M37-M17)/M37) -> 0.099379965
... A40: P15 | B40: =INDEX(Products!$B$2:$B$16,MATCH($A40,Products!$A$2:$A$16,0)) -> Water Pump 0.5 HP Monoblock | C40: =SUMIFS(BOM!$I$2:$I$400,BOM!$B$2:$B$400,$A40,BOM!$E$2:$E$400,C$25) -> 2.8571429 | D40: =SUMIFS(BOM!$I$2:$I$400,BOM!$B$2:$B$400,$A40,BOM!$E$2:$E$400,D$25) -> 0.82352941 | E40: =SUMIFS(BOM!$I$2:$I$400,BOM!$B$2:$B$400,$A40,BOM!$E$2:$E$400,E$25) -> 1.4130435 | F40: =SUMIFS(BOM!$I$2:$I$400,BOM!$B$2:$B$400,$A40,BOM!$E$2:$E$400,F$25) -> 0.81632653 | G40: =SUMIFS(BOM!$I$2:$I$400,BOM!$B$2:$B$400,$A40,BOM!$E$2:$E$400,G$25) -> 0.28865979 | H40: =SUMIFS(BOM!$I$2:$I$400,BOM!$B$2:$B$400,$A40,BOM!$E$2:$E$400,H$25) -> 0 | I40: =SUMIFS(BOM!$I$2:$I$400,BOM!$B$2:$B$400,$A40,BOM!$E$2:$E$400,I$25) -> 0.2195122 | J40: =SUMIFS(BOM!$I$2:$I$400,BOM!$B$2:$B$400,$A40,BOM!$E$2:$E$400,J$25) -> 0 | ... L40: =SUMIFS(BOM!$I$2:$I$400,BOM!$B$2:$B$400,$A40,BOM!$E$2:$E$400,L$25) -> 0.87628866 | M40: =SUM(C40:L40) -> 7.3695029 | N40: =IF(M40=0,0,(M40-M20)/M40) -> 0.16276578
A42: C. Raw-material cost per unit (₹) = gross kg x standard price
C43: =RawMaterials!$C$2 -> CRNGO steel coil | D43: =RawMaterials!$C$3 -> CRCA steel sheet | E43: =RawMaterials!$C$4 -> Aluminium ADC12 | F43: =RawMaterials!$C$5 -> Copper winding wire | G43: =RawMaterials!$C$6 -> PP granules | H43: =RawMaterials!$C$7 -> ABS granules | I43: =RawMaterials!$C$8 -> SS304 sheet | J43: =RawMaterials!$C$9 -> Nichrome wire | K43: =RawMaterials!$C$10 -> Powder coating | L43: =RawMaterials!$C$11 -> Corrugated cartons
A44: Product ID | B44: Product | C44: RW01 | D44: RW02 | E44: RW03 | F44: RW04 | G44: RW05 | H44: RW06 | I44: RW07 | J44: RW08 | K44: RW09 | L44: RW10 | M44: Total RM cost (₹ / unit) | N44: Largest cost driver
A45: P01 | B45: =INDEX(Products!$B$2:$B$16,MATCH($A45,Products!$A$2:$A$16,0)) -> Ceiling Fan 1200 mm - Induction | C45: =SUMIFS(BOM!$K$2:$K$400,BOM!$B$2:$B$400,$A45,BOM!$E$2:$E$400,C$44) -> 113.41429 | D45: =SUMIFS(BOM!$K$2:$K$400,BOM!$B$2:$B$400,$A45,BOM!$E$2:$E$400,D$44) -> 164.66471 | E45: =SUMIFS(BOM!$K$2:$K$400,BOM!$B$2:$B$400,$A45,BOM!$E$2:$E$400,E$44) -> 142.11957 | F45: =SUMIFS(BOM!$K$2:$K$400,BOM!$B$2:$B$400,$A45,BOM!$E$2:$E$400,F$44) -> 572.67857 | G45: =SUMIFS(BOM!$K$2:$K$400,BOM!$B$2:$B$400,$A45,BOM!$E$2:$E$400,G$44) -> 0 | H45: =SUMIFS(BOM!$K$2:$K$400,BOM!$B$2:$B$400,$A45,BOM!$E$2:$E$400,H$44) -> 0 | I45: =SUMIFS(BOM!$K$2:$K$400,BOM!$B$2:$B$400,$A45,BOM!$E$2:$E$400,I$44) -> 0 | J45: =SUMIFS(BOM!$K$2:$K$400,BOM!$B$2:$B$400,$A45,BOM!$E$2:$E$400,J$44) -> 0 | ... L45: =SUMIFS(BOM!$K$2:$K$400,BOM!$B$2:$B$400,$A45,BOM!$E$2:$E$400,L$44) -> 40.206186 | M45: =SUM(C45:L45) -> 1067.5833 | N45: =INDEX($C$43:$L$43,MATCH(MAX(C45:L45),C45:L45,0)) -> Copper winding wire
A46: P02 | B46: =INDEX(Products!$B$2:$B$16,MATCH($A46,Products!$A$2:$A$16,0)) -> Ceiling Fan 1200 mm - BLDC | C46: =SUMIFS(BOM!$K$2:$K$400,BOM!$B$2:$B$400,$A46,BOM!$E$2:$E$400,C$44) -> 82.725714 | D46: =SUMIFS(BOM!$K$2:$K$400,BOM!$B$2:$B$400,$A46,BOM!$E$2:$E$400,D$44) -> 145.06176 | E46: =SUMIFS(BOM!$K$2:$K$400,BOM!$B$2:$B$400,$A46,BOM!$E$2:$E$400,E$44) -> 127.90761 | F46: =SUMIFS(BOM!$K$2:$K$400,BOM!$B$2:$B$400,$A46,BOM!$E$2:$E$400,F$44) -> 449.96173 | G46: =SUMIFS(BOM!$K$2:$K$400,BOM!$B$2:$B$400,$A46,BOM!$E$2:$E$400,G$44) -> 0 | H46: =SUMIFS(BOM!$K$2:$K$400,BOM!$B$2:$B$400,$A46,BOM!$E$2:$E$400,H$44) -> 0 | I46: =SUMIFS(BOM!$K$2:$K$400,BOM!$B$2:$B$400,$A46,BOM!$E$2:$E$400,I$44) -> 0 | J46: =SUMIFS(BOM!$K$2:$K$400,BOM!$B$2:$B$400,$A46,BOM!$E$2:$E$400,J$44) -> 0 | ... L46: =SUMIFS(BOM!$K$2:$K$400,BOM!$B$2:$B$400,$A46,BOM!$E$2:$E$400,L$44) -> 38.597938 | M46: =SUM(C46:L46) -> 874.44226 | N46: =INDEX($C$43:$L$43,MATCH(MAX(C46:L46),C46:L46,0)) -> Copper winding wire
A47: P03 | B47: =INDEX(Products!$B$2:$B$16,MATCH($A47,Products!$A$2:$A$16,0)) -> Pedestal Fan 400 mm | C47: =SUMIFS(BOM!$K$2:$K$400,BOM!$B$2:$B$400,$A47,BOM!$E$2:$E$400,C$44) -> 50.702857 | D47: =SUMIFS(BOM!$K$2:$K$400,BOM!$B$2:$B$400,$A47,BOM!$E$2:$E$400,D$44) -> 121.53824 | E47: =SUMIFS(BOM!$K$2:$K$400,BOM!$B$2:$B$400,$A47,BOM!$E$2:$E$400,E$44) -> 90.956522 | F47: =SUMIFS(BOM!$K$2:$K$400,BOM!$B$2:$B$400,$A47,BOM!$E$2:$E$400,F$44) -> 327.2449 | G47: =SUMIFS(BOM!$K$2:$K$400,BOM!$B$2:$B$400,$A47,BOM!$E$2:$E$400,G$44) -> 33.092784 | H47: =SUMIFS(BOM!$K$2:$K$400,BOM!$B$2:$B$400,$A47,BOM!$E$2:$E$400,H$44) -> 64.329897 | I47: =SUMIFS(BOM!$K$2:$K$400,BOM!$B$2:$B$400,$A47,BOM!$E$2:$E$400,I$44) -> 0 | J47: =SUMIFS(BOM!$K$2:$K$400,BOM!$B$2:$B$400,$A47,BOM!$E$2:$E$400,J$44) -> 0 | ... L47: =SUMIFS(BOM!$K$2:$K$400,BOM!$B$2:$B$400,$A47,BOM!$E$2:$E$400,L$44) -> 64.329897 | M47: =SUM(C47:L47) -> 782.38259 | N47: =INDEX($C$43:$L$43,MATCH(MAX(C47:L47),C47:L47,0)) -> Copper winding wire
A48: P04 | B48: =INDEX(Products!$B$2:$B$16,MATCH($A48,Products!$A$2:$A$16,0)) -> Table Fan 400 mm | C48: =SUMIFS(BOM!$K$2:$K$400,BOM!$B$2:$B$400,$A48,BOM!$E$2:$E$400,C$44) -> 40.028571 | D48: =SUMIFS(BOM!$K$2:$K$400,BOM!$B$2:$B$400,$A48,BOM!$E$2:$E$400,D$44) -> 58.808824 | E48: =SUMIFS(BOM!$K$2:$K$400,BOM!$B$2:$B$400,$A48,BOM!$E$2:$E$400,E$44) -> 56.847826 | F48: =SUMIFS(BOM!$K$2:$K$400,BOM!$B$2:$B$400,$A48,BOM!$E$2:$E$400,F$44) -> 259.06888 | G48: =SUMIFS(BOM!$K$2:$K$400,BOM!$B$2:$B$400,$A48,BOM!$E$2:$E$400,G$44) -> 27.57732 | H48: =SUMIFS(BOM!$K$2:$K$400,BOM!$B$2:$B$400,$A48,BOM!$E$2:$E$400,H$44) -> 67.546392 | I48: =SUMIFS(BOM!$K$2:$K$400,BOM!$B$2:$B$400,$A48,BOM!$E$2:$E$400,I$44) -> 0 | J48: =SUMIFS(BOM!$K$2:$K$400,BOM!$B$2:$B$400,$A48,BOM!$E$2:$E$400,J$44) -> 0 | ... L48: =SUMIFS(BOM!$K$2:$K$400,BOM!$B$2:$B$400,$A48,BOM!$E$2:$E$400,L$44) -> 32.164948 | M48: =SUM(C48:L48) -> 554.98026 | N48: =INDEX($C$43:$L$43,MATCH(MAX(C48:L48),C48:L48,0)) -> Copper winding wire
A49: P05 | B49: =INDEX(Products!$B$2:$B$16,MATCH($A49,Products!$A$2:$A$16,0)) -> Exhaust Fan 230 mm | C49: =SUMIFS(BOM!$K$2:$K$400,BOM!$B$2:$B$400,$A49,BOM!$E$2:$E$400,C$44) -> 21.348571 | D49: =SUMIFS(BOM!$K$2:$K$400,BOM!$B$2:$B$400,$A49,BOM!$E$2:$E$400,D$44) -> 35.285294 | E49: =SUMIFS(BOM!$K$2:$K$400,BOM!$B$2:$B$400,$A49,BOM!$E$2:$E$400,E$44) -> 22.73913 | F49: =SUMIFS(BOM!$K$2:$K$400,BOM!$B$2:$B$400,$A49,BOM!$E$2:$E$400,F$44) -> 122.71684 | G49: =SUMIFS(BOM!$K$2:$K$400,BOM!$B$2:$B$400,$A49,BOM!$E$2:$E$400,G$44) -> 22.061856 | H49: =SUMIFS(BOM!$K$2:$K$400,BOM!$B$2:$B$400,$A49,BOM!$E$2:$E$400,H$44) -> 61.113402 | I49: =SUMIFS(BOM!$K$2:$K$400,BOM!$B$2:$B$400,$A49,BOM!$E$2:$E$400,I$44) -> 0 | J49: =SUMIFS(BOM!$K$2:$K$400,BOM!$B$2:$B$400,$A49,BOM!$E$2:$E$400,J$44) -> 0 | ... L49: =SUMIFS(BOM!$K$2:$K$400,BOM!$B$2:$B$400,$A49,BOM!$E$2:$E$400,L$44) -> 21.443299 | M49: =SUM(C49:L49) -> 315.33339 | N49: =INDEX($C$43:$L$43,MATCH(MAX(C49:L49),C49:L49,0)) -> Copper winding wire
A50: P06 | B50: =INDEX(Products!$B$2:$B$16,MATCH($A50,Products!$A$2:$A$16,0)) -> Personal Air Cooler 30 L | C50: =SUMIFS(BOM!$K$2:$K$400,BOM!$B$2:$B$400,$A50,BOM!$E$2:$E$400,C$44) -> 29.354286 | D50: =SUMIFS(BOM!$K$2:$K$400,BOM!$B$2:$B$400,$A50,BOM!$E$2:$E$400,D$44) -> 27.444118 | E50: =SUMIFS(BOM!$K$2:$K$400,BOM!$B$2:$B$400,$A50,BOM!$E$2:$E$400,E$44) -> 28.423913 | F50: =SUMIFS(BOM!$K$2:$K$400,BOM!$B$2:$B$400,$A50,BOM!$E$2:$E$400,F$44) -> 163.62245 | G50: =SUMIFS(BOM!$K$2:$K$400,BOM!$B$2:$B$400,$A50,BOM!$E$2:$E$400,G$44) -> 507.42268 | H50: =SUMIFS(BOM!$K$2:$K$400,BOM!$B$2:$B$400,$A50,BOM!$E$2:$E$400,H$44) -> 56.28866 | I50: =SUMIFS(BOM!$K$2:$K$400,BOM!$B$2:$B$400,$A50,BOM!$E$2:$E$400,I$44) -> 0 | J50: =SUMIFS(BOM!$K$2:$K$400,BOM!$B$2:$B$400,$A50,BOM!$E$2:$E$400,J$44) -> 0 | ... L50: =SUMIFS(BOM!$K$2:$K$400,BOM!$B$2:$B$400,$A50,BOM!$E$2:$E$400,L$44) -> 85.773196 | M50: =SUM(C50:L50) -> 898.3293 | N50: =INDEX($C$43:$L$43,MATCH(MAX(C50:L50),C50:L50,0)) -> PP granules
A51: P07 | B51: =INDEX(Products!$B$2:$B$16,MATCH($A51,Products!$A$2:$A$16,0)) -> Mixer Grinder 500 W | C51: =SUMIFS(BOM!$K$2:$K$400,BOM!$B$2:$B$400,$A51,BOM!$E$2:$E$400,C$44) -> 60.042857 | D51: =SUMIFS(BOM!$K$2:$K$400,BOM!$B$2:$B$400,$A51,BOM!$E$2:$E$400,D$44) -> 9.4094118 | E51: =SUMIFS(BOM!$K$2:$K$400,BOM!$B$2:$B$400,$A51,BOM!$E$2:$E$400,E$44) -> 99.483696 | F51: =SUMIFS(BOM!$K$2:$K$400,BOM!$B$2:$B$400,$A51,BOM!$E$2:$E$400,F$44) -> 299.97449 | G51: =SUMIFS(BOM!$K$2:$K$400,BOM!$B$2:$B$400,$A51,BOM!$E$2:$E$400,G$44) -> 33.092784 | H51: =SUMIFS(BOM!$K$2:$K$400,BOM!$B$2:$B$400,$A51,BOM!$E$2:$E$400,H$44) -> 88.453608 | I51: =SUMIFS(BOM!$K$2:$K$400,BOM!$B$2:$B$400,$A51,BOM!$E$2:$E$400,I$44) -> 151.09756 | J51: =SUMIFS(BOM!$K$2:$K$400,BOM!$B$2:$B$400,$A51,BOM!$E$2:$E$400,J$44) -> 0 | ... L51: =SUMIFS(BOM!$K$2:$K$400,BOM!$B$2:$B$400,$A51,BOM!$E$2:$E$400,L$44) -> 29.484536 | M51: =SUM(C51:L51) -> 771.03894 | N51: =INDEX($C$43:$L$43,MATCH(MAX(C51:L51),C51:L51,0)) -> Copper winding wire
A52: P08 | B52: =INDEX(Products!$B$2:$B$16,MATCH($A52,Products!$A$2:$A$16,0)) -> Mixer Grinder 750 W | C52: =SUMIFS(BOM!$K$2:$K$400,BOM!$B$2:$B$400,$A52,BOM!$E$2:$E$400,C$44) -> 82.725714 | D52: =SUMIFS(BOM!$K$2:$K$400,BOM!$B$2:$B$400,$A52,BOM!$E$2:$E$400,D$44) -> 11.761765 | E52: =SUMIFS(BOM!$K$2:$K$400,BOM!$B$2:$B$400,$A52,BOM!$E$2:$E$400,E$44) -> 136.43478 | F52: =SUMIFS(BOM!$K$2:$K$400,BOM!$B$2:$B$400,$A52,BOM!$E$2:$E$400,F$44) -> 409.05612 | G52: =SUMIFS(BOM!$K$2:$K$400,BOM!$B$2:$B$400,$A52,BOM!$E$2:$E$400,G$44) -> 37.505155 | H52: =SUMIFS(BOM!$K$2:$K$400,BOM!$B$2:$B$400,$A52,BOM!$E$2:$E$400,H$44) -> 99.71134 | I52: =SUMIFS(BOM!$K$2:$K$400,BOM!$B$2:$B$400,$A52,BOM!$E$2:$E$400,I$44) -> 196.42683 | J52: =SUMIFS(BOM!$K$2:$K$400,BOM!$B$2:$B$400,$A52,BOM!$E$2:$E$400,J$44) -> 0 | ... L52: =SUMIFS(BOM!$K$2:$K$400,BOM!$B$2:$B$400,$A52,BOM!$E$2:$E$400,L$44) -> 33.237113 | M52: =SUM(C52:L52) -> 1006.8588 | N52: =INDEX($C$43:$L$43,MATCH(MAX(C52:L52),C52:L52,0)) -> Copper winding wire
A53: P09 | B53: =INDEX(Products!$B$2:$B$16,MATCH($A53,Products!$A$2:$A$16,0)) -> Electric Kettle 1.5 L | C53: =SUMIFS(BOM!$K$2:$K$400,BOM!$B$2:$B$400,$A53,BOM!$E$2:$E$400,C$44) -> 0 | D53: =SUMIFS(BOM!$K$2:$K$400,BOM!$B$2:$B$400,$A53,BOM!$E$2:$E$400,D$44) -> 0 | E53: =SUMIFS(BOM!$K$2:$K$400,BOM!$B$2:$B$400,$A53,BOM!$E$2:$E$400,E$44) -> 0 | F53: =SUMIFS(BOM!$K$2:$K$400,BOM!$B$2:$B$400,$A53,BOM!$E$2:$E$400,F$44) -> 0 | G53: =SUMIFS(BOM!$K$2:$K$400,BOM!$B$2:$B$400,$A53,BOM!$E$2:$E$400,G$44) -> 15.443299 | H53: =SUMIFS(BOM!$K$2:$K$400,BOM!$B$2:$B$400,$A53,BOM!$E$2:$E$400,H$44) -> 32.164948 | I53: =SUMIFS(BOM!$K$2:$K$400,BOM!$B$2:$B$400,$A53,BOM!$E$2:$E$400,I$44) -> 105.76829 | J53: =SUMIFS(BOM!$K$2:$K$400,BOM!$B$2:$B$400,$A53,BOM!$E$2:$E$400,J$44) -> 26 | ... L53: =SUMIFS(BOM!$K$2:$K$400,BOM!$B$2:$B$400,$A53,BOM!$E$2:$E$400,L$44) -> 17.690722 | M53: =SUM(C53:L53) -> 197.06726 | N53: =INDEX($C$43:$L$43,MATCH(MAX(C53:L53),C53:L53,0)) -> SS304 sheet
A54: P10 | B54: =INDEX(Products!$B$2:$B$16,MATCH($A54,Products!$A$2:$A$16,0)) -> Induction Cooktop 2000 W | C54: =SUMIFS(BOM!$K$2:$K$400,BOM!$B$2:$B$400,$A54,BOM!$E$2:$E$400,C$44) -> 0 | D54: =SUMIFS(BOM!$K$2:$K$400,BOM!$B$2:$B$400,$A54,BOM!$E$2:$E$400,D$44) -> 62.729412 | E54: =SUMIFS(BOM!$K$2:$K$400,BOM!$B$2:$B$400,$A54,BOM!$E$2:$E$400,E$44) -> 51.163043 | F54: =SUMIFS(BOM!$K$2:$K$400,BOM!$B$2:$B$400,$A54,BOM!$E$2:$E$400,F$44) -> 163.62245 | G54: =SUMIFS(BOM!$K$2:$K$400,BOM!$B$2:$B$400,$A54,BOM!$E$2:$E$400,G$44) -> 0 | H54: =SUMIFS(BOM!$K$2:$K$400,BOM!$B$2:$B$400,$A54,BOM!$E$2:$E$400,H$44) -> 61.113402 | I54: =SUMIFS(BOM!$K$2:$K$400,BOM!$B$2:$B$400,$A54,BOM!$E$2:$E$400,I$44) -> 0 | J54: =SUMIFS(BOM!$K$2:$K$400,BOM!$B$2:$B$400,$A54,BOM!$E$2:$E$400,J$44) -> 0 | ... L54: =SUMIFS(BOM!$K$2:$K$400,BOM!$B$2:$B$400,$A54,BOM!$E$2:$E$400,L$44) -> 24.123711 | M54: =SUM(C54:L54) -> 371.37702 | N54: =INDEX($C$43:$L$43,MATCH(MAX(C54:L54),C54:L54,0)) -> Copper winding wire
A55: P11 | B55: =INDEX(Products!$B$2:$B$16,MATCH($A55,Products!$A$2:$A$16,0)) -> Sandwich Maker 750 W | C55: =SUMIFS(BOM!$K$2:$K$400,BOM!$B$2:$B$400,$A55,BOM!$E$2:$E$400,C$44) -> 0 | D55: =SUMIFS(BOM!$K$2:$K$400,BOM!$B$2:$B$400,$A55,BOM!$E$2:$E$400,D$44) -> 27.444118 | E55: =SUMIFS(BOM!$K$2:$K$400,BOM!$B$2:$B$400,$A55,BOM!$E$2:$E$400,E$44) -> 156.33152 | F55: =SUMIFS(BOM!$K$2:$K$400,BOM!$B$2:$B$400,$A55,BOM!$E$2:$E$400,F$44) -> 0 | G55: =SUMIFS(BOM!$K$2:$K$400,BOM!$B$2:$B$400,$A55,BOM!$E$2:$E$400,G$44) -> 0 | H55: =SUMIFS(BOM!$K$2:$K$400,BOM!$B$2:$B$400,$A55,BOM!$E$2:$E$400,H$44) -> 45.030928 | I55: =SUMIFS(BOM!$K$2:$K$400,BOM!$B$2:$B$400,$A55,BOM!$E$2:$E$400,I$44) -> 0 | J55: =SUMIFS(BOM!$K$2:$K$400,BOM!$B$2:$B$400,$A55,BOM!$E$2:$E$400,J$44) -> 56.333333 | ... L55: =SUMIFS(BOM!$K$2:$K$400,BOM!$B$2:$B$400,$A55,BOM!$E$2:$E$400,L$44) -> 17.690722 | M55: =SUM(C55:L55) -> 302.83062 | N55: =INDEX($C$43:$L$43,MATCH(MAX(C55:L55),C55:L55,0)) -> Aluminium ADC12
A56: P12 | B56: =INDEX(Products!$B$2:$B$16,MATCH($A56,Products!$A$2:$A$16,0)) -> Fan Room Heater 2000 W | C56: =SUMIFS(BOM!$K$2:$K$400,BOM!$B$2:$B$400,$A56,BOM!$E$2:$E$400,C$44) -> 12.008571 | D56: =SUMIFS(BOM!$K$2:$K$400,BOM!$B$2:$B$400,$A56,BOM!$E$2:$E$400,D$44) -> 82.332353 | E56: =SUMIFS(BOM!$K$2:$K$400,BOM!$B$2:$B$400,$A56,BOM!$E$2:$E$400,E$44) -> 34.108696 | F56: =SUMIFS(BOM!$K$2:$K$400,BOM!$B$2:$B$400,$A56,BOM!$E$2:$E$400,F$44) -> 68.17602 | G56: =SUMIFS(BOM!$K$2:$K$400,BOM!$B$2:$B$400,$A56,BOM!$E$2:$E$400,G$44) -> 22.061856 | H56: =SUMIFS(BOM!$K$2:$K$400,BOM!$B$2:$B$400,$A56,BOM!$E$2:$E$400,H$44) -> 67.546392 | I56: =SUMIFS(BOM!$K$2:$K$400,BOM!$B$2:$B$400,$A56,BOM!$E$2:$E$400,I$44) -> 0 | J56: =SUMIFS(BOM!$K$2:$K$400,BOM!$B$2:$B$400,$A56,BOM!$E$2:$E$400,J$44) -> 108.33333 | ... L56: =SUMIFS(BOM!$K$2:$K$400,BOM!$B$2:$B$400,$A56,BOM!$E$2:$E$400,L$44) -> 29.484536 | M56: =SUM(C56:L56) -> 441.30176 | N56: =INDEX($C$43:$L$43,MATCH(MAX(C56:L56),C56:L56,0)) -> Nichrome wire
... A59: P15 | B59: =INDEX(Products!$B$2:$B$16,MATCH($A59,Products!$A$2:$A$16,0)) -> Water Pump 0.5 HP Monoblock | C59: =SUMIFS(BOM!$K$2:$K$400,BOM!$B$2:$B$400,$A59,BOM!$E$2:$E$400,C$44) -> 266.85714 | D59: =SUMIFS(BOM!$K$2:$K$400,BOM!$B$2:$B$400,$A59,BOM!$E$2:$E$400,D$44) -> 54.888235 | E59: =SUMIFS(BOM!$K$2:$K$400,BOM!$B$2:$B$400,$A59,BOM!$E$2:$E$400,E$44) -> 369.51087 | F59: =SUMIFS(BOM!$K$2:$K$400,BOM!$B$2:$B$400,$A59,BOM!$E$2:$E$400,F$44) -> 1090.8163 | G59: =SUMIFS(BOM!$K$2:$K$400,BOM!$B$2:$B$400,$A59,BOM!$E$2:$E$400,G$44) -> 30.886598 | H59: =SUMIFS(BOM!$K$2:$K$400,BOM!$B$2:$B$400,$A59,BOM!$E$2:$E$400,H$44) -> 0 | I59: =SUMIFS(BOM!$K$2:$K$400,BOM!$B$2:$B$400,$A59,BOM!$E$2:$E$400,I$44) -> 45.329268 | J59: =SUMIFS(BOM!$K$2:$K$400,BOM!$B$2:$B$400,$A59,BOM!$E$2:$E$400,J$44) -> 0 | ... L59: =SUMIFS(BOM!$K$2:$K$400,BOM!$B$2:$B$400,$A59,BOM!$E$2:$E$400,L$44) -> 45.56701 | M59: =SUM(C59:L59) -> 1929.7305 | N59: =INDEX($C$43:$L$43,MATCH(MAX(C59:L59),C59:L59,0)) -> Copper winding wire
A62: D. Raw-material cost per unit by assembly module (₹) - where the material cost sits in the build sequence
A63: Product ID | B63: Product | C63: Motor / coil sub-assembly | D63: Heating sub-assembly | E63: Pump casing & impeller | F63: Jars & blades | G63: Blades & guard | H63: Body & structure | I63: Finishing (powder coat) | J63: Packaging | K63: Total (₹ / unit) | L63: Check vs block C
A64: P01 | B64: =INDEX(Products!$B$2:$B$16,MATCH($A64,Products!$A$2:$A$16,0)) -> Ceiling Fan 1200 mm - Induction | C64: =SUMIFS(BOM!$K$2:$K$400,BOM!$B$2:$B$400,$A64,BOM!$D$2:$D$400,C$63) -> 828.21242 | D64: =SUMIFS(BOM!$K$2:$K$400,BOM!$B$2:$B$400,$A64,BOM!$D$2:$D$400,D$63) -> 0 | E64: =SUMIFS(BOM!$K$2:$K$400,BOM!$B$2:$B$400,$A64,BOM!$D$2:$D$400,E$63) -> 0 | F64: =SUMIFS(BOM!$K$2:$K$400,BOM!$B$2:$B$400,$A64,BOM!$D$2:$D$400,F$63) -> 0 | G64: =SUMIFS(BOM!$K$2:$K$400,BOM!$B$2:$B$400,$A64,BOM!$D$2:$D$400,G$63) -> 0 | H64: =SUMIFS(BOM!$K$2:$K$400,BOM!$B$2:$B$400,$A64,BOM!$D$2:$D$400,H$63) -> 164.66471 | I64: =SUMIFS(BOM!$K$2:$K$400,BOM!$B$2:$B$400,$A64,BOM!$D$2:$D$400,I$63) -> 34.5 | J64: =SUMIFS(BOM!$K$2:$K$400,BOM!$B$2:$B$400,$A64,BOM!$D$2:$D$400,J$63) -> 40.206186 | K64: =SUM(C64:J64) -> 1067.5833 | L64: =K64-M45 -> 0
A65: P02 | B65: =INDEX(Products!$B$2:$B$16,MATCH($A65,Products!$A$2:$A$16,0)) -> Ceiling Fan 1200 mm - BLDC | C65: =SUMIFS(BOM!$K$2:$K$400,BOM!$B$2:$B$400,$A65,BOM!$D$2:$D$400,C$63) -> 660.59506 | D65: =SUMIFS(BOM!$K$2:$K$400,BOM!$B$2:$B$400,$A65,BOM!$D$2:$D$400,D$63) -> 0 | E65: =SUMIFS(BOM!$K$2:$K$400,BOM!$B$2:$B$400,$A65,BOM!$D$2:$D$400,E$63) -> 0 | F65: =SUMIFS(BOM!$K$2:$K$400,BOM!$B$2:$B$400,$A65,BOM!$D$2:$D$400,F$63) -> 0 | G65: =SUMIFS(BOM!$K$2:$K$400,BOM!$B$2:$B$400,$A65,BOM!$D$2:$D$400,G$63) -> 0 | H65: =SUMIFS(BOM!$K$2:$K$400,BOM!$B$2:$B$400,$A65,BOM!$D$2:$D$400,H$63) -> 145.06176 | I65: =SUMIFS(BOM!$K$2:$K$400,BOM!$B$2:$B$400,$A65,BOM!$D$2:$D$400,I$63) -> 30.1875 | J65: =SUMIFS(BOM!$K$2:$K$400,BOM!$B$2:$B$400,$A65,BOM!$D$2:$D$400,J$63) -> 38.597938 | K65: =SUM(C65:J65) -> 874.44226 | L65: =K65-M46 -> 0
A66: P03 | B66: =INDEX(Products!$B$2:$B$16,MATCH($A66,Products!$A$2:$A$16,0)) -> Pedestal Fan 400 mm | C66: =SUMIFS(BOM!$K$2:$K$400,BOM!$B$2:$B$400,$A66,BOM!$D$2:$D$400,C$63) -> 468.90428 | D66: =SUMIFS(BOM!$K$2:$K$400,BOM!$B$2:$B$400,$A66,BOM!$D$2:$D$400,D$63) -> 0 | E66: =SUMIFS(BOM!$K$2:$K$400,BOM!$B$2:$B$400,$A66,BOM!$D$2:$D$400,E$63) -> 0 | F66: =SUMIFS(BOM!$K$2:$K$400,BOM!$B$2:$B$400,$A66,BOM!$D$2:$D$400,F$63) -> 0 | G66: =SUMIFS(BOM!$K$2:$K$400,BOM!$B$2:$B$400,$A66,BOM!$D$2:$D$400,G$63) -> 33.092784 | H66: =SUMIFS(BOM!$K$2:$K$400,BOM!$B$2:$B$400,$A66,BOM!$D$2:$D$400,H$63) -> 185.86813 | I66: =SUMIFS(BOM!$K$2:$K$400,BOM!$B$2:$B$400,$A66,BOM!$D$2:$D$400,I$63) -> 30.1875 | J66: =SUMIFS(BOM!$K$2:$K$400,BOM!$B$2:$B$400,$A66,BOM!$D$2:$D$400,J$63) -> 64.329897 | K66: =SUM(C66:J66) -> 782.38259 | L66: =K66-M47 -> 0
A67: P04 | B67: =INDEX(Products!$B$2:$B$16,MATCH($A67,Products!$A$2:$A$16,0)) -> Table Fan 400 mm | C67: =SUMIFS(BOM!$K$2:$K$400,BOM!$B$2:$B$400,$A67,BOM!$D$2:$D$400,C$63) -> 355.94528 | D67: =SUMIFS(BOM!$K$2:$K$400,BOM!$B$2:$B$400,$A67,BOM!$D$2:$D$400,D$63) -> 0 | E67: =SUMIFS(BOM!$K$2:$K$400,BOM!$B$2:$B$400,$A67,BOM!$D$2:$D$400,E$63) -> 0 | F67: =SUMIFS(BOM!$K$2:$K$400,BOM!$B$2:$B$400,$A67,BOM!$D$2:$D$400,F$63) -> 0 | G67: =SUMIFS(BOM!$K$2:$K$400,BOM!$B$2:$B$400,$A67,BOM!$D$2:$D$400,G$63) -> 27.57732 | H67: =SUMIFS(BOM!$K$2:$K$400,BOM!$B$2:$B$400,$A67,BOM!$D$2:$D$400,H$63) -> 126.35522 | I67: =SUMIFS(BOM!$K$2:$K$400,BOM!$B$2:$B$400,$A67,BOM!$D$2:$D$400,I$63) -> 12.9375 | J67: =SUMIFS(BOM!$K$2:$K$400,BOM!$B$2:$B$400,$A67,BOM!$D$2:$D$400,J$63) -> 32.164948 | K67: =SUM(C67:J67) -> 554.98026 | L67: =K67-M48 -> 0
A68: P05 | B68: =INDEX(Products!$B$2:$B$16,MATCH($A68,Products!$A$2:$A$16,0)) -> Exhaust Fan 230 mm | C68: =SUMIFS(BOM!$K$2:$K$400,BOM!$B$2:$B$400,$A68,BOM!$D$2:$D$400,C$63) -> 166.80454 | D68: =SUMIFS(BOM!$K$2:$K$400,BOM!$B$2:$B$400,$A68,BOM!$D$2:$D$400,D$63) -> 0 | E68: =SUMIFS(BOM!$K$2:$K$400,BOM!$B$2:$B$400,$A68,BOM!$D$2:$D$400,E$63) -> 0 | F68: =SUMIFS(BOM!$K$2:$K$400,BOM!$B$2:$B$400,$A68,BOM!$D$2:$D$400,F$63) -> 0 | G68: =SUMIFS(BOM!$K$2:$K$400,BOM!$B$2:$B$400,$A68,BOM!$D$2:$D$400,G$63) -> 22.061856 | H68: =SUMIFS(BOM!$K$2:$K$400,BOM!$B$2:$B$400,$A68,BOM!$D$2:$D$400,H$63) -> 96.398696 | I68: =SUMIFS(BOM!$K$2:$K$400,BOM!$B$2:$B$400,$A68,BOM!$D$2:$D$400,I$63) -> 8.625 | J68: =SUMIFS(BOM!$K$2:$K$400,BOM!$B$2:$B$400,$A68,BOM!$D$2:$D$400,J$63) -> 21.443299 | K68: =SUM(C68:J68) -> 315.33339 | L68: =K68-M49 -> 0
A69: P06 | B69: =INDEX(Products!$B$2:$B$16,MATCH($A69,Products!$A$2:$A$16,0)) -> Personal Air Cooler 30 L | C69: =SUMIFS(BOM!$K$2:$K$400,BOM!$B$2:$B$400,$A69,BOM!$D$2:$D$400,C$63) -> 221.40065 | D69: =SUMIFS(BOM!$K$2:$K$400,BOM!$B$2:$B$400,$A69,BOM!$D$2:$D$400,D$63) -> 0 | E69: =SUMIFS(BOM!$K$2:$K$400,BOM!$B$2:$B$400,$A69,BOM!$D$2:$D$400,E$63) -> 0 | F69: =SUMIFS(BOM!$K$2:$K$400,BOM!$B$2:$B$400,$A69,BOM!$D$2:$D$400,F$63) -> 0 | G69: =SUMIFS(BOM!$K$2:$K$400,BOM!$B$2:$B$400,$A69,BOM!$D$2:$D$400,G$63) -> 0 | H69: =SUMIFS(BOM!$K$2:$K$400,BOM!$B$2:$B$400,$A69,BOM!$D$2:$D$400,H$63) -> 591.15546 | I69: =SUMIFS(BOM!$K$2:$K$400,BOM!$B$2:$B$400,$A69,BOM!$D$2:$D$400,I$63) -> 0 | J69: =SUMIFS(BOM!$K$2:$K$400,BOM!$B$2:$B$400,$A69,BOM!$D$2:$D$400,J$63) -> 85.773196 | K69: =SUM(C69:J69) -> 898.3293 | L69: =K69-M50 -> 0
A70: P07 | B70: =INDEX(Products!$B$2:$B$16,MATCH($A70,Products!$A$2:$A$16,0)) -> Mixer Grinder 500 W | C70: =SUMIFS(BOM!$K$2:$K$400,BOM!$B$2:$B$400,$A70,BOM!$D$2:$D$400,C$63) -> 459.50104 | D70: =SUMIFS(BOM!$K$2:$K$400,BOM!$B$2:$B$400,$A70,BOM!$D$2:$D$400,D$63) -> 0 | E70: =SUMIFS(BOM!$K$2:$K$400,BOM!$B$2:$B$400,$A70,BOM!$D$2:$D$400,E$63) -> 0 | F70: =SUMIFS(BOM!$K$2:$K$400,BOM!$B$2:$B$400,$A70,BOM!$D$2:$D$400,F$63) -> 151.09756 | G70: =SUMIFS(BOM!$K$2:$K$400,BOM!$B$2:$B$400,$A70,BOM!$D$2:$D$400,G$63) -> 0 | H70: =SUMIFS(BOM!$K$2:$K$400,BOM!$B$2:$B$400,$A70,BOM!$D$2:$D$400,H$63) -> 130.9558 | I70: =SUMIFS(BOM!$K$2:$K$400,BOM!$B$2:$B$400,$A70,BOM!$D$2:$D$400,I$63) -> 0 | J70: =SUMIFS(BOM!$K$2:$K$400,BOM!$B$2:$B$400,$A70,BOM!$D$2:$D$400,J$63) -> 29.484536 | K70: =SUM(C70:J70) -> 771.03894 | L70: =K70-M51 -> 0
A71: P08 | B71: =INDEX(Products!$B$2:$B$16,MATCH($A71,Products!$A$2:$A$16,0)) -> Mixer Grinder 750 W | C71: =SUMIFS(BOM!$K$2:$K$400,BOM!$B$2:$B$400,$A71,BOM!$D$2:$D$400,C$63) -> 628.21662 | D71: =SUMIFS(BOM!$K$2:$K$400,BOM!$B$2:$B$400,$A71,BOM!$D$2:$D$400,D$63) -> 0 | E71: =SUMIFS(BOM!$K$2:$K$400,BOM!$B$2:$B$400,$A71,BOM!$D$2:$D$400,E$63) -> 0 | F71: =SUMIFS(BOM!$K$2:$K$400,BOM!$B$2:$B$400,$A71,BOM!$D$2:$D$400,F$63) -> 196.42683 | G71: =SUMIFS(BOM!$K$2:$K$400,BOM!$B$2:$B$400,$A71,BOM!$D$2:$D$400,G$63) -> 0 | H71: =SUMIFS(BOM!$K$2:$K$400,BOM!$B$2:$B$400,$A71,BOM!$D$2:$D$400,H$63) -> 148.97826 | I71: =SUMIFS(BOM!$K$2:$K$400,BOM!$B$2:$B$400,$A71,BOM!$D$2:$D$400,I$63) -> 0 | J71: =SUMIFS(BOM!$K$2:$K$400,BOM!$B$2:$B$400,$A71,BOM!$D$2:$D$400,J$63) -> 33.237113 | K71: =SUM(C71:J71) -> 1006.8588 | L71: =K71-M52 -> 0
A72: P09 | B72: =INDEX(Products!$B$2:$B$16,MATCH($A72,Products!$A$2:$A$16,0)) -> Electric Kettle 1.5 L | C72: =SUMIFS(BOM!$K$2:$K$400,BOM!$B$2:$B$400,$A72,BOM!$D$2:$D$400,C$63) -> 0 | D72: =SUMIFS(BOM!$K$2:$K$400,BOM!$B$2:$B$400,$A72,BOM!$D$2:$D$400,D$63) -> 26 | E72: =SUMIFS(BOM!$K$2:$K$400,BOM!$B$2:$B$400,$A72,BOM!$D$2:$D$400,E$63) -> 0 | F72: =SUMIFS(BOM!$K$2:$K$400,BOM!$B$2:$B$400,$A72,BOM!$D$2:$D$400,F$63) -> 0 | G72: =SUMIFS(BOM!$K$2:$K$400,BOM!$B$2:$B$400,$A72,BOM!$D$2:$D$400,G$63) -> 0 | H72: =SUMIFS(BOM!$K$2:$K$400,BOM!$B$2:$B$400,$A72,BOM!$D$2:$D$400,H$63) -> 153.37654 | I72: =SUMIFS(BOM!$K$2:$K$400,BOM!$B$2:$B$400,$A72,BOM!$D$2:$D$400,I$63) -> 0 | J72: =SUMIFS(BOM!$K$2:$K$400,BOM!$B$2:$B$400,$A72,BOM!$D$2:$D$400,J$63) -> 17.690722 | K72: =SUM(C72:J72) -> 197.06726 | L72: =K72-M53 -> 0
A73: P10 | B73: =INDEX(Products!$B$2:$B$16,MATCH($A73,Products!$A$2:$A$16,0)) -> Induction Cooktop 2000 W | C73: =SUMIFS(BOM!$K$2:$K$400,BOM!$B$2:$B$400,$A73,BOM!$D$2:$D$400,C$63) -> 214.78549 | D73: =SUMIFS(BOM!$K$2:$K$400,BOM!$B$2:$B$400,$A73,BOM!$D$2:$D$400,D$63) -> 0 | E73: =SUMIFS(BOM!$K$2:$K$400,BOM!$B$2:$B$400,$A73,BOM!$D$2:$D$400,E$63) -> 0 | F73: =SUMIFS(BOM!$K$2:$K$400,BOM!$B$2:$B$400,$A73,BOM!$D$2:$D$400,F$63) -> 0 | G73: =SUMIFS(BOM!$K$2:$K$400,BOM!$B$2:$B$400,$A73,BOM!$D$2:$D$400,G$63) -> 0 | H73: =SUMIFS(BOM!$K$2:$K$400,BOM!$B$2:$B$400,$A73,BOM!$D$2:$D$400,H$63) -> 123.84281 | I73: =SUMIFS(BOM!$K$2:$K$400,BOM!$B$2:$B$400,$A73,BOM!$D$2:$D$400,I$63) -> 8.625 | J73: =SUMIFS(BOM!$K$2:$K$400,BOM!$B$2:$B$400,$A73,BOM!$D$2:$D$400,J$63) -> 24.123711 | K73: =SUM(C73:J73) -> 371.37702 | L73: =K73-M54 -> 0
A74: P11 | B74: =INDEX(Products!$B$2:$B$16,MATCH($A74,Products!$A$2:$A$16,0)) -> Sandwich Maker 750 W | C74: =SUMIFS(BOM!$K$2:$K$400,BOM!$B$2:$B$400,$A74,BOM!$D$2:$D$400,C$63) -> 0 | D74: =SUMIFS(BOM!$K$2:$K$400,BOM!$B$2:$B$400,$A74,BOM!$D$2:$D$400,D$63) -> 212.66486 | E74: =SUMIFS(BOM!$K$2:$K$400,BOM!$B$2:$B$400,$A74,BOM!$D$2:$D$400,E$63) -> 0 | F74: =SUMIFS(BOM!$K$2:$K$400,BOM!$B$2:$B$400,$A74,BOM!$D$2:$D$400,F$63) -> 0 | G74: =SUMIFS(BOM!$K$2:$K$400,BOM!$B$2:$B$400,$A74,BOM!$D$2:$D$400,G$63) -> 0 | H74: =SUMIFS(BOM!$K$2:$K$400,BOM!$B$2:$B$400,$A74,BOM!$D$2:$D$400,H$63) -> 72.475045 | I74: =SUMIFS(BOM!$K$2:$K$400,BOM!$B$2:$B$400,$A74,BOM!$D$2:$D$400,I$63) -> 0 | J74: =SUMIFS(BOM!$K$2:$K$400,BOM!$B$2:$B$400,$A74,BOM!$D$2:$D$400,J$63) -> 17.690722 | K74: =SUM(C74:J74) -> 302.83062 | L74: =K74-M55 -> 0
A75: P12 | B75: =INDEX(Products!$B$2:$B$16,MATCH($A75,Products!$A$2:$A$16,0)) -> Fan Room Heater 2000 W | C75: =SUMIFS(BOM!$K$2:$K$400,BOM!$B$2:$B$400,$A75,BOM!$D$2:$D$400,C$63) -> 114.29329 | D75: =SUMIFS(BOM!$K$2:$K$400,BOM!$B$2:$B$400,$A75,BOM!$D$2:$D$400,D$63) -> 108.33333 | E75: =SUMIFS(BOM!$K$2:$K$400,BOM!$B$2:$B$400,$A75,BOM!$D$2:$D$400,E$63) -> 0 | F75: =SUMIFS(BOM!$K$2:$K$400,BOM!$B$2:$B$400,$A75,BOM!$D$2:$D$400,F$63) -> 0 | G75: =SUMIFS(BOM!$K$2:$K$400,BOM!$B$2:$B$400,$A75,BOM!$D$2:$D$400,G$63) -> 0 | H75: =SUMIFS(BOM!$K$2:$K$400,BOM!$B$2:$B$400,$A75,BOM!$D$2:$D$400,H$63) -> 171.9406 | I75: =SUMIFS(BOM!$K$2:$K$400,BOM!$B$2:$B$400,$A75,BOM!$D$2:$D$400,I$63) -> 17.25 | J75: =SUMIFS(BOM!$K$2:$K$400,BOM!$B$2:$B$400,$A75,BOM!$D$2:$D$400,J$63) -> 29.484536 | K75: =SUM(C75:J75) -> 441.30176 | L75: =K75-M56 -> 0
... A78: P15 | B78: =INDEX(Products!$B$2:$B$16,MATCH($A78,Products!$A$2:$A$16,0)) -> Water Pump 0.5 HP Monoblock | C78: =SUMIFS(BOM!$K$2:$K$400,BOM!$B$2:$B$400,$A78,BOM!$D$2:$D$400,C$63) -> 1357.6735 | D78: =SUMIFS(BOM!$K$2:$K$400,BOM!$B$2:$B$400,$A78,BOM!$D$2:$D$400,D$63) -> 0 | E78: =SUMIFS(BOM!$K$2:$K$400,BOM!$B$2:$B$400,$A78,BOM!$D$2:$D$400,E$63) -> 445.72674 | F78: =SUMIFS(BOM!$K$2:$K$400,BOM!$B$2:$B$400,$A78,BOM!$D$2:$D$400,F$63) -> 0 | G78: =SUMIFS(BOM!$K$2:$K$400,BOM!$B$2:$B$400,$A78,BOM!$D$2:$D$400,G$63) -> 0 | H78: =SUMIFS(BOM!$K$2:$K$400,BOM!$B$2:$B$400,$A78,BOM!$D$2:$D$400,H$63) -> 54.888235 | I78: =SUMIFS(BOM!$K$2:$K$400,BOM!$B$2:$B$400,$A78,BOM!$D$2:$D$400,I$63) -> 25.875 | J78: =SUMIFS(BOM!$K$2:$K$400,BOM!$B$2:$B$400,$A78,BOM!$D$2:$D$400,J$63) -> 45.56701 | K78: =SUM(C78:J78) -> 1929.7305 | L78: =K78-M59 -> 0

Sheet Demand_Plan
A1: Demand & production plan - 12 months, make-to-forecast
A2: Production = demand, rounded up to the product's batch size: CEILING(base demand x seasonality index x demand multiplier, batch).
A3: Demand multiplier (lever on Assumptions) | D3: =Assumptions!$B$10 -> 1
A4: A. Seasonality index by product (average of the 12 months = 1.00; >1 = above-average month)
A5: Product ID | B5: Product | C5: Demand pattern | D5: Average index | E5: =Assumptions!$B$8 -> 46327 | F5: =EDATE(E5,1) -> 46357 | G5: =EDATE(F5,1) -> 46388 | H5: =EDATE(G5,1) -> 46419 | I5: =EDATE(H5,1) -> 46447 | J5: =EDATE(I5,1) -> 46478 | K5: =EDATE(J5,1) -> 46508 | L5: =EDATE(K5,1) -> 46539 | M5: =EDATE(L5,1) -> 46569 | ... P5: =EDATE(O5,1) -> 46661
A6: P01 | B6: =INDEX(Products!$B$2:$B$16,MATCH($A6,Products!$A$2:$A$16,0)) -> Ceiling Fan 1200 mm - Induction | C6: Summer peak (Apr-Jul) | D6: =AVERAGE(E6:P6) -> 1 | E6: 0.55 | F6: 0.45 | G6: 0.5 | H6: 0.85 | I6: 1.45 | J6: 1.75 | K6: 1.65 | L6: 1.3 | M6: 0.85 | N6: 0.75 | O6: 0.95 | P6: 0.95
A7: P02 | B7: =INDEX(Products!$B$2:$B$16,MATCH($A7,Products!$A$2:$A$16,0)) -> Ceiling Fan 1200 mm - BLDC | C7: Summer peak (Apr-Jul) | D7: =AVERAGE(E7:P7) -> 1 | E7: 0.55 | F7: 0.45 | G7: 0.5 | H7: 0.85 | I7: 1.45 | J7: 1.75 | K7: 1.65 | L7: 1.3 | M7: 0.85 | N7: 0.75 | O7: 0.95 | P7: 0.95
A8: P03 | B8: =INDEX(Products!$B$2:$B$16,MATCH($A8,Products!$A$2:$A$16,0)) -> Pedestal Fan 400 mm | C8: Summer peak (Apr-Jul) | D8: =AVERAGE(E8:P8) -> 1 | E8: 0.65 | F8: 0.55 | G8: 0.6 | H8: 0.9 | I8: 1.4 | J8: 1.6 | K8: 1.5 | L8: 1.2 | M8: 0.9 | N8: 0.8 | O8: 0.95 | P8: 0.95
A9: P04 | B9: =INDEX(Products!$B$2:$B$16,MATCH($A9,Products!$A$2:$A$16,0)) -> Table Fan 400 mm | C9: Summer peak (Apr-Jul) | D9: =AVERAGE(E9:P9) -> 1 | E9: 0.65 | F9: 0.55 | G9: 0.6 | H9: 0.9 | I9: 1.4 | J9: 1.6 | K9: 1.5 | L9: 1.2 | M9: 0.9 | N9: 0.8 | O9: 0.95 | P9: 0.95
A10: P05 | B10: =INDEX(Products!$B$2:$B$16,MATCH($A10,Products!$A$2:$A$16,0)) -> Exhaust Fan 230 mm | C10: Mild summer lift | D10: =AVERAGE(E10:P10) -> 1 | E10: 0.9 | F10: 0.85 | G10: 0.85 | H10: 0.95 | I10: 1.15 | J10: 1.2 | K10: 1.2 | L10: 1.1 | M10: 0.95 | N10: 0.9 | O10: 0.95 | P10: 1
A11: P06 | B11: =INDEX(Products!$B$2:$B$16,MATCH($A11,Products!$A$2:$A$16,0)) -> Personal Air Cooler 30 L | C11: Strong summer peak (Apr-Jun) | D11: =AVERAGE(E11:P11) -> 1 | E11: 0.1 | F11: 0.05 | G11: 0.1 | H11: 0.6 | I11: 2.2 | J11: 3 | K11: 2.7 | L11: 1.6 | M11: 0.8 | N11: 0.4 | O11: 0.35 | P11: 0.1
A12: P07 | B12: =INDEX(Products!$B$2:$B$16,MATCH($A12,Products!$A$2:$A$16,0)) -> Mixer Grinder 500 W | C12: Festive & weddings (Oct-Dec) | D12: =AVERAGE(E12:P12) -> 1 | E12: 1.35 | F12: 1.1 | G12: 0.95 | H12: 1.05 | I12: 0.95 | J12: 0.85 | K12: 0.85 | L12: 0.85 | M12: 0.85 | N12: 0.9 | O12: 1 | P12: 1.3
A13: P08 | B13: =INDEX(Products!$B$2:$B$16,MATCH($A13,Products!$A$2:$A$16,0)) -> Mixer Grinder 750 W | C13: Festive & weddings (Oct-Dec) | D13: =AVERAGE(E13:P13) -> 1 | E13: 1.35 | F13: 1.1 | G13: 0.95 | H13: 1.05 | I13: 0.95 | J13: 0.85 | K13: 0.85 | L13: 0.85 | M13: 0.85 | N13: 0.9 | O13: 1 | P13: 1.3
A14: P09 | B14: =INDEX(Products!$B$2:$B$16,MATCH($A14,Products!$A$2:$A$16,0)) -> Electric Kettle 1.5 L | C14: Winter lift (Dec-Feb) | D14: =AVERAGE(E14:P14) -> 1 | E14: 1.25 | F14: 1.45 | G14: 1.4 | H14: 1.1 | I14: 0.85 | J14: 0.7 | K14: 0.65 | L14: 0.7 | M14: 0.8 | N14: 0.85 | O14: 0.95 | P14: 1.3
A15: P10 | B15: =INDEX(Products!$B$2:$B$16,MATCH($A15,Products!$A$2:$A$16,0)) -> Induction Cooktop 2000 W | C15: Festive lift (Oct-Dec) | D15: =AVERAGE(E15:P15) -> 1 | E15: 1.3 | F15: 1.05 | G15: 0.95 | H15: 0.95 | I15: 0.9 | J15: 0.85 | K15: 0.85 | L15: 0.9 | M15: 0.9 | N15: 0.95 | O15: 1.05 | P15: 1.35
A16: P11 | B16: =INDEX(Products!$B$2:$B$16,MATCH($A16,Products!$A$2:$A$16,0)) -> Sandwich Maker 750 W | C16: Festive and winter lift | D16: =AVERAGE(E16:P16) -> 1 | E16: 1.2 | F16: 1.15 | G16: 1.1 | H16: 1 | I16: 0.9 | J16: 0.8 | K16: 0.8 | L16: 0.85 | M16: 0.9 | N16: 0.95 | O16: 1.05 | P16: 1.3
A17: P12 | B17: =INDEX(Products!$B$2:$B$16,MATCH($A17,Products!$A$2:$A$16,0)) -> Fan Room Heater 2000 W | C17: Winter peak (Dec-Feb) | D17: =AVERAGE(E17:P17) -> 1 | E17: 2.2 | F17: 3 | G17: 3.1 | H17: 1.7 | I17: 0.4 | J17: 0.1 | K17: 0.05 | L17: 0.05 | M17: 0.05 | N17: 0.1 | O17: 0.35 | P17: 0.9
... A20: P15 | B20: =INDEX(Products!$B$2:$B$16,MATCH($A20,Products!$A$2:$A$16,0)) -> Water Pump 0.5 HP Monoblock | C20: Summer, pre-monsoon (Mar-Jul) | D20: =AVERAGE(E20:P20) -> 1 | E20: 0.85 | F20: 0.8 | G20: 0.85 | H20: 0.95 | I20: 1.2 | J20: 1.35 | K20: 1.35 | L20: 1.25 | M20: 1 | N20: 0.85 | O20: 0.75 | P20: 0.8
A22: B. Production plan (units per month)
A23: Product ID | B23: Product | C23: Base demand (units / month) | D23: Batch size (units) | E23: =E$5 -> 46327 | F23: =F$5 -> 46357 | G23: =G$5 -> 46388 | H23: =H$5 -> 46419 | I23: =I$5 -> 46447 | J23: =J$5 -> 46478 | K23: =K$5 -> 46508 | L23: =L$5 -> 46539 | ... P23: =P$5 -> 46661 | Q23: Annual units | R23: Peak month
A24: =A6 -> P01 | B24: =B6 -> Ceiling Fan 1200 mm - Induction | C24: =INDEX(Products!$I$2:$I$16,MATCH($A24,Products!$A$2:$A$16,0)) -> 38000 | D24: =INDEX(Products!$G$2:$G$16,MATCH($A24,Products!$A$2:$A$16,0)) -> 500 | E24: =CEILING(ROUND($C24*E6*Assumptions!$B$10,3),$D24) -> 21000 | F24: =CEILING(ROUND($C24*F6*Assumptions!$B$10,3),$D24) -> 17500 | G24: =CEILING(ROUND($C24*G6*Assumptions!$B$10,3),$D24) -> 19000 | H24: =CEILING(ROUND($C24*H6*Assumptions!$B$10,3),$D24) -> 32500 | I24: =CEILING(ROUND($C24*I6*Assumptions!$B$10,3),$D24) -> 55500 | J24: =CEILING(ROUND($C24*J6*Assumptions!$B$10,3),$D24) -> 66500 | K24: =CEILING(ROUND($C24*K6*Assumptions!$B$10,3),$D24) -> 63000 | L24: =CEILING(ROUND($C24*L6*Assumptions!$B$10,3),$D24) -> 49500 | ... P24: =CEILING(ROUND($C24*P6*Assumptions!$B$10,3),$D24) -> 36500 | Q24: =SUM(E24:P24) -> 458500 | R24: =INDEX($E$23:$P$23,MATCH(MAX(E24:P24),E24:P24,0)) -> 46478
A25: =A7 -> P02 | B25: =B7 -> Ceiling Fan 1200 mm - BLDC | C25: =INDEX(Products!$I$2:$I$16,MATCH($A25,Products!$A$2:$A$16,0)) -> 12000 | D25: =INDEX(Products!$G$2:$G$16,MATCH($A25,Products!$A$2:$A$16,0)) -> 250 | E25: =CEILING(ROUND($C25*E7*Assumptions!$B$10,3),$D25) -> 6750 | F25: =CEILING(ROUND($C25*F7*Assumptions!$B$10,3),$D25) -> 5500 | G25: =CEILING(ROUND($C25*G7*Assumptions!$B$10,3),$D25) -> 6000 | H25: =CEILING(ROUND($C25*H7*Assumptions!$B$10,3),$D25) -> 10250 | I25: =CEILING(ROUND($C25*I7*Assumptions!$B$10,3),$D25) -> 17500 | J25: =CEILING(ROUND($C25*J7*Assumptions!$B$10,3),$D25) -> 21000 | K25: =CEILING(ROUND($C25*K7*Assumptions!$B$10,3),$D25) -> 20000 | L25: =CEILING(ROUND($C25*L7*Assumptions!$B$10,3),$D25) -> 15750 | ... P25: =CEILING(ROUND($C25*P7*Assumptions!$B$10,3),$D25) -> 11500 | Q25: =SUM(E25:P25) -> 145000 | R25: =INDEX($E$23:$P$23,MATCH(MAX(E25:P25),E25:P25,0)) -> 46478
A26: =A8 -> P03 | B26: =B8 -> Pedestal Fan 400 mm | C26: =INDEX(Products!$I$2:$I$16,MATCH($A26,Products!$A$2:$A$16,0)) -> 9000 | D26: =INDEX(Products!$G$2:$G$16,MATCH($A26,Products!$A$2:$A$16,0)) -> 250 | E26: =CEILING(ROUND($C26*E8*Assumptions!$B$10,3),$D26) -> 6000 | F26: =CEILING(ROUND($C26*F8*Assumptions!$B$10,3),$D26) -> 5000 | G26: =CEILING(ROUND($C26*G8*Assumptions!$B$10,3),$D26) -> 5500 | H26: =CEILING(ROUND($C26*H8*Assumptions!$B$10,3),$D26) -> 8250 | I26: =CEILING(ROUND($C26*I8*Assumptions!$B$10,3),$D26) -> 12750 | J26: =CEILING(ROUND($C26*J8*Assumptions!$B$10,3),$D26) -> 14500 | K26: =CEILING(ROUND($C26*K8*Assumptions!$B$10,3),$D26) -> 13500 | L26: =CEILING(ROUND($C26*L8*Assumptions!$B$10,3),$D26) -> 11000 | ... P26: =CEILING(ROUND($C26*P8*Assumptions!$B$10,3),$D26) -> 8750 | Q26: =SUM(E26:P26) -> 109500 | R26: =INDEX($E$23:$P$23,MATCH(MAX(E26:P26),E26:P26,0)) -> 46478
A27: =A9 -> P04 | B27: =B9 -> Table Fan 400 mm | C27: =INDEX(Products!$I$2:$I$16,MATCH($A27,Products!$A$2:$A$16,0)) -> 14000 | D27: =INDEX(Products!$G$2:$G$16,MATCH($A27,Products!$A$2:$A$16,0)) -> 500 | E27: =CEILING(ROUND($C27*E9*Assumptions!$B$10,3),$D27) -> 9500 | F27: =CEILING(ROUND($C27*F9*Assumptions!$B$10,3),$D27) -> 8000 | G27: =CEILING(ROUND($C27*G9*Assumptions!$B$10,3),$D27) -> 8500 | H27: =CEILING(ROUND($C27*H9*Assumptions!$B$10,3),$D27) -> 13000 | I27: =CEILING(ROUND($C27*I9*Assumptions!$B$10,3),$D27) -> 20000 | J27: =CEILING(ROUND($C27*J9*Assumptions!$B$10,3),$D27) -> 22500 | K27: =CEILING(ROUND($C27*K9*Assumptions!$B$10,3),$D27) -> 21000 | L27: =CEILING(ROUND($C27*L9*Assumptions!$B$10,3),$D27) -> 17000 | ... P27: =CEILING(ROUND($C27*P9*Assumptions!$B$10,3),$D27) -> 13500 | Q27: =SUM(E27:P27) -> 171000 | R27: =INDEX($E$23:$P$23,MATCH(MAX(E27:P27),E27:P27,0)) -> 46478
A28: =A10 -> P05 | B28: =B10 -> Exhaust Fan 230 mm | C28: =INDEX(Products!$I$2:$I$16,MATCH($A28,Products!$A$2:$A$16,0)) -> 16000 | D28: =INDEX(Products!$G$2:$G$16,MATCH($A28,Products!$A$2:$A$16,0)) -> 500 | E28: =CEILING(ROUND($C28*E10*Assumptions!$B$10,3),$D28) -> 14500 | F28: =CEILING(ROUND($C28*F10*Assumptions!$B$10,3),$D28) -> 14000 | G28: =CEILING(ROUND($C28*G10*Assumptions!$B$10,3),$D28) -> 14000 | H28: =CEILING(ROUND($C28*H10*Assumptions!$B$10,3),$D28) -> 15500 | I28: =CEILING(ROUND($C28*I10*Assumptions!$B$10,3),$D28) -> 18500 | J28: =CEILING(ROUND($C28*J10*Assumptions!$B$10,3),$D28) -> 19500 | K28: =CEILING(ROUND($C28*K10*Assumptions!$B$10,3),$D28) -> 19500 | L28: =CEILING(ROUND($C28*L10*Assumptions!$B$10,3),$D28) -> 18000 | ... P28: =CEILING(ROUND($C28*P10*Assumptions!$B$10,3),$D28) -> 16000 | Q28: =SUM(E28:P28) -> 195000 | R28: =INDEX($E$23:$P$23,MATCH(MAX(E28:P28),E28:P28,0)) -> 46478
A29: =A11 -> P06 | B29: =B11 -> Personal Air Cooler 30 L | C29: =INDEX(Products!$I$2:$I$16,MATCH($A29,Products!$A$2:$A$16,0)) -> 6500 | D29: =INDEX(Products!$G$2:$G$16,MATCH($A29,Products!$A$2:$A$16,0)) -> 100 | E29: =CEILING(ROUND($C29*E11*Assumptions!$B$10,3),$D29) -> 700 | F29: =CEILING(ROUND($C29*F11*Assumptions!$B$10,3),$D29) -> 400 | G29: =CEILING(ROUND($C29*G11*Assumptions!$B$10,3),$D29) -> 700 | H29: =CEILING(ROUND($C29*H11*Assumptions!$B$10,3),$D29) -> 3900 | I29: =CEILING(ROUND($C29*I11*Assumptions!$B$10,3),$D29) -> 14300 | J29: =CEILING(ROUND($C29*J11*Assumptions!$B$10,3),$D29) -> 19500 | K29: =CEILING(ROUND($C29*K11*Assumptions!$B$10,3),$D29) -> 17600 | L29: =CEILING(ROUND($C29*L11*Assumptions!$B$10,3),$D29) -> 10400 | ... P29: =CEILING(ROUND($C29*P11*Assumptions!$B$10,3),$D29) -> 700 | Q29: =SUM(E29:P29) -> 78300 | R29: =INDEX($E$23:$P$23,MATCH(MAX(E29:P29),E29:P29,0)) -> 46478
A30: =A12 -> P07 | B30: =B12 -> Mixer Grinder 500 W | C30: =INDEX(Products!$I$2:$I$16,MATCH($A30,Products!$A$2:$A$16,0)) -> 18000 | D30: =INDEX(Products!$G$2:$G$16,MATCH($A30,Products!$A$2:$A$16,0)) -> 500 | E30: =CEILING(ROUND($C30*E12*Assumptions!$B$10,3),$D30) -> 24500 | F30: =CEILING(ROUND($C30*F12*Assumptions!$B$10,3),$D30) -> 20000 | G30: =CEILING(ROUND($C30*G12*Assumptions!$B$10,3),$D30) -> 17500 | H30: =CEILING(ROUND($C30*H12*Assumptions!$B$10,3),$D30) -> 19000 | I30: =CEILING(ROUND($C30*I12*Assumptions!$B$10,3),$D30) -> 17500 | J30: =CEILING(ROUND($C30*J12*Assumptions!$B$10,3),$D30) -> 15500 | K30: =CEILING(ROUND($C30*K12*Assumptions!$B$10,3),$D30) -> 15500 | L30: =CEILING(ROUND($C30*L12*Assumptions!$B$10,3),$D30) -> 15500 | ... P30: =CEILING(ROUND($C30*P12*Assumptions!$B$10,3),$D30) -> 23500 | Q30: =SUM(E30:P30) -> 218500 | R30: =INDEX($E$23:$P$23,MATCH(MAX(E30:P30),E30:P30,0)) -> 46327
A31: =A13 -> P08 | B31: =B13 -> Mixer Grinder 750 W | C31: =INDEX(Products!$I$2:$I$16,MATCH($A31,Products!$A$2:$A$16,0)) -> 14000 | D31: =INDEX(Products!$G$2:$G$16,MATCH($A31,Products!$A$2:$A$16,0)) -> 250 | E31: =CEILING(ROUND($C31*E13*Assumptions!$B$10,3),$D31) -> 19000 | F31: =CEILING(ROUND($C31*F13*Assumptions!$B$10,3),$D31) -> 15500 | G31: =CEILING(ROUND($C31*G13*Assumptions!$B$10,3),$D31) -> 13500 | H31: =CEILING(ROUND($C31*H13*Assumptions!$B$10,3),$D31) -> 14750 | I31: =CEILING(ROUND($C31*I13*Assumptions!$B$10,3),$D31) -> 13500 | J31: =CEILING(ROUND($C31*J13*Assumptions!$B$10,3),$D31) -> 12000 | K31: =CEILING(ROUND($C31*K13*Assumptions!$B$10,3),$D31) -> 12000 | L31: =CEILING(ROUND($C31*L13*Assumptions!$B$10,3),$D31) -> 12000 | ... P31: =CEILING(ROUND($C31*P13*Assumptions!$B$10,3),$D31) -> 18250 | Q31: =SUM(E31:P31) -> 169250 | R31: =INDEX($E$23:$P$23,MATCH(MAX(E31:P31),E31:P31,0)) -> 46327
A32: =A14 -> P09 | B32: =B14 -> Electric Kettle 1.5 L | C32: =INDEX(Products!$I$2:$I$16,MATCH($A32,Products!$A$2:$A$16,0)) -> 22000 | D32: =INDEX(Products!$G$2:$G$16,MATCH($A32,Products!$A$2:$A$16,0)) -> 500 | E32: =CEILING(ROUND($C32*E14*Assumptions!$B$10,3),$D32) -> 27500 | F32: =CEILING(ROUND($C32*F14*Assumptions!$B$10,3),$D32) -> 32000 | G32: =CEILING(ROUND($C32*G14*Assumptions!$B$10,3),$D32) -> 31000 | H32: =CEILING(ROUND($C32*H14*Assumptions!$B$10,3),$D32) -> 24500 | I32: =CEILING(ROUND($C32*I14*Assumptions!$B$10,3),$D32) -> 19000 | J32: =CEILING(ROUND($C32*J14*Assumptions!$B$10,3),$D32) -> 15500 | K32: =CEILING(ROUND($C32*K14*Assumptions!$B$10,3),$D32) -> 14500 | L32: =CEILING(ROUND($C32*L14*Assumptions!$B$10,3),$D32) -> 15500 | ... P32: =CEILING(ROUND($C32*P14*Assumptions!$B$10,3),$D32) -> 29000 | Q32: =SUM(E32:P32) -> 266500 | R32: =INDEX($E$23:$P$23,MATCH(MAX(E32:P32),E32:P32,0)) -> 46357
A33: =A15 -> P10 | B33: =B15 -> Induction Cooktop 2000 W | C33: =INDEX(Products!$I$2:$I$16,MATCH($A33,Products!$A$2:$A$16,0)) -> 11000 | D33: =INDEX(Products!$G$2:$G$16,MATCH($A33,Products!$A$2:$A$16,0)) -> 250 | E33: =CEILING(ROUND($C33*E15*Assumptions!$B$10,3),$D33) -> 14500 | F33: =CEILING(ROUND($C33*F15*Assumptions!$B$10,3),$D33) -> 11750 | G33: =CEILING(ROUND($C33*G15*Assumptions!$B$10,3),$D33) -> 10500 | H33: =CEILING(ROUND($C33*H15*Assumptions!$B$10,3),$D33) -> 10500 | I33: =CEILING(ROUND($C33*I15*Assumptions!$B$10,3),$D33) -> 10000 | J33: =CEILING(ROUND($C33*J15*Assumptions!$B$10,3),$D33) -> 9500 | K33: =CEILING(ROUND($C33*K15*Assumptions!$B$10,3),$D33) -> 9500 | L33: =CEILING(ROUND($C33*L15*Assumptions!$B$10,3),$D33) -> 10000 | ... P33: =CEILING(ROUND($C33*P15*Assumptions!$B$10,3),$D33) -> 15000 | Q33: =SUM(E33:P33) -> 133500 | R33: =INDEX($E$23:$P$23,MATCH(MAX(E33:P33),E33:P33,0)) -> 46661
A34: =A16 -> P11 | B34: =B16 -> Sandwich Maker 750 W | C34: =INDEX(Products!$I$2:$I$16,MATCH($A34,Products!$A$2:$A$16,0)) -> 9500 | D34: =INDEX(Products!$G$2:$G$16,MATCH($A34,Products!$A$2:$A$16,0)) -> 250 | E34: =CEILING(ROUND($C34*E16*Assumptions!$B$10,3),$D34) -> 11500 | F34: =CEILING(ROUND($C34*F16*Assumptions!$B$10,3),$D34) -> 11000 | G34: =CEILING(ROUND($C34*G16*Assumptions!$B$10,3),$D34) -> 10500 | H34: =CEILING(ROUND($C34*H16*Assumptions!$B$10,3),$D34) -> 9500 | I34: =CEILING(ROUND($C34*I16*Assumptions!$B$10,3),$D34) -> 8750 | J34: =CEILING(ROUND($C34*J16*Assumptions!$B$10,3),$D34) -> 7750 | K34: =CEILING(ROUND($C34*K16*Assumptions!$B$10,3),$D34) -> 7750 | L34: =CEILING(ROUND($C34*L16*Assumptions!$B$10,3),$D34) -> 8250 | ... P34: =CEILING(ROUND($C34*P16*Assumptions!$B$10,3),$D34) -> 12500 | Q34: =SUM(E34:P34) -> 115500 | R34: =INDEX($E$23:$P$23,MATCH(MAX(E34:P34),E34:P34,0)) -> 46661
A35: =A17 -> P12 | B35: =B17 -> Fan Room Heater 2000 W | C35: =INDEX(Products!$I$2:$I$16,MATCH($A35,Products!$A$2:$A$16,0)) -> 7000 | D35: =INDEX(Products!$G$2:$G$16,MATCH($A35,Products!$A$2:$A$16,0)) -> 250 | E35: =CEILING(ROUND($C35*E17*Assumptions!$B$10,3),$D35) -> 15500 | F35: =CEILING(ROUND($C35*F17*Assumptions!$B$10,3),$D35) -> 21000 | G35: =CEILING(ROUND($C35*G17*Assumptions!$B$10,3),$D35) -> 21750 | H35: =CEILING(ROUND($C35*H17*Assumptions!$B$10,3),$D35) -> 12000 | I35: =CEILING(ROUND($C35*I17*Assumptions!$B$10,3),$D35) -> 3000 | J35: =CEILING(ROUND($C35*J17*Assumptions!$B$10,3),$D35) -> 750 | K35: =CEILING(ROUND($C35*K17*Assumptions!$B$10,3),$D35) -> 500 | L35: =CEILING(ROUND($C35*L17*Assumptions!$B$10,3),$D35) -> 500 | ... P35: =CEILING(ROUND($C35*P17*Assumptions!$B$10,3),$D35) -> 6500 | Q35: =SUM(E35:P35) -> 85250 | R35: =INDEX($E$23:$P$23,MATCH(MAX(E35:P35),E35:P35,0)) -> 46388
... A38: =A20 -> P15 | B38: =B20 -> Water Pump 0.5 HP Monoblock | C38: =INDEX(Products!$I$2:$I$16,MATCH($A38,Products!$A$2:$A$16,0)) -> 4500 | D38: =INDEX(Products!$G$2:$G$16,MATCH($A38,Products!$A$2:$A$16,0)) -> 100 | E38: =CEILING(ROUND($C38*E20*Assumptions!$B$10,3),$D38) -> 3900 | F38: =CEILING(ROUND($C38*F20*Assumptions!$B$10,3),$D38) -> 3600 | G38: =CEILING(ROUND($C38*G20*Assumptions!$B$10,3),$D38) -> 3900 | H38: =CEILING(ROUND($C38*H20*Assumptions!$B$10,3),$D38) -> 4300 | I38: =CEILING(ROUND($C38*I20*Assumptions!$B$10,3),$D38) -> 5400 | J38: =CEILING(ROUND($C38*J20*Assumptions!$B$10,3),$D38) -> 6100 | K38: =CEILING(ROUND($C38*K20*Assumptions!$B$10,3),$D38) -> 6100 | L38: =CEILING(ROUND($C38*L20*Assumptions!$B$10,3),$D38) -> 5700 | ... P38: =CEILING(ROUND($C38*P20*Assumptions!$B$10,3),$D38) -> 3600 | Q38: =SUM(E38:P38) -> 54400 | R38: =INDEX($E$23:$P$23,MATCH(MAX(E38:P38),E38:P38,0)) -> 46478
A39: Total units | E39: =SUM(E24:E38) -> 224850 | F39: =SUM(F24:F38) -> 220750 | G39: =SUM(G24:G38) -> 218350 | H39: =SUM(H24:H38) -> 221950 | I39: =SUM(I24:I38) -> 246200 | J39: =SUM(J24:J38) -> 253100 | K39: =SUM(K24:K38) -> 240450 | L39: =SUM(L24:L38) -> 210100 | ... P39: =SUM(P24:P38) -> 240300 | Q39: =SUM(E39:P39) -> 2620700 | R39: =INDEX($E$23:$P$23,MATCH(MAX(E39:P39),E39:P39,0)) -> 46478
A40: Revenue (₹ lakh) | B40: units x selling price, ex-GST | E40: =SUMPRODUCT(E24:E38,Products!$O$2:$O$16)/Assumptions!$B$20 -> 2717.44 | F40: =SUMPRODUCT(F24:F38,Products!$O$2:$O$16)/Assumptions!$B$20 -> 2462.5875 | G40: =SUMPRODUCT(G24:G38,Products!$O$2:$O$16)/Assumptions!$B$20 -> 2434.59 | H40: =SUMPRODUCT(H24:H38,Products!$O$2:$O$16)/Assumptions!$B$20 -> 2875.3175 | I40: =SUMPRODUCT(I24:I38,Products!$O$2:$O$16)/Assumptions!$B$20 -> 3746.18 | J40: =SUMPRODUCT(J24:J38,Products!$O$2:$O$16)/Assumptions!$B$20 -> 4114.84 | K40: =SUMPRODUCT(K24:K38,Products!$O$2:$O$16)/Assumptions!$B$20 -> 3922.03 | L40: =SUMPRODUCT(L24:L38,Products!$O$2:$O$16)/Assumptions!$B$20 -> 3287.39 | ... P40: =SUMPRODUCT(P24:P38,Products!$O$2:$O$16)/Assumptions!$B$20 -> 3128.3575 | Q40: =SUM(E40:P40) -> 36387.618 | R40: =INDEX($E$23:$P$23,MATCH(MAX(E40:P40),E40:P40,0)) -> 46478
A42: C. Monthly revenue by product family (₹ lakh)
A43: Family | E43: =E$5 -> 46327 | F43: =F$5 -> 46357 | G43: =G$5 -> 46388 | H43: =H$5 -> 46419 | I43: =I$5 -> 46447 | J43: =J$5 -> 46478 | K43: =K$5 -> 46508 | L43: =L$5 -> 46539 | ... P43: =P$5 -> 46661 | Q43: Annual (₹ lakh)
A44: Fans & Cooling | E44: =SUMPRODUCT((Products!$C$2:$C$16=$A44)*E$24:E$38*Products!$O$2:$O$16)/Assumptions!$B$20 -> 936.405 | F44: =SUMPRODUCT((Products!$C$2:$C$16=$A44)*F$24:F$38*Products!$O$2:$O$16)/Assumptions!$B$20 -> 787.66 | G44: =SUMPRODUCT((Products!$C$2:$C$16=$A44)*G$24:G$38*Products!$O$2:$O$16)/Assumptions!$B$20 -> 852.28 | H44: =SUMPRODUCT((Products!$C$2:$C$16=$A44)*H$24:H$38*Products!$O$2:$O$16)/Assumptions!$B$20 -> 1418.31 | I44: =SUMPRODUCT((Products!$C$2:$C$16=$A44)*I$24:I$38*Products!$O$2:$O$16)/Assumptions!$B$20 -> 2484.295 | J44: =SUMPRODUCT((Products!$C$2:$C$16=$A44)*J$24:J$38*Products!$O$2:$O$16)/Assumptions!$B$20 -> 2979.5 | K44: =SUMPRODUCT((Products!$C$2:$C$16=$A44)*K$24:K$38*Products!$O$2:$O$16)/Assumptions!$B$20 -> 2805.34 | L44: =SUMPRODUCT((Products!$C$2:$C$16=$A44)*L$24:L$38*Products!$O$2:$O$16)/Assumptions!$B$20 -> 2161.185 | ... P44: =SUMPRODUCT((Products!$C$2:$C$16=$A44)*P$24:P$38*Products!$O$2:$O$16)/Assumptions!$B$20 -> 1478.63 | Q44: =SUM(E44:P44) -> 20095.045
A45: Kitchen Appliances | E45: =SUMPRODUCT((Products!$C$2:$C$16=$A45)*E$24:E$38*Products!$O$2:$O$16)/Assumptions!$B$20 -> 1257.85 | F45: =SUMPRODUCT((Products!$C$2:$C$16=$A45)*F$24:F$38*Products!$O$2:$O$16)/Assumptions!$B$20 -> 1089.9875 | G45: =SUMPRODUCT((Products!$C$2:$C$16=$A45)*G$24:G$38*Products!$O$2:$O$16)/Assumptions!$B$20 -> 979.425 | H45: =SUMPRODUCT((Products!$C$2:$C$16=$A45)*H$24:H$38*Products!$O$2:$O$16)/Assumptions!$B$20 -> 984.3125 | I45: =SUMPRODUCT((Products!$C$2:$C$16=$A45)*I$24:I$38*Products!$O$2:$O$16)/Assumptions!$B$20 -> 890.825 | J45: =SUMPRODUCT((Products!$C$2:$C$16=$A45)*J$24:J$38*Products!$O$2:$O$16)/Assumptions!$B$20 -> 793.975 | K45: =SUMPRODUCT((Products!$C$2:$C$16=$A45)*K$24:K$38*Products!$O$2:$O$16)/Assumptions!$B$20 -> 788.375 | L45: =SUMPRODUCT((Products!$C$2:$C$16=$A45)*L$24:L$38*Products!$O$2:$O$16)/Assumptions!$B$20 -> 806.5 | ... P45: =SUMPRODUCT((Products!$C$2:$C$16=$A45)*P$24:P$38*Products!$O$2:$O$16)/Assumptions!$B$20 -> 1251.7375 | Q45: =SUM(E45:P45) -> 11499.913
A46: Heating & Water | E46: =SUMPRODUCT((Products!$C$2:$C$16=$A46)*E$24:E$38*Products!$O$2:$O$16)/Assumptions!$B$20 -> 523.185 | F46: =SUMPRODUCT((Products!$C$2:$C$16=$A46)*F$24:F$38*Products!$O$2:$O$16)/Assumptions!$B$20 -> 584.94 | G46: =SUMPRODUCT((Products!$C$2:$C$16=$A46)*G$24:G$38*Products!$O$2:$O$16)/Assumptions!$B$20 -> 602.885 | H46: =SUMPRODUCT((Products!$C$2:$C$16=$A46)*H$24:H$38*Products!$O$2:$O$16)/Assumptions!$B$20 -> 472.695 | I46: =SUMPRODUCT((Products!$C$2:$C$16=$A46)*I$24:I$38*Products!$O$2:$O$16)/Assumptions!$B$20 -> 371.06 | J46: =SUMPRODUCT((Products!$C$2:$C$16=$A46)*J$24:J$38*Products!$O$2:$O$16)/Assumptions!$B$20 -> 341.365 | K46: =SUMPRODUCT((Products!$C$2:$C$16=$A46)*K$24:K$38*Products!$O$2:$O$16)/Assumptions!$B$20 -> 328.315 | L46: =SUMPRODUCT((Products!$C$2:$C$16=$A46)*L$24:L$38*Products!$O$2:$O$16)/Assumptions!$B$20 -> 319.705 | ... P46: =SUMPRODUCT((Products!$C$2:$C$16=$A46)*P$24:P$38*Products!$O$2:$O$16)/Assumptions!$B$20 -> 397.99 | Q46: =SUM(E46:P46) -> 4792.66
A47: Total | E47: =SUM(E44:E46) -> 2717.44 | F47: =SUM(F44:F46) -> 2462.5875 | G47: =SUM(G44:G46) -> 2434.59 | H47: =SUM(H44:H46) -> 2875.3175 | I47: =SUM(I44:I46) -> 3746.18 | J47: =SUM(J44:J46) -> 4114.84 | K47: =SUM(K44:K46) -> 3922.03 | L47: =SUM(L44:L46) -> 3287.39 | ... P47: =SUM(P44:P46) -> 3128.3575 | Q47: =SUM(E47:P47) -> 36387.618
A49: Seasonality indices are illustrative planning assumptions for the Indian market (fans and coolers peak in Apr-Jul, heaters and immersion rods in Dec-Feb, kitchen appliances around festivals and weddings). Replace with your own forecast.
A50: Chase strategy: the plan builds what is sold each month, so the Capacity sheet shows where peaks would need a 3rd shift, overtime or off-season pre-build.

Sheet MRP
A1: Material requirements (MRP) - gross kg needed each month
A2: Requirement = production plan (units) x gross kg per unit from BOM_Matrix, summed over all 15 products. Gross includes process yield loss.
A4: RM ID | B4: Raw material | C4: UoM | D4: =Demand_Plan!E$23 -> 46327 | E4: =Demand_Plan!F$23 -> 46357 | F4: =Demand_Plan!G$23 -> 46388 | G4: =Demand_Plan!H$23 -> 46419 | H4: =Demand_Plan!I$23 -> 46447 | I4: =Demand_Plan!J$23 -> 46478 | J4: =Demand_Plan!K$23 -> 46508 | K4: =Demand_Plan!L$23 -> 46539 | ... O4: =Demand_Plan!P$23 -> 46661 | P4: Annual gross (kg) | Q4: Average / month (kg) | R4: Peak month (kg) | S4: Peak month | T4: Annual net (kg) | U4: Process scrap (kg) | V4: Scrap (%)
A5: RW01 | B5: =INDEX(RawMaterials!$B$2:$B$11,MATCH($A5,RawMaterials!$A$2:$A$11,0)) -> CRNGO Electrical Steel Coil | C5: kg | D5: =SUMPRODUCT(Demand_Plan!E$24:E$38,INDEX(BOM_Matrix!$C$26:$L$40,0,MATCH($A5,BOM_Matrix!$C$25:$L$25,0))) -> 88055.714 | E5: =SUMPRODUCT(Demand_Plan!F$24:F$38,INDEX(BOM_Matrix!$C$26:$L$40,0,MATCH($A5,BOM_Matrix!$C$25:$L$25,0))) -> 75161.429 | F5: =SUMPRODUCT(Demand_Plan!G$24:G$38,INDEX(BOM_Matrix!$C$26:$L$40,0,MATCH($A5,BOM_Matrix!$C$25:$L$25,0))) -> 75580.714 | G5: =SUMPRODUCT(Demand_Plan!H$24:H$38,INDEX(BOM_Matrix!$C$26:$L$40,0,MATCH($A5,BOM_Matrix!$C$25:$L$25,0))) -> 102468.57 | H5: =SUMPRODUCT(Demand_Plan!I$24:I$38,INDEX(BOM_Matrix!$C$26:$L$40,0,MATCH($A5,BOM_Matrix!$C$25:$L$25,0))) -> 146130 | I5: =SUMPRODUCT(Demand_Plan!J$24:J$38,INDEX(BOM_Matrix!$C$26:$L$40,0,MATCH($A5,BOM_Matrix!$C$25:$L$25,0))) -> 165567.86 | J5: =SUMPRODUCT(Demand_Plan!K$24:K$38,INDEX(BOM_Matrix!$C$26:$L$40,0,MATCH($A5,BOM_Matrix!$C$25:$L$25,0))) -> 158617.14 | K5: =SUMPRODUCT(Demand_Plan!L$24:L$38,INDEX(BOM_Matrix!$C$26:$L$40,0,MATCH($A5,BOM_Matrix!$C$25:$L$25,0))) -> 131640 | ... O5: =SUMPRODUCT(Demand_Plan!P$24:P$38,INDEX(BOM_Matrix!$C$26:$L$40,0,MATCH($A5,BOM_Matrix!$C$25:$L$25,0))) -> 111312.86 | P5: =SUM(D5:O5) -> 1343847.9 | Q5: =P5/12 -> 111987.32 | R5: =MAX(D5:O5) -> 165567.86 | S5: =INDEX($D$4:$O$4,MATCH(R5,D5:O5,0)) -> 46478 | T5: =SUMPRODUCT(Demand_Plan!$Q$24:$Q$38,INDEX(BOM_Matrix!$C$6:$L$20,0,MATCH($A5,BOM_Matrix!$C$5:$L$5,0))) -> 940693.5 | U5: =P5-T5 -> 403154.36 | V5: =IF(P5=0,0,U5/P5) -> 0.3
A6: RW02 | B6: =INDEX(RawMaterials!$B$2:$B$11,MATCH($A6,RawMaterials!$A$2:$A$11,0)) -> CRCA Steel Sheet / Coil | C6: kg | D6: =SUMPRODUCT(Demand_Plan!E$24:E$38,INDEX(BOM_Matrix!$C$26:$L$40,0,MATCH($A6,BOM_Matrix!$C$25:$L$25,0))) -> 143579.41 | E6: =SUMPRODUCT(Demand_Plan!F$24:F$38,INDEX(BOM_Matrix!$C$26:$L$40,0,MATCH($A6,BOM_Matrix!$C$25:$L$25,0))) -> 130988.24 | F6: =SUMPRODUCT(Demand_Plan!G$24:G$38,INDEX(BOM_Matrix!$C$26:$L$40,0,MATCH($A6,BOM_Matrix!$C$25:$L$25,0))) -> 136250 | G6: =SUMPRODUCT(Demand_Plan!H$24:H$38,INDEX(BOM_Matrix!$C$26:$L$40,0,MATCH($A6,BOM_Matrix!$C$25:$L$25,0))) -> 178255.88 | H6: =SUMPRODUCT(Demand_Plan!I$24:I$38,INDEX(BOM_Matrix!$C$26:$L$40,0,MATCH($A6,BOM_Matrix!$C$25:$L$25,0))) -> 259688.24 | I6: =SUMPRODUCT(Demand_Plan!J$24:J$38,INDEX(BOM_Matrix!$C$26:$L$40,0,MATCH($A6,BOM_Matrix!$C$25:$L$25,0))) -> 298729.41 | J6: =SUMPRODUCT(Demand_Plan!K$24:K$38,INDEX(BOM_Matrix!$C$26:$L$40,0,MATCH($A6,BOM_Matrix!$C$25:$L$25,0))) -> 283573.53 | K6: =SUMPRODUCT(Demand_Plan!L$24:L$38,INDEX(BOM_Matrix!$C$26:$L$40,0,MATCH($A6,BOM_Matrix!$C$25:$L$25,0))) -> 229564.71 | ... O6: =SUMPRODUCT(Demand_Plan!P$24:P$38,INDEX(BOM_Matrix!$C$26:$L$40,0,MATCH($A6,BOM_Matrix!$C$25:$L$25,0))) -> 190794.12 | P6: =SUM(D6:O6) -> 2341005.9 | Q6: =P6/12 -> 195083.82 | R6: =MAX(D6:O6) -> 298729.41 | S6: =INDEX($D$4:$O$4,MATCH(R6,D6:O6,0)) -> 46478 | T6: =SUMPRODUCT(Demand_Plan!$Q$24:$Q$38,INDEX(BOM_Matrix!$C$6:$L$20,0,MATCH($A6,BOM_Matrix!$C$5:$L$5,0))) -> 1989855 | U6: =P6-T6 -> 351150.88 | V6: =IF(P6=0,0,U6/P6) -> 0.15
A7: RW03 | B7: =INDEX(RawMaterials!$B$2:$B$11,MATCH($A7,RawMaterials!$A$2:$A$11,0)) -> Aluminium Alloy Ingot (ADC12) | C7: kg | D7: =SUMPRODUCT(Demand_Plan!E$24:E$38,INDEX(BOM_Matrix!$C$26:$L$40,0,MATCH($A7,BOM_Matrix!$C$25:$L$25,0))) -> 65432.065 | E7: =SUMPRODUCT(Demand_Plan!F$24:F$38,INDEX(BOM_Matrix!$C$26:$L$40,0,MATCH($A7,BOM_Matrix!$C$25:$L$25,0))) -> 57326.087 | F7: =SUMPRODUCT(Demand_Plan!G$24:G$38,INDEX(BOM_Matrix!$C$26:$L$40,0,MATCH($A7,BOM_Matrix!$C$25:$L$25,0))) -> 56304.348 | G7: =SUMPRODUCT(Demand_Plan!H$24:H$38,INDEX(BOM_Matrix!$C$26:$L$40,0,MATCH($A7,BOM_Matrix!$C$25:$L$25,0))) -> 68051.63 | H7: =SUMPRODUCT(Demand_Plan!I$24:I$38,INDEX(BOM_Matrix!$C$26:$L$40,0,MATCH($A7,BOM_Matrix!$C$25:$L$25,0))) -> 87187.5 | I7: =SUMPRODUCT(Demand_Plan!J$24:J$38,INDEX(BOM_Matrix!$C$26:$L$40,0,MATCH($A7,BOM_Matrix!$C$25:$L$25,0))) -> 94377.717 | J7: =SUMPRODUCT(Demand_Plan!K$24:K$38,INDEX(BOM_Matrix!$C$26:$L$40,0,MATCH($A7,BOM_Matrix!$C$25:$L$25,0))) -> 90692.935 | K7: =SUMPRODUCT(Demand_Plan!L$24:L$38,INDEX(BOM_Matrix!$C$26:$L$40,0,MATCH($A7,BOM_Matrix!$C$25:$L$25,0))) -> 78836.957 | ... O7: =SUMPRODUCT(Demand_Plan!P$24:P$38,INDEX(BOM_Matrix!$C$26:$L$40,0,MATCH($A7,BOM_Matrix!$C$25:$L$25,0))) -> 76461.957 | P7: =SUM(D7:O7) -> 866728.26 | Q7: =P7/12 -> 72227.355 | R7: =MAX(D7:O7) -> 94377.717 | S7: =INDEX($D$4:$O$4,MATCH(R7,D7:O7,0)) -> 46478 | T7: =SUMPRODUCT(Demand_Plan!$Q$24:$Q$38,INDEX(BOM_Matrix!$C$6:$L$20,0,MATCH($A7,BOM_Matrix!$C$5:$L$5,0))) -> 797390 | U7: =P7-T7 -> 69338.261 | V7: =IF(P7=0,0,U7/P7) -> 0.08
A8: RW04 | B8: =INDEX(RawMaterials!$B$2:$B$11,MATCH($A8,RawMaterials!$A$2:$A$11,0)) -> Enamelled Copper Winding Wire | C8: kg | D8: =SUMPRODUCT(Demand_Plan!E$24:E$38,INDEX(BOM_Matrix!$C$26:$L$40,0,MATCH($A8,BOM_Matrix!$C$25:$L$25,0))) -> 33067.857 | E8: =SUMPRODUCT(Demand_Plan!F$24:F$38,INDEX(BOM_Matrix!$C$26:$L$40,0,MATCH($A8,BOM_Matrix!$C$25:$L$25,0))) -> 28145.918 | F8: =SUMPRODUCT(Demand_Plan!G$24:G$38,INDEX(BOM_Matrix!$C$26:$L$40,0,MATCH($A8,BOM_Matrix!$C$25:$L$25,0))) -> 28169.898 | G8: =SUMPRODUCT(Demand_Plan!H$24:H$38,INDEX(BOM_Matrix!$C$26:$L$40,0,MATCH($A8,BOM_Matrix!$C$25:$L$25,0))) -> 38010.714 | H8: =SUMPRODUCT(Demand_Plan!I$24:I$38,INDEX(BOM_Matrix!$C$26:$L$40,0,MATCH($A8,BOM_Matrix!$C$25:$L$25,0))) -> 53975.51 | I8: =SUMPRODUCT(Demand_Plan!J$24:J$38,INDEX(BOM_Matrix!$C$26:$L$40,0,MATCH($A8,BOM_Matrix!$C$25:$L$25,0))) -> 60997.449 | J8: =SUMPRODUCT(Demand_Plan!K$24:K$38,INDEX(BOM_Matrix!$C$26:$L$40,0,MATCH($A8,BOM_Matrix!$C$25:$L$25,0))) -> 58379.592 | K8: =SUMPRODUCT(Demand_Plan!L$24:L$38,INDEX(BOM_Matrix!$C$26:$L$40,0,MATCH($A8,BOM_Matrix!$C$25:$L$25,0))) -> 48490.306 | ... O8: =SUMPRODUCT(Demand_Plan!P$24:P$38,INDEX(BOM_Matrix!$C$26:$L$40,0,MATCH($A8,BOM_Matrix!$C$25:$L$25,0))) -> 41800 | P8: =SUM(D8:O8) -> 498758.67 | Q8: =P8/12 -> 41563.223 | R8: =MAX(D8:O8) -> 60997.449 | S8: =INDEX($D$4:$O$4,MATCH(R8,D8:O8,0)) -> 46478 | T8: =SUMPRODUCT(Demand_Plan!$Q$24:$Q$38,INDEX(BOM_Matrix!$C$6:$L$20,0,MATCH($A8,BOM_Matrix!$C$5:$L$5,0))) -> 488783.5 | U8: =P8-T8 -> 9975.1735 | V8: =IF(P8=0,0,U8/P8) -> 0.02
A9: RW05 | B9: =INDEX(RawMaterials!$B$2:$B$11,MATCH($A9,RawMaterials!$A$2:$A$11,0)) -> Polypropylene (PP) Granules | C9: kg | D9: =SUMPRODUCT(Demand_Plan!E$24:E$38,INDEX(BOM_Matrix!$C$26:$L$40,0,MATCH($A9,BOM_Matrix!$C$25:$L$25,0))) -> 36708.247 | E9: =SUMPRODUCT(Demand_Plan!F$24:F$38,INDEX(BOM_Matrix!$C$26:$L$40,0,MATCH($A9,BOM_Matrix!$C$25:$L$25,0))) -> 33863.918 | F9: =SUMPRODUCT(Demand_Plan!G$24:G$38,INDEX(BOM_Matrix!$C$26:$L$40,0,MATCH($A9,BOM_Matrix!$C$25:$L$25,0))) -> 34203.093 | G9: =SUMPRODUCT(Demand_Plan!H$24:H$38,INDEX(BOM_Matrix!$C$26:$L$40,0,MATCH($A9,BOM_Matrix!$C$25:$L$25,0))) -> 49024.742 | H9: =SUMPRODUCT(Demand_Plan!I$24:I$38,INDEX(BOM_Matrix!$C$26:$L$40,0,MATCH($A9,BOM_Matrix!$C$25:$L$25,0))) -> 98089.691 | I9: =SUMPRODUCT(Demand_Plan!J$24:J$38,INDEX(BOM_Matrix!$C$26:$L$40,0,MATCH($A9,BOM_Matrix!$C$25:$L$25,0))) -> 121693.81 | J9: =SUMPRODUCT(Demand_Plan!K$24:K$38,INDEX(BOM_Matrix!$C$26:$L$40,0,MATCH($A9,BOM_Matrix!$C$25:$L$25,0))) -> 111616.49 | K9: =SUMPRODUCT(Demand_Plan!L$24:L$38,INDEX(BOM_Matrix!$C$26:$L$40,0,MATCH($A9,BOM_Matrix!$C$25:$L$25,0))) -> 75470.103 | ... O9: =SUMPRODUCT(Demand_Plan!P$24:P$38,INDEX(BOM_Matrix!$C$26:$L$40,0,MATCH($A9,BOM_Matrix!$C$25:$L$25,0))) -> 36291.753 | P9: =SUM(D9:O9) -> 719069.07 | Q9: =P9/12 -> 59922.423 | R9: =MAX(D9:O9) -> 121693.81 | S9: =INDEX($D$4:$O$4,MATCH(R9,D9:O9,0)) -> 46478 | T9: =SUMPRODUCT(Demand_Plan!$Q$24:$Q$38,INDEX(BOM_Matrix!$C$6:$L$20,0,MATCH($A9,BOM_Matrix!$C$5:$L$5,0))) -> 697497 | U9: =P9-T9 -> 21572.072 | V9: =IF(P9=0,0,U9/P9) -> 0.03
A10: RW06 | B10: =INDEX(RawMaterials!$B$2:$B$11,MATCH($A10,RawMaterials!$A$2:$A$11,0)) -> ABS Granules | C10: kg | D10: =SUMPRODUCT(Demand_Plan!E$24:E$38,INDEX(BOM_Matrix!$C$26:$L$40,0,MATCH($A10,BOM_Matrix!$C$25:$L$25,0))) -> 65154.639 | E10: =SUMPRODUCT(Demand_Plan!F$24:F$38,INDEX(BOM_Matrix!$C$26:$L$40,0,MATCH($A10,BOM_Matrix!$C$25:$L$25,0))) -> 60634.021 | F10: =SUMPRODUCT(Demand_Plan!G$24:G$38,INDEX(BOM_Matrix!$C$26:$L$40,0,MATCH($A10,BOM_Matrix!$C$25:$L$25,0))) -> 57726.804 | G10: =SUMPRODUCT(Demand_Plan!H$24:H$38,INDEX(BOM_Matrix!$C$26:$L$40,0,MATCH($A10,BOM_Matrix!$C$25:$L$25,0))) -> 58350.515 | H10: =SUMPRODUCT(Demand_Plan!I$24:I$38,INDEX(BOM_Matrix!$C$26:$L$40,0,MATCH($A10,BOM_Matrix!$C$25:$L$25,0))) -> 61072.165 | I10: =SUMPRODUCT(Demand_Plan!J$24:J$38,INDEX(BOM_Matrix!$C$26:$L$40,0,MATCH($A10,BOM_Matrix!$C$25:$L$25,0))) -> 60417.526 | J10: =SUMPRODUCT(Demand_Plan!K$24:K$38,INDEX(BOM_Matrix!$C$26:$L$40,0,MATCH($A10,BOM_Matrix!$C$25:$L$25,0))) -> 58128.866 | K10: =SUMPRODUCT(Demand_Plan!L$24:L$38,INDEX(BOM_Matrix!$C$26:$L$40,0,MATCH($A10,BOM_Matrix!$C$25:$L$25,0))) -> 52953.608 | ... O10: =SUMPRODUCT(Demand_Plan!P$24:P$38,INDEX(BOM_Matrix!$C$26:$L$40,0,MATCH($A10,BOM_Matrix!$C$25:$L$25,0))) -> 64458.763 | P10: =SUM(D10:O10) -> 687845.36 | Q10: =P10/12 -> 57320.447 | R10: =MAX(D10:O10) -> 65154.639 | S10: =INDEX($D$4:$O$4,MATCH(R10,D10:O10,0)) -> 46327 | T10: =SUMPRODUCT(Demand_Plan!$Q$24:$Q$38,INDEX(BOM_Matrix!$C$6:$L$20,0,MATCH($A10,BOM_Matrix!$C$5:$L$5,0))) -> 667210 | U10: =P10-T10 -> 20635.361 | V10: =IF(P10=0,0,U10/P10) -> 0.03
A11: RW07 | B11: =INDEX(RawMaterials!$B$2:$B$11,MATCH($A11,RawMaterials!$A$2:$A$11,0)) -> Stainless Steel 304 Sheet | C11: kg | D11: =SUMPRODUCT(Demand_Plan!E$24:E$38,INDEX(BOM_Matrix!$C$26:$L$40,0,MATCH($A11,BOM_Matrix!$C$25:$L$25,0))) -> 53246.341 | E11: =SUMPRODUCT(Demand_Plan!F$24:F$38,INDEX(BOM_Matrix!$C$26:$L$40,0,MATCH($A11,BOM_Matrix!$C$25:$L$25,0))) -> 49503.659 | F11: =SUMPRODUCT(Demand_Plan!G$24:G$38,INDEX(BOM_Matrix!$C$26:$L$40,0,MATCH($A11,BOM_Matrix!$C$25:$L$25,0))) -> 45453.659 | G11: =SUMPRODUCT(Demand_Plan!H$24:H$38,INDEX(BOM_Matrix!$C$26:$L$40,0,MATCH($A11,BOM_Matrix!$C$25:$L$25,0))) -> 43474.39 | H11: =SUMPRODUCT(Demand_Plan!I$24:I$38,INDEX(BOM_Matrix!$C$26:$L$40,0,MATCH($A11,BOM_Matrix!$C$25:$L$25,0))) -> 37459.756 | I11: =SUMPRODUCT(Demand_Plan!J$24:J$38,INDEX(BOM_Matrix!$C$26:$L$40,0,MATCH($A11,BOM_Matrix!$C$25:$L$25,0))) -> 32418.293 | J11: =SUMPRODUCT(Demand_Plan!K$24:K$38,INDEX(BOM_Matrix!$C$26:$L$40,0,MATCH($A11,BOM_Matrix!$C$25:$L$25,0))) -> 31778.049 | K11: =SUMPRODUCT(Demand_Plan!L$24:L$38,INDEX(BOM_Matrix!$C$26:$L$40,0,MATCH($A11,BOM_Matrix!$C$25:$L$25,0))) -> 32202.439 | ... O11: =SUMPRODUCT(Demand_Plan!P$24:P$38,INDEX(BOM_Matrix!$C$26:$L$40,0,MATCH($A11,BOM_Matrix!$C$25:$L$25,0))) -> 52076.829 | P11: =SUM(D11:O11) -> 484721.95 | Q11: =P11/12 -> 40393.496 | R11: =MAX(D11:O11) -> 53246.341 | S11: =INDEX($D$4:$O$4,MATCH(R11,D11:O11,0)) -> 46327 | T11: =SUMPRODUCT(Demand_Plan!$Q$24:$Q$38,INDEX(BOM_Matrix!$C$6:$L$20,0,MATCH($A11,BOM_Matrix!$C$5:$L$5,0))) -> 397472 | U11: =P11-T11 -> 87249.951 | V11: =IF(P11=0,0,U11/P11) -> 0.18
A12: RW08 | B12: =INDEX(RawMaterials!$B$2:$B$11,MATCH($A12,RawMaterials!$A$2:$A$11,0)) -> Nichrome Resistance Wire (Ni80/Cr20) | C12: kg | D12: =SUMPRODUCT(Demand_Plan!E$24:E$38,INDEX(BOM_Matrix!$C$26:$L$40,0,MATCH($A12,BOM_Matrix!$C$25:$L$25,0))) -> 2833.3333 | E12: =SUMPRODUCT(Demand_Plan!F$24:F$38,INDEX(BOM_Matrix!$C$26:$L$40,0,MATCH($A12,BOM_Matrix!$C$25:$L$25,0))) -> 3351.0417 | F12: =SUMPRODUCT(Demand_Plan!G$24:G$38,INDEX(BOM_Matrix!$C$26:$L$40,0,MATCH($A12,BOM_Matrix!$C$25:$L$25,0))) -> 3388.0208 | G12: =SUMPRODUCT(Demand_Plan!H$24:H$38,INDEX(BOM_Matrix!$C$26:$L$40,0,MATCH($A12,BOM_Matrix!$C$25:$L$25,0))) -> 2396.875 | H12: =SUMPRODUCT(Demand_Plan!I$24:I$38,INDEX(BOM_Matrix!$C$26:$L$40,0,MATCH($A12,BOM_Matrix!$C$25:$L$25,0))) -> 1417.1875 | I12: =SUMPRODUCT(Demand_Plan!J$24:J$38,INDEX(BOM_Matrix!$C$26:$L$40,0,MATCH($A12,BOM_Matrix!$C$25:$L$25,0))) -> 995.83333 | J12: =SUMPRODUCT(Demand_Plan!K$24:K$38,INDEX(BOM_Matrix!$C$26:$L$40,0,MATCH($A12,BOM_Matrix!$C$25:$L$25,0))) -> 900.52083 | K12: =SUMPRODUCT(Demand_Plan!L$24:L$38,INDEX(BOM_Matrix!$C$26:$L$40,0,MATCH($A12,BOM_Matrix!$C$25:$L$25,0))) -> 949.47917 | ... O12: =SUMPRODUCT(Demand_Plan!P$24:P$38,INDEX(BOM_Matrix!$C$26:$L$40,0,MATCH($A12,BOM_Matrix!$C$25:$L$25,0))) -> 2254.1667 | P12: =SUM(D12:O12) -> 22040.104 | Q12: =P12/12 -> 1836.6753 | R12: =MAX(D12:O12) -> 3388.0208 | S12: =INDEX($D$4:$O$4,MATCH(R12,D12:O12,0)) -> 46388 | T12: =SUMPRODUCT(Demand_Plan!$Q$24:$Q$38,INDEX(BOM_Matrix!$C$6:$L$20,0,MATCH($A12,BOM_Matrix!$C$5:$L$5,0))) -> 21158.5 | U12: =P12-T12 -> 881.60417 | V12: =IF(P12=0,0,U12/P12) -> 0.04
A13: RW09 | B13: =INDEX(RawMaterials!$B$2:$B$11,MATCH($A13,RawMaterials!$A$2:$A$11,0)) -> Powder Coating (Epoxy-Polyester) | C13: kg | D13: =SUMPRODUCT(Demand_Plan!E$24:E$38,INDEX(BOM_Matrix!$C$26:$L$40,0,MATCH($A13,BOM_Matrix!$C$25:$L$25,0))) -> 5364.375 | E13: =SUMPRODUCT(Demand_Plan!F$24:F$38,INDEX(BOM_Matrix!$C$26:$L$40,0,MATCH($A13,BOM_Matrix!$C$25:$L$25,0))) -> 4932.5 | F13: =SUMPRODUCT(Demand_Plan!G$24:G$38,INDEX(BOM_Matrix!$C$26:$L$40,0,MATCH($A13,BOM_Matrix!$C$25:$L$25,0))) -> 5217.5 | G13: =SUMPRODUCT(Demand_Plan!H$24:H$38,INDEX(BOM_Matrix!$C$26:$L$40,0,MATCH($A13,BOM_Matrix!$C$25:$L$25,0))) -> 6928.75 | H13: =SUMPRODUCT(Demand_Plan!I$24:I$38,INDEX(BOM_Matrix!$C$26:$L$40,0,MATCH($A13,BOM_Matrix!$C$25:$L$25,0))) -> 10214.375 | I13: =SUMPRODUCT(Demand_Plan!J$24:J$38,INDEX(BOM_Matrix!$C$26:$L$40,0,MATCH($A13,BOM_Matrix!$C$25:$L$25,0))) -> 11820 | J13: =SUMPRODUCT(Demand_Plan!K$24:K$38,INDEX(BOM_Matrix!$C$26:$L$40,0,MATCH($A13,BOM_Matrix!$C$25:$L$25,0))) -> 11226.25 | K13: =SUMPRODUCT(Demand_Plan!L$24:L$38,INDEX(BOM_Matrix!$C$26:$L$40,0,MATCH($A13,BOM_Matrix!$C$25:$L$25,0))) -> 9080.625 | ... O13: =SUMPRODUCT(Demand_Plan!P$24:P$38,INDEX(BOM_Matrix!$C$26:$L$40,0,MATCH($A13,BOM_Matrix!$C$25:$L$25,0))) -> 7298.125 | P13: =SUM(D13:O13) -> 91086.25 | Q13: =P13/12 -> 7590.5208 | R13: =MAX(D13:O13) -> 11820 | S13: =INDEX($D$4:$O$4,MATCH(R13,D13:O13,0)) -> 46478 | T13: =SUMPRODUCT(Demand_Plan!$Q$24:$Q$38,INDEX(BOM_Matrix!$C$6:$L$20,0,MATCH($A13,BOM_Matrix!$C$5:$L$5,0))) -> 72869 | U13: =P13-T13 -> 18217.25 | V13: =IF(P13=0,0,U13/P13) -> 0.2
A14: RW10 | B14: =INDEX(RawMaterials!$B$2:$B$11,MATCH($A14,RawMaterials!$A$2:$A$11,0)) -> Corrugated Board / Cartons | C14: kg | D14: =SUMPRODUCT(Demand_Plan!E$24:E$38,INDEX(BOM_Matrix!$C$26:$L$40,0,MATCH($A14,BOM_Matrix!$C$25:$L$25,0))) -> 110371.13 | E14: =SUMPRODUCT(Demand_Plan!F$24:F$38,INDEX(BOM_Matrix!$C$26:$L$40,0,MATCH($A14,BOM_Matrix!$C$25:$L$25,0))) -> 102332.47 | F14: =SUMPRODUCT(Demand_Plan!G$24:G$38,INDEX(BOM_Matrix!$C$26:$L$40,0,MATCH($A14,BOM_Matrix!$C$25:$L$25,0))) -> 102064.43 | G14: =SUMPRODUCT(Demand_Plan!H$24:H$38,INDEX(BOM_Matrix!$C$26:$L$40,0,MATCH($A14,BOM_Matrix!$C$25:$L$25,0))) -> 120175.26 | H14: =SUMPRODUCT(Demand_Plan!I$24:I$38,INDEX(BOM_Matrix!$C$26:$L$40,0,MATCH($A14,BOM_Matrix!$C$25:$L$25,0))) -> 161811.86 | I14: =SUMPRODUCT(Demand_Plan!J$24:J$38,INDEX(BOM_Matrix!$C$26:$L$40,0,MATCH($A14,BOM_Matrix!$C$25:$L$25,0))) -> 179737.11 | J14: =SUMPRODUCT(Demand_Plan!K$24:K$38,INDEX(BOM_Matrix!$C$26:$L$40,0,MATCH($A14,BOM_Matrix!$C$25:$L$25,0))) -> 170012.89 | K14: =SUMPRODUCT(Demand_Plan!L$24:L$38,INDEX(BOM_Matrix!$C$26:$L$40,0,MATCH($A14,BOM_Matrix!$C$25:$L$25,0))) -> 139059.28 | ... O14: =SUMPRODUCT(Demand_Plan!P$24:P$38,INDEX(BOM_Matrix!$C$26:$L$40,0,MATCH($A14,BOM_Matrix!$C$25:$L$25,0))) -> 126427.84 | P14: =SUM(D14:O14) -> 1529471.6 | Q14: =P14/12 -> 127455.97 | R14: =MAX(D14:O14) -> 179737.11 | S14: =INDEX($D$4:$O$4,MATCH(R14,D14:O14,0)) -> 46478 | T14: =SUMPRODUCT(Demand_Plan!$Q$24:$Q$38,INDEX(BOM_Matrix!$C$6:$L$20,0,MATCH($A14,BOM_Matrix!$C$5:$L$5,0))) -> 1483587.5 | U14: =P14-T14 -> 45884.149 | V14: =IF(P14=0,0,U14/P14) -> 0.03
A15: Total | B15: all materials (kg) | D15: =SUM(D5:D14) -> 603813.12 | E15: =SUM(E5:E14) -> 546239.28 | F15: =SUM(F5:F14) -> 544358.47 | G15: =SUM(G5:G14) -> 667137.33 | H15: =SUM(H5:H14) -> 917046.28 | I15: =SUM(I5:I14) -> 1026755 | J15: =SUM(J5:J14) -> 974926.27 | K15: =SUM(K5:K14) -> 798247.5 | ... Q15: =SUM(Q5:Q14) -> 715381.26 | T15: =SUM(T5:T14) -> 7556516 | U15: =SUM(U5:U14) -> 1028059.1 | V15: =IF(P15=0,0,U15/P15) -> 0.11975655
A17: Monthly purchase value of the requirement at standard price (₹ lakh)
A18: RM ID | B18: Raw material | C18: Std price (₹ / kg) | D18: =D$4 -> 46327 | E18: =E$4 -> 46357 | F18: =F$4 -> 46388 | G18: =G$4 -> 46419 | H18: =H$4 -> 46447 | I18: =I$4 -> 46478 | J18: =J$4 -> 46508 | K18: =K$4 -> 46539 | ... O18: =O$4 -> 46661 | P18: Annual (₹ lakh)
A19: =A5 -> RW01 | B19: =B5 -> CRNGO Electrical Steel Coil | C19: =INDEX(RawMaterials!$G$2:$G$11,MATCH($A19,RawMaterials!$A$2:$A$11,0)) -> 93.4 | D19: =D5*$C19/Assumptions!$B$20 -> 82.244037 | E19: =E5*$C19/Assumptions!$B$20 -> 70.200774 | F19: =F5*$C19/Assumptions!$B$20 -> 70.592387 | G19: =G5*$C19/Assumptions!$B$20 -> 95.705646 | H19: =H5*$C19/Assumptions!$B$20 -> 136.48542 | I19: =I5*$C19/Assumptions!$B$20 -> 154.64038 | J19: =J5*$C19/Assumptions!$B$20 -> 148.14841 | K19: =K5*$C19/Assumptions!$B$20 -> 122.95176 | ... O19: =O5*$C19/Assumptions!$B$20 -> 103.96621 | P19: =SUM(D19:O19) -> 1255.1539
A20: =A6 -> RW02 | B20: =B6 -> CRCA Steel Sheet / Coil | C20: =INDEX(RawMaterials!$G$2:$G$11,MATCH($A20,RawMaterials!$A$2:$A$11,0)) -> 66.65 | D20: =D6*$C20/Assumptions!$B$20 -> 95.695678 | E20: =E6*$C20/Assumptions!$B$20 -> 87.303659 | F20: =F6*$C20/Assumptions!$B$20 -> 90.810625 | G20: =G6*$C20/Assumptions!$B$20 -> 118.80755 | H20: =H6*$C20/Assumptions!$B$20 -> 173.08221 | I20: =I6*$C20/Assumptions!$B$20 -> 199.10315 | J20: =J6*$C20/Assumptions!$B$20 -> 189.00176 | K20: =K6*$C20/Assumptions!$B$20 -> 153.00488 | ... O20: =O6*$C20/Assumptions!$B$20 -> 127.16428 | P20: =SUM(D20:O20) -> 1560.2804
A21: =A7 -> RW03 | B21: =B7 -> Aluminium Alloy Ingot (ADC12) | C21: =INDEX(RawMaterials!$G$2:$G$11,MATCH($A21,RawMaterials!$A$2:$A$11,0)) -> 261.5 | D21: =D7*$C21/Assumptions!$B$20 -> 171.10485 | E21: =E7*$C21/Assumptions!$B$20 -> 149.90772 | F21: =F7*$C21/Assumptions!$B$20 -> 147.23587 | G21: =G7*$C21/Assumptions!$B$20 -> 177.95501 | H21: =H7*$C21/Assumptions!$B$20 -> 227.99531 | I21: =I7*$C21/Assumptions!$B$20 -> 246.79773 | J21: =J7*$C21/Assumptions!$B$20 -> 237.16202 | K21: =K7*$C21/Assumptions!$B$20 -> 206.15864 | ... O21: =O7*$C21/Assumptions!$B$20 -> 199.94802 | P21: =SUM(D21:O21) -> 2266.4944
A22: =A8 -> RW04 | B22: =B8 -> Enamelled Copper Winding Wire | C22: =INDEX(RawMaterials!$G$2:$G$11,MATCH($A22,RawMaterials!$A$2:$A$11,0)) -> 1336.25 | D22: =D8*$C22/Assumptions!$B$20 -> 441.86924 | E22: =E8*$C22/Assumptions!$B$20 -> 376.09983 | F22: =F8*$C22/Assumptions!$B$20 -> 376.42026 | G22: =G8*$C22/Assumptions!$B$20 -> 507.91817 | H22: =H8*$C22/Assumptions!$B$20 -> 721.24776 | I22: =I8*$C22/Assumptions!$B$20 -> 815.07841 | J22: =J8*$C22/Assumptions!$B$20 -> 780.0973 | K22: =K8*$C22/Assumptions!$B$20 -> 647.95172 | ... O22: =O8*$C22/Assumptions!$B$20 -> 558.5525 | P22: =SUM(D22:O22) -> 6664.6628
A23: =A9 -> RW05 | B23: =B9 -> Polypropylene (PP) Granules | C23: =INDEX(RawMaterials!$G$2:$G$11,MATCH($A23,RawMaterials!$A$2:$A$11,0)) -> 107 | D23: =D9*$C23/Assumptions!$B$20 -> 39.277825 | E23: =E9*$C23/Assumptions!$B$20 -> 36.234392 | F23: =F9*$C23/Assumptions!$B$20 -> 36.597309 | G23: =G9*$C23/Assumptions!$B$20 -> 52.456474 | H23: =H9*$C23/Assumptions!$B$20 -> 104.95597 | I23: =I9*$C23/Assumptions!$B$20 -> 130.21238 | J23: =J9*$C23/Assumptions!$B$20 -> 119.42965 | K23: =K9*$C23/Assumptions!$B$20 -> 80.75301 | ... O23: =O9*$C23/Assumptions!$B$20 -> 38.832175 | P23: =SUM(D23:O23) -> 769.40391
A24: =A10 -> RW06 | B24: =B10 -> ABS Granules | C24: =INDEX(RawMaterials!$G$2:$G$11,MATCH($A24,RawMaterials!$A$2:$A$11,0)) -> 156 | D24: =D10*$C24/Assumptions!$B$20 -> 101.64124 | E24: =E10*$C24/Assumptions!$B$20 -> 94.589072 | F24: =F10*$C24/Assumptions!$B$20 -> 90.053814 | G24: =G10*$C24/Assumptions!$B$20 -> 91.026804 | H24: =H10*$C24/Assumptions!$B$20 -> 95.272577 | I24: =I10*$C24/Assumptions!$B$20 -> 94.25134 | J24: =J10*$C24/Assumptions!$B$20 -> 90.681031 | K24: =K10*$C24/Assumptions!$B$20 -> 82.607629 | ... O24: =O10*$C24/Assumptions!$B$20 -> 100.55567 | P24: =SUM(D24:O24) -> 1073.0388
A25: =A11 -> RW07 | B25: =B11 -> Stainless Steel 304 Sheet | C25: =INDEX(RawMaterials!$G$2:$G$11,MATCH($A25,RawMaterials!$A$2:$A$11,0)) -> 206.5 | D25: =D11*$C25/Assumptions!$B$20 -> 109.9537 | E25: =E11*$C25/Assumptions!$B$20 -> 102.22505 | F25: =F11*$C25/Assumptions!$B$20 -> 93.861805 | G25: =G11*$C25/Assumptions!$B$20 -> 89.774616 | H25: =H11*$C25/Assumptions!$B$20 -> 77.354396 | I25: =I11*$C25/Assumptions!$B$20 -> 66.943774 | J25: =J11*$C25/Assumptions!$B$20 -> 65.621671 | K25: =K11*$C25/Assumptions!$B$20 -> 66.498037 | ... O25: =O11*$C25/Assumptions!$B$20 -> 107.53865 | P25: =SUM(D25:O25) -> 1000.9508
A26: =A12 -> RW08 | B26: =B12 -> Nichrome Resistance Wire (Ni80/Cr20) | C26: =INDEX(RawMaterials!$G$2:$G$11,MATCH($A26,RawMaterials!$A$2:$A$11,0)) -> 2080 | D26: =D12*$C26/Assumptions!$B$20 -> 58.933333 | E26: =E12*$C26/Assumptions!$B$20 -> 69.701667 | F26: =F12*$C26/Assumptions!$B$20 -> 70.470833 | G26: =G12*$C26/Assumptions!$B$20 -> 49.855 | H26: =H12*$C26/Assumptions!$B$20 -> 29.4775 | I26: =I12*$C26/Assumptions!$B$20 -> 20.713333 | J26: =J12*$C26/Assumptions!$B$20 -> 18.730833 | K26: =K12*$C26/Assumptions!$B$20 -> 19.749167 | ... O26: =O12*$C26/Assumptions!$B$20 -> 46.886667 | P26: =SUM(D26:O26) -> 458.43417
A27: =A13 -> RW09 | B27: =B13 -> Powder Coating (Epoxy-Polyester) | C27: =INDEX(RawMaterials!$G$2:$G$11,MATCH($A27,RawMaterials!$A$2:$A$11,0)) -> 345 | D27: =D13*$C27/Assumptions!$B$20 -> 18.507094 | E27: =E13*$C27/Assumptions!$B$20 -> 17.017125 | F27: =F13*$C27/Assumptions!$B$20 -> 18.000375 | G27: =G13*$C27/Assumptions!$B$20 -> 23.904187 | H27: =H13*$C27/Assumptions!$B$20 -> 35.239594 | I27: =I13*$C27/Assumptions!$B$20 -> 40.779 | J27: =J13*$C27/Assumptions!$B$20 -> 38.730562 | K27: =K13*$C27/Assumptions!$B$20 -> 31.328156 | ... O27: =O13*$C27/Assumptions!$B$20 -> 25.178531 | P27: =SUM(D27:O27) -> 314.24756
A28: =A14 -> RW10 | B28: =B14 -> Corrugated Board / Cartons | C28: =INDEX(RawMaterials!$G$2:$G$11,MATCH($A28,RawMaterials!$A$2:$A$11,0)) -> 52 | D28: =D14*$C28/Assumptions!$B$20 -> 57.39299 | E28: =E14*$C28/Assumptions!$B$20 -> 53.212887 | F28: =F14*$C28/Assumptions!$B$20 -> 53.073505 | G28: =G14*$C28/Assumptions!$B$20 -> 62.491134 | H28: =H14*$C28/Assumptions!$B$20 -> 84.142165 | I28: =I14*$C28/Assumptions!$B$20 -> 93.463299 | J28: =J14*$C28/Assumptions!$B$20 -> 88.406701 | K28: =K14*$C28/Assumptions!$B$20 -> 72.310825 | ... O28: =O14*$C28/Assumptions!$B$20 -> 65.742474 | P28: =SUM(D28:O28) -> 795.32526
A29: Total | D29: =SUM(D19:D28) -> 1176.62 | E29: =SUM(E19:E28) -> 1056.4922 | F29: =SUM(F19:F28) -> 1047.1168 | G29: =SUM(G19:G28) -> 1269.8946 | H29: =SUM(H19:H28) -> 1685.2529 | I29: =SUM(I19:I28) -> 1861.9828 | J29: =SUM(J19:J28) -> 1776.0099 | K29: =SUM(K19:K28) -> 1483.3138 | ... P29: =SUM(P19:P28) -> 16157.992
A31: Requirement is for production only (no sales of raw material). Net = kg that ends up in the product; scrap = gross - net (trimmings, runners, cut-offs); much of it is recoverable (steel, aluminium and plastic scrap is re-melted or re-ground and sold), which this model does not credit.
A32: Use the monthly figures to time purchase orders against each source's lead time on Sourcing; the Inventory sheet turns the next-3-month usage into reorder points.

Sheet Capacity
A1: Capacity - load vs available hours by work centre
A2: Load hours = production plan x routing minutes / 60. Utilization = load / effective capacity (after OEE). Red = overload, amber = tight.
A3: A. Load (hours per month)
A4: WC ID | B4: Work centre | C4: Units | D4: Effective capacity (h / month) | E4: =Demand_Plan!E$23 -> 46327 | F4: =Demand_Plan!F$23 -> 46357 | G4: =Demand_Plan!G$23 -> 46388 | H4: =Demand_Plan!H$23 -> 46419 | I4: =Demand_Plan!I$23 -> 46447 | J4: =Demand_Plan!J$23 -> 46478 | K4: =Demand_Plan!K$23 -> 46508 | L4: =Demand_Plan!L$23 -> 46539 | ... P4: =Demand_Plan!P$23 -> 46661 | Q4: Average load (h) | R4: Peak load (h)
A5: WC01 | B5: =INDEX(WorkCentres!$B$2:$B$10,MATCH($A5,WorkCentres!$A$2:$A$10,0)) -> Press Shop | C5: =INDEX(WorkCentres!$G$2:$G$10,MATCH($A5,WorkCentres!$A$2:$A$10,0)) -> 21 | D5: =INDEX(WorkCentres!$M$2:$M$10,MATCH($A5,WorkCentres!$A$2:$A$10,0)) -> 6988.8 | E5: =SUMPRODUCT(Demand_Plan!E$24:E$38,INDEX(Routing!$C$6:$K$20,0,MATCH($A5,Routing!$C$4:$K$4,0)))/60 -> 4335.1333 | F5: =SUMPRODUCT(Demand_Plan!F$24:F$38,INDEX(Routing!$C$6:$K$20,0,MATCH($A5,Routing!$C$4:$K$4,0)))/60 -> 3977.0167 | G5: =SUMPRODUCT(Demand_Plan!G$24:G$38,INDEX(Routing!$C$6:$K$20,0,MATCH($A5,Routing!$C$4:$K$4,0)))/60 -> 3972.675 | H5: =SUMPRODUCT(Demand_Plan!H$24:H$38,INDEX(Routing!$C$6:$K$20,0,MATCH($A5,Routing!$C$4:$K$4,0)))/60 -> 4730.8083 | I5: =SUMPRODUCT(Demand_Plan!I$24:I$38,INDEX(Routing!$C$6:$K$20,0,MATCH($A5,Routing!$C$4:$K$4,0)))/60 -> 6150.1167 | J5: =SUMPRODUCT(Demand_Plan!J$24:J$38,INDEX(Routing!$C$6:$K$20,0,MATCH($A5,Routing!$C$4:$K$4,0)))/60 -> 6760.875 | K5: =SUMPRODUCT(Demand_Plan!K$24:K$38,INDEX(Routing!$C$6:$K$20,0,MATCH($A5,Routing!$C$4:$K$4,0)))/60 -> 6449.7333 | L5: =SUMPRODUCT(Demand_Plan!L$24:L$38,INDEX(Routing!$C$6:$K$20,0,MATCH($A5,Routing!$C$4:$K$4,0)))/60 -> 5419.6 | ... P5: =SUMPRODUCT(Demand_Plan!P$24:P$38,INDEX(Routing!$C$6:$K$20,0,MATCH($A5,Routing!$C$4:$K$4,0)))/60 -> 5167.175 | Q5: =AVERAGE(E5:P5) -> 4965.5583 | R5: =MAX(E5:P5) -> 6760.875
A6: WC02 | B6: =INDEX(WorkCentres!$B$2:$B$10,MATCH($A6,WorkCentres!$A$2:$A$10,0)) -> Aluminium Die-Casting & Machining | C6: =INDEX(WorkCentres!$G$2:$G$10,MATCH($A6,WorkCentres!$A$2:$A$10,0)) -> 7 | D6: =INDEX(WorkCentres!$M$2:$M$10,MATCH($A6,WorkCentres!$A$2:$A$10,0)) -> 3276 | E6: =SUMPRODUCT(Demand_Plan!E$24:E$38,INDEX(Routing!$C$6:$K$20,0,MATCH($A6,Routing!$C$4:$K$4,0)))/60 -> 2272.7583 | F6: =SUMPRODUCT(Demand_Plan!F$24:F$38,INDEX(Routing!$C$6:$K$20,0,MATCH($A6,Routing!$C$4:$K$4,0)))/60 -> 2007.4417 | G6: =SUMPRODUCT(Demand_Plan!G$24:G$38,INDEX(Routing!$C$6:$K$20,0,MATCH($A6,Routing!$C$4:$K$4,0)))/60 -> 1971.1333 | H6: =SUMPRODUCT(Demand_Plan!H$24:H$38,INDEX(Routing!$C$6:$K$20,0,MATCH($A6,Routing!$C$4:$K$4,0)))/60 -> 2351.8083 | I6: =SUMPRODUCT(Demand_Plan!I$24:I$38,INDEX(Routing!$C$6:$K$20,0,MATCH($A6,Routing!$C$4:$K$4,0)))/60 -> 2995.8333 | J6: =SUMPRODUCT(Demand_Plan!J$24:J$38,INDEX(Routing!$C$6:$K$20,0,MATCH($A6,Routing!$C$4:$K$4,0)))/60 -> 3238.4333 | K6: =SUMPRODUCT(Demand_Plan!K$24:K$38,INDEX(Routing!$C$6:$K$20,0,MATCH($A6,Routing!$C$4:$K$4,0)))/60 -> 3108.6333 | L6: =SUMPRODUCT(Demand_Plan!L$24:L$38,INDEX(Routing!$C$6:$K$20,0,MATCH($A6,Routing!$C$4:$K$4,0)))/60 -> 2694.7917 | ... P6: =SUMPRODUCT(Demand_Plan!P$24:P$38,INDEX(Routing!$C$6:$K$20,0,MATCH($A6,Routing!$C$4:$K$4,0)))/60 -> 2624.5 | Q6: =AVERAGE(E6:P6) -> 2486.8403 | R6: =MAX(E6:P6) -> 3238.4333
